Workbook

Sheet NY不動産(総計)
A1: 総計 | B1: 2024 | C1: 45412 | D1: 45443 | E1: 45473 | F1: 45504 | G1: 2025 | H1: 45535 | I1: 45565 | J1: 45596 | K1: 45626 | L1: 45657 | M1: 45688 | N1: 45716 | O1: 45747 | P1: 45777 | Q1: 45808 | R1: 45838 | S1: 45869 | T1: 2026 | U1: 45900 | V1: 45930 | W1: 45961 | X1: 45991 | Y1: 46022 | Z1: 46053 | AA1: 46081 | AB1: 46112 | AC1: 46142 | AD1: 46173 | AE1: 46203 | AF1: 46234
A2: 取得簿価(円) | B2: =B3*150 -> 4049634000
A3: 取得簿価(ドル) | B3: =SUM('1Wall#831:248-250W102nd'!B3) -> 26997560
A4: 賃料収入(円) | B4: =SUM(B6*B5) -> 25541112 | C4: =SUM(C6*C5) -> 0 | D4: =SUM(D6*D5) -> 103473.48 | E4: =SUM(E6*E5) -> 729647.1 | F4: =SUM(F6*F5) -> 1864640 | H4: =SUM(H6*H5) -> 2156131.4 | I4: =SUM(I6*I5) -> 3158809 | J4: =SUM(J6*J5) -> 3858278.4 | K4: =SUM(K6*K5) -> 4643609 | L4: =SUM(L6*L5) -> 6271974.6 | M4: =SUM(M6*M5) -> 8600148 | N4: =SUM(N6*N5) -> 10893807 | O4: =SUM(O6*O5) -> 9594219.9 | ... S4: =SUM(S6*S5) -> 19852788 | U4: =SUM(U6*U5) -> 19973369 | V4: =SUM(V6*V5) -> 20026065 | W4: =SUM(W6*W5) -> 24261207 | X4: =SUM(X6*X5) -> 25523643 | Y4: =SUM(Y6*Y5) -> 24479747 | Z4: =SUM(Z6*Z5) -> 24411990 | AA4: =SUM(AA6*AA5) -> 25966651 | AB4: =SUM(AB6*AB5) -> 25381773 | ... AF4: =SUM(AF6*AF5) -> 0
A5: 為替レート(ドル円)TTM | B5: 150 | C5: 156.9 | D5: 156.74 | E5: 161.07 | F5: 152.44 | H5: 144.8 | I5: 142.73 | J5: 153.64 | K5: 150.74 | L5: 158.18 | M5: 154.43 | N5: 149.67 | O5: 149.52 | P5: 142.57 | Q5: 143.87 | R5: 144.81 | S5: 149.39 | U5: 146.92 | V5: 148.88 | W5: 154.1 | X5: 156.63 | Y5: 156.56 | Z5: 153.66 | AA5: 155.81 | AB5: 159.88 | AC5: 160.39 | AG5: ※月末TTMベース
A6: 賃料収入(ドル) | B6: =SUM('1Wall#831:248-250W102nd'!B6) -> 170274.08 | C6: =SUM('1Wall#831:248-250W102nd'!C6) -> 0 | D6: =SUM('1Wall#831:248-250W102nd'!D6) -> 660.16 | E6: =SUM('1Wall#831:248-250W102nd'!E6) -> 4530 | F6: =SUM('1Wall#831:248-250W102nd'!F6) -> 12231.96 | H6: =SUM('1Wall#831:248-250W102nd'!H6) -> 14890.41 | I6: =SUM('1Wall#831:248-250W102nd'!I6) -> 22131.36 | J6: =SUM('1Wall#831:248-250W102nd'!J6) -> 25112.46 | K6: =SUM('1Wall#831:248-250W102nd'!K6) -> 30805.42 | L6: =SUM('1Wall#831:248-250W102nd'!L6) -> 39650.87 | M6: =SUM('1Wall#831:248-250W102nd'!M6) -> 55689.62 | N6: =SUM('1Wall#831:248-250W102nd'!N6) -> 72785.51 | O6: =SUM('1Wall#831:248-250W102nd'!O6) -> 64166.8 | ... S6: =SUM('1Wall#831:248-250W102nd'!S6) -> 132892.35 | U6: =SUM('1Wall#831:248-250W102nd'!U6) -> 135947.24 | V6: =SUM('1Wall#831:248-250W102nd'!V6) -> 134511.45 | W6: =SUM('1Wall#831:248-250W102nd'!W6) -> 157438.07 | X6: =SUM('1Wall#831:248-250W102nd'!X6) -> 162955.01 | Y6: =SUM('1Wall#831:248-250W102nd'!Y6) -> 156360.16 | Z6: =SUM('1Wall#831:248-250W102nd'!Z6) -> 158870.17 | AA6: =SUM('1Wall#831:248-250W102nd'!AA6) -> 166655.87 | AB6: =SUM('1Wall#831:248-250W102nd'!AB6) -> 158755.15 | ... AF6: =SUM('1Wall#831:248-250W102nd'!AF6) -> 0
A7: 減価償却費(円) | B7: =SUM('1Wall#831:248-250W102nd'!B7) -> 3059113726 | C7: =SUM('1Wall#831:248-250W102nd'!C7) -> 3668273 | D7: =SUM('1Wall#831:248-250W102nd'!D7) -> 4938140 | E7: =SUM('1Wall#831:248-250W102nd'!E7) -> 4938140 | F7: =SUM('1Wall#831:248-250W102nd'!F7) -> 6177180 | H7: =SUM('1Wall#831:248-250W102nd'!H7) -> 6177172 | I7: =SUM('1Wall#831:248-250W102nd'!I7) -> 8862692 | J7: =SUM('1Wall#831:248-250W102nd'!J7) -> 8862692 | K7: =SUM('1Wall#831:248-250W102nd'!K7) -> 10536573 | L7: =SUM('1Wall#831:248-250W102nd'!L7) -> 11807263 | M7: =SUM('1Wall#831:248-250W102nd'!M7) -> 28855758 | N7: =SUM('1Wall#831:248-250W102nd'!N7) -> 28855724 | O7: =SUM('1Wall#831:248-250W102nd'!O7) -> 28855724 | ... S7: =SUM('1Wall#831:248-250W102nd'!S7) -> 40483129 | U7: =SUM('1Wall#831:248-250W102nd'!U7) -> 46486085 | V7: =SUM('1Wall#831:248-250W102nd'!V7) -> 46486085 | W7: =SUM('1Wall#831:248-250W102nd'!W7) -> 48253271 | X7: =SUM('1Wall#831:248-250W102nd'!X7) -> 48253271 | Y7: =SUM('1Wall#831:248-250W102nd'!Y7) -> 48253271 | Z7: =SUM('1Wall#831:248-250W102nd'!Z7) -> 48253325 | AA7: =SUM('1Wall#831:248-250W102nd'!AA7) -> 48253271 | AB7: =SUM('1Wall#831:248-250W102nd'!AB7) -> 48253271 | ... AF7: =SUM('1Wall#831:248-250W102nd'!AF7) -> 48253335
A8: 減価償却費(ドル)
A9: 残存簿価(円) | B9: =SUM('1Wall#831:248-250W102nd'!B9) -> 3056520279 | C9: =SUM('1Wall#831:248-250W102nd'!C9) -> 386767709 | D9: =SUM('1Wall#831:248-250W102nd'!D9) -> 517886837 | E9: =SUM('1Wall#831:248-250W102nd'!E9) -> 512948697 | F9: =SUM('1Wall#831:248-250W102nd'!F9) -> 639525030 | H9: =SUM('1Wall#831:248-250W102nd'!H9) -> 633347858 | I9: =SUM('1Wall#831:248-250W102nd'!I9) -> 912219591 | J9: =SUM('1Wall#831:248-250W102nd'!J9) -> 903356899 | K9: =SUM('1Wall#831:248-250W102nd'!K9) -> 1072164906 | L9: =SUM('1Wall#831:248-250W102nd'!L9) -> 1196503072 | M9: =SUM('1Wall#831:248-250W102nd'!M9) -> 1985973482 | N9: =SUM('1Wall#831:248-250W102nd'!N9) -> 1957117758 | O9: =SUM('1Wall#831:248-250W102nd'!O9) -> 1928262034 | ... S9: =SUM('1Wall#831:248-250W102nd'!S9) -> 3147295398 | U9: =SUM('1Wall#831:248-250W102nd'!U9) -> 3100809313 | V9: =SUM('1Wall#831:248-250W102nd'!V9) -> 3181306658 | W9: =SUM('1Wall#831:248-250W102nd'!W9) -> 3133053387 | X9: =SUM('1Wall#831:248-250W102nd'!X9) -> 3084800116 | Y9: =SUM('1Wall#831:248-250W102nd'!Y9) -> 3036546845 | Z9: =SUM('1Wall#831:248-250W102nd'!Z9) -> 2988293520 | AA9: =SUM('1Wall#831:248-250W102nd'!AA9) -> 2940040249 | AB9: =SUM('1Wall#831:248-250W102nd'!AB9) -> 2891786978 | ... AF9: =SUM('1Wall#831:248-250W102nd'!AF9) -> 2698773830
A10: 残存簿価(ドル)
A11: 管理費(ドル) | C11: =SUM('1Wall#831:248-250W102nd'!C11) -> 1263.27 | D11: =SUM('1Wall#831:248-250W102nd'!D11) -> 300 | E11: =SUM('1Wall#831:248-250W102nd'!E11) -> 300 | F11: =SUM('1Wall#831:248-250W102nd'!F11) -> 1228 | H11: =SUM('1Wall#831:248-250W102nd'!H11) -> 6944 | I11: =SUM('1Wall#831:248-250W102nd'!I11) -> 8024.5 | J11: =SUM('1Wall#831:248-250W102nd'!J11) -> 3140.45 | K11: =SUM('1Wall#831:248-250W102nd'!K11) -> 14560.22 | L11: =SUM('1Wall#831:248-250W102nd'!L11) -> 3080.66 | M11: =SUM('1Wall#831:248-250W102nd'!M11) -> 3949.2 | N11: =SUM('1Wall#831:248-250W102nd'!N11) -> 4685.5 | O11: =SUM('1Wall#831:248-250W102nd'!O11) -> 4487.5 | ... S11: =SUM('1Wall#831:248-250W102nd'!S11) -> 7972.87 | U11: =SUM('1Wall#831:248-250W102nd'!U11) -> 8011.55 | V11: =SUM('1Wall#831:248-250W102nd'!V11) -> 7939.96 | W11: =SUM('1Wall#831:248-250W102nd'!W11) -> 9416.4 | X11: =SUM('1Wall#831:248-250W102nd'!X11) -> 9401.96 | Y11: =SUM('1Wall#831:248-250W102nd'!Y11) -> 7783.89 | Z11: =SUM('1Wall#831:248-250W102nd'!Z11) -> 9363.12 | AA11: =SUM('1Wall#831:248-250W102nd'!AA11) -> 9482.16 | AB11: =SUM('1Wall#831:248-250W102nd'!AB11) -> 9705.87 | ... AF11: =SUM('1Wall#831:248-250W102nd'!AF11) -> 0
A12: 諸経費(税金、募集経費等)(ドル) | B12: =SUM('1Wall#831:248-250W102nd'!B12) -> 933135.06 | C12: =SUM('1Wall#831:248-250W102nd'!C12) -> 2980.36 | D12: =SUM('1Wall#831:248-250W102nd'!D12) -> 15580.58 | E12: =SUM('1Wall#831:248-250W102nd'!E12) -> 10500.52 | F12: =SUM('1Wall#831:248-250W102nd'!F12) -> 11039.94 | H12: =SUM('1Wall#831:248-250W102nd'!H12) -> 13185.91 | I12: =SUM('1Wall#831:248-250W102nd'!I12) -> 52022.08 | J12: =SUM('1Wall#831:248-250W102nd'!J12) -> 19726.18 | K12: =SUM('1Wall#831:248-250W102nd'!K12) -> 15135.99 | L12: =SUM('1Wall#831:248-250W102nd'!L12) -> 36335.8 | M12: =SUM('1Wall#831:248-250W102nd'!M12) -> 15063.16 | N12: =SUM('1Wall#831:248-250W102nd'!N12) -> 25078.89 | O12: =SUM('1Wall#831:248-250W102nd'!O12) -> 32325.54 | ... S12: =SUM('1Wall#831:248-250W102nd'!S12) -> 157874.59 | U12: =SUM('1Wall#831:248-250W102nd'!U12) -> 54594.46 | V12: =SUM('1Wall#831:248-250W102nd'!V12) -> 69155.82 | W12: =SUM('1Wall#831:248-250W102nd'!W12) -> 72882.19 | X12: =SUM('1Wall#831:248-250W102nd'!X12) -> 39175.31 | Y12: =SUM('1Wall#831:248-250W102nd'!Y12) -> 48187.08 | Z12: =SUM('1Wall#831:248-250W102nd'!Z12) -> 54711.57 | AA12: =SUM('1Wall#831:248-250W102nd'!AA12) -> 46105.46 | AB12: =SUM('1Wall#831:248-250W102nd'!AB12) -> 57886.17 | ... AF12: =SUM('1Wall#831:248-250W102nd'!AF12) -> 0
A13: ネット賃貸収入利回り(円)
A14: ネット賃貸収入利回り(ドル)
A15: 取得時簿価利回り(円)
A16: 取得時簿価利回り(ドル)
A17: 残存簿価利回り(円)
A18: 残存簿価利回り(ドル)
A19: CF(円) | C19: =SUM(C5*C20) -> -665825.55 | D19: =SUM(D5*D20) -> -2385648.6 | E19: =SUM(E5*E20) -> -1009992.7 | F19: =SUM(F5*F20) -> -5484.7912 | G19: =SUM(C19:F19) -> -4066951.6 | H19: =SUM(H5*H20) -> -758679.6 | I19: =SUM(I5*I20) -> -5411639.4 | J19: =SUM(J5*J20) -> 345049.32 | K19: =SUM(K5*K20) -> 167202.32 | L19: =SUM(L5*L20) -> 37078.974 | M19: =SUM(M5*M20) -> 5664069.3 | N19: =SUM(N5*N20) -> 6438971 | O19: =SUM(O5*O20) -> 4089934.2 | ... S19: =SUM(S5*S20) -> -4923163.9 | T19: =SUM(G19:S19) -> 5608030.4 | U19: =SUM(U5*U20) -> 10775294 | V19: =SUM(V5*V20) -> 8548044.9 | W19: =SUM(W5*W20) -> 11578994 | X19: =SUM(X5*X20) -> 17914985 | Y19: =SUM(Y5*Y20) -> 15716932 | Z19: =SUM(Z5*Z20) -> 14566273 | AA19: =SUM(AA5*AA20) -> 17305544 | AB19: =SUM(AB5*AB20) -> 14575158 | ... AF19: =SUM(AF5*AF20) -> 0 | AG19: =SUM(T19:AF19) -> 1.1845867e+08
A20: CF(ドル) | C20: =SUM('1Wall#831:248-250W102nd'!C20) -> -4243.63 | D20: =SUM('1Wall#831:248-250W102nd'!D20) -> -15220.42 | E20: =SUM('1Wall#831:248-250W102nd'!E20) -> -6270.52 | F20: =SUM('1Wall#831:248-250W102nd'!F20) -> -35.98 | G20: =SUM(C20:F20) -> -25770.55 | H20: =SUM('1Wall#831:248-250W102nd'!H20) -> -5239.5 | I20: =SUM('1Wall#831:248-250W102nd'!I20) -> -37915.22 | J20: =SUM('1Wall#831:248-250W102nd'!J20) -> 2245.83 | K20: =SUM('1Wall#831:248-250W102nd'!K20) -> 1109.21 | L20: =SUM('1Wall#831:248-250W102nd'!L20) -> 234.41 | M20: =SUM('1Wall#831:248-250W102nd'!M20) -> 36677.26 | N20: =SUM('1Wall#831:248-250W102nd'!N20) -> 43021.12 | O20: =SUM('1Wall#831:248-250W102nd'!O20) -> 27353.76 | ... S20: =SUM('1Wall#831:248-250W102nd'!S20) -> -32955.11 | T20: =SUM(G20:S20) -> 37700.3 | U20: =SUM('1Wall#831:248-250W102nd'!U20) -> 73341.23 | V20: =SUM('1Wall#831:248-250W102nd'!V20) -> 57415.67 | W20: =SUM('1Wall#831:248-250W102nd'!W20) -> 75139.48 | X20: =SUM('1Wall#831:248-250W102nd'!X20) -> 114377.74 | Y20: =SUM('1Wall#831:248-250W102nd'!Y20) -> 100389.19 | Z20: =SUM('1Wall#831:248-250W102nd'!Z20) -> 94795.48 | AA20: =SUM('1Wall#831:248-250W102nd'!AA20) -> 111068.25 | AB20: =SUM('1Wall#831:248-250W102nd'!AB20) -> 91163.11 | ... AF20: =SUM('1Wall#831:248-250W102nd'!AF20) -> 0 | AG20: =SUM(T20:AF20) -> 770032.03
A21: PL(円)
A22: PL(ドル)
A24: 購入日
A25: 下記表は固都税を各月の諸経費に分散して計上した表です
A26: 総計 | B26: 2024 | C26: 45412 | D26: 45443 | E26: 45473 | F26: 45504 | G26: 2025 | H26: 45535 | I26: 45565 | J26: 45596 | K26: 45626 | L26: 45657 | M26: 45688 | N26: 45716 | O26: 45747 | P26: 45777 | Q26: 45808 | R26: 45838 | S26: 45869 | T26: 2026 | U26: 45900 | V26: 45930 | W26: 45961 | X26: 45991 | Y26: 46022 | Z26: 46053 | AA26: 46081 | AB26: 46112 | AC26: 46142 | AD26: 46173 | AE26: 46203 | AF26: 46234
A27: 取得簿価(円) | B27: =B28*150 -> 4049634000
A28: 取得簿価(ドル) | B28: =SUM('1Wall#831:248-250W102nd'!B28) -> 26997560
A29: 賃料収入(円) | B29: =SUM(B31*B30) -> 11733750 | C29: =SUM(C31*C30) -> 0 | D29: =SUM(D31*D30) -> 103473.48 | E29: =SUM(E31*E30) -> 729647.1 | F29: =SUM(F31*F30) -> 1864640 | H29: =SUM(H31*H30) -> 2156131.4 | I29: =SUM(I31*I30) -> 3158809 | J29: =SUM(J31*J30) -> 3858278.4 | K29: =SUM(K31*K30) -> 4643609 | L29: =SUM(L31*L30) -> 6271974.6 | M29: =SUM(M31*M30) -> 8600148 | N29: =SUM(N31*N30) -> 10893807 | O29: =SUM(O31*O30) -> 9594219.9 | ... S29: =SUM(S31*S30) -> 19852788 | U29: =SUM(U31*U30) -> 19973369 | V29: =SUM(V31*V30) -> 20026065 | W29: =SUM(W31*W30) -> 24261207 | X29: =SUM(X31*X30) -> 25523643 | Y29: =SUM(Y31*Y30) -> 24479747 | Z29: =SUM(Z31*Z30) -> 24411990 | AA29: =SUM(AA31*AA30) -> 25966651 | AB29: =SUM(AB31*AB30) -> 23994076 | ... AF29: =SUM(AF31*AF30) -> 0
A30: 為替レート(ドル円)TTM | B30: 150 | C30: 156.9 | D30: 156.74 | E30: 161.07 | F30: 152.44 | H30: 144.8 | I30: 142.73 | J30: 153.64 | K30: 150.74 | L30: 158.18 | M30: 154.43 | N30: 149.67 | O30: 149.52 | P30: 142.57 | Q30: 143.87 | R30: 144.81 | S30: 149.39 | U30: 146.92 | V30: 148.88 | W30: 154.1 | X30: 156.63 | Y30: 156.56 | Z30: 153.66 | AA30: 155.81 | AB30: 159.88 | AC30: 160.39 | AG30: ※月末TTMベース
A31: 賃料収入(ドル) | B31: =SUM('1Wall#831:248-250W102nd'!B31) -> 78225 | C31: =SUM('1Wall#831:248-250W102nd'!C31) -> 0 | D31: =SUM('1Wall#831:248-250W102nd'!D31) -> 660.16 | E31: =SUM('1Wall#831:248-250W102nd'!E31) -> 4530 | F31: =SUM('1Wall#831:248-250W102nd'!F31) -> 12231.96 | H31: =SUM('1Wall#831:248-250W102nd'!H31) -> 14890.41 | I31: =SUM('1Wall#831:248-250W102nd'!I31) -> 22131.36 | J31: =SUM('1Wall#831:248-250W102nd'!J31) -> 25112.46 | K31: =SUM('1Wall#831:248-250W102nd'!K31) -> 30805.42 | L31: =SUM('1Wall#831:248-250W102nd'!L31) -> 39650.87 | M31: =SUM('1Wall#831:248-250W102nd'!M31) -> 55689.62 | N31: =SUM('1Wall#831:248-250W102nd'!N31) -> 72785.51 | O31: =SUM('1Wall#831:248-250W102nd'!O31) -> 64166.8 | ... S31: =SUM('1Wall#831:248-250W102nd'!S31) -> 132892.35 | U31: =SUM('1Wall#831:248-250W102nd'!U31) -> 135947.24 | V31: =SUM('1Wall#831:248-250W102nd'!V31) -> 134511.45 | W31: =SUM('1Wall#831:248-250W102nd'!W31) -> 157438.07 | X31: =SUM('1Wall#831:248-250W102nd'!X31) -> 162955.01 | Y31: =SUM('1Wall#831:248-250W102nd'!Y31) -> 156360.16 | Z31: =SUM('1Wall#831:248-250W102nd'!Z31) -> 158870.17 | AA31: =SUM('1Wall#831:248-250W102nd'!AA31) -> 166655.87 | AB31: =SUM('1Wall#831:248-250W102nd'!AB31) -> 150075.53 | ... AF31: =SUM('1Wall#831:248-250W102nd'!AF31) -> 0
A32: 減価償却費(円) | B32: =SUM('1Wall#831:248-250W102nd'!B32) -> 3059113726 | C32: =SUM('1Wall#831:248-250W102nd'!C32) -> 3668273 | D32: =SUM('1Wall#831:248-250W102nd'!D32) -> 4938140 | E32: =SUM('1Wall#831:248-250W102nd'!E32) -> 4938140 | F32: =SUM('1Wall#831:248-250W102nd'!F32) -> 6177180 | H32: =SUM('1Wall#831:248-250W102nd'!H32) -> 6177172 | I32: =SUM('1Wall#831:248-250W102nd'!I32) -> 8862692 | J32: =SUM('1Wall#831:248-250W102nd'!J32) -> 8862692 | K32: =SUM('1Wall#831:248-250W102nd'!K32) -> 10536573 | L32: =SUM('1Wall#831:248-250W102nd'!L32) -> 11807263 | M32: =SUM('1Wall#831:248-250W102nd'!M32) -> 28855758 | N32: =SUM('1Wall#831:248-250W102nd'!N32) -> 28855724 | O32: =SUM('1Wall#831:248-250W102nd'!O32) -> 28855724 | ... S32: =SUM('1Wall#831:248-250W102nd'!S32) -> 40483129 | U32: =SUM('1Wall#831:248-250W102nd'!U32) -> 46486085 | V32: =SUM('1Wall#831:248-250W102nd'!V32) -> 46486085 | W32: =SUM('1Wall#831:248-250W102nd'!W32) -> 46486085 | X32: =SUM('1Wall#831:248-250W102nd'!X32) -> 46486085 | Y32: =SUM('1Wall#831:248-250W102nd'!Y32) -> 46486085 | Z32: =SUM('1Wall#831:248-250W102nd'!Z32) -> 46486139 | AA32: =SUM('1Wall#831:248-250W102nd'!AA32) -> 46486085 | AB32: =SUM('1Wall#831:248-250W102nd'!AB32) -> 46486085 | ... AF32: =SUM('1Wall#831:248-250W102nd'!AF32) -> 46486149
A33: 減価償却費(ドル)
A34: 残存簿価(円) | B34: =SUM('1Wall#831:248-250W102nd'!B34) -> 3056520279 | C34: =SUM('1Wall#831:248-250W102nd'!C34) -> 386767709 | D34: =SUM('1Wall#831:248-250W102nd'!D34) -> 517886837 | E34: =SUM('1Wall#831:248-250W102nd'!E34) -> 512948697 | F34: =SUM('1Wall#831:248-250W102nd'!F34) -> 639525030 | H34: =SUM('1Wall#831:248-250W102nd'!H34) -> 633347858 | I34: =SUM('1Wall#831:248-250W102nd'!I34) -> 912219591 | J34: =SUM('1Wall#831:248-250W102nd'!J34) -> 903356899 | K34: =SUM('1Wall#831:248-250W102nd'!K34) -> 1072164906 | L34: =SUM('1Wall#831:248-250W102nd'!L34) -> 1196503072 | M34: =SUM('1Wall#831:248-250W102nd'!M34) -> 1985973482 | N34: =SUM('1Wall#831:248-250W102nd'!N34) -> 1957117758 | O34: =SUM('1Wall#831:248-250W102nd'!O34) -> 1928262034 | ... S34: =SUM('1Wall#831:248-250W102nd'!S34) -> 3147295398 | U34: =SUM('1Wall#831:248-250W102nd'!U34) -> 3100809313 | V34: =SUM('1Wall#831:248-250W102nd'!V34) -> 3054323228 | W34: =SUM('1Wall#831:248-250W102nd'!W34) -> 3007837143 | X34: =SUM('1Wall#831:248-250W102nd'!X34) -> 2961351058 | Y34: =SUM('1Wall#831:248-250W102nd'!Y34) -> 2914864973 | Z34: =SUM('1Wall#831:248-250W102nd'!Z34) -> 2868378834 | AA34: =SUM('1Wall#831:248-250W102nd'!AA34) -> 2821892749 | AB34: =SUM('1Wall#831:248-250W102nd'!AB34) -> 2775406664 | ... AF34: =SUM('1Wall#831:248-250W102nd'!AF34) -> 2589462260
A35: 残存簿価(ドル)
A36: 管理費(ドル) | C36: =SUM('1Wall#831:248-250W102nd'!C36) -> 1263.27 | D36: =SUM('1Wall#831:248-250W102nd'!D36) -> 300 | E36: =SUM('1Wall#831:248-250W102nd'!E36) -> 300 | F36: =SUM('1Wall#831:248-250W102nd'!F36) -> 1228 | H36: =SUM('1Wall#831:248-250W102nd'!H36) -> 6944 | I36: =SUM('1Wall#831:248-250W102nd'!I36) -> 8024.5 | J36: =SUM('1Wall#831:248-250W102nd'!J36) -> 3140.45 | K36: =SUM('1Wall#831:248-250W102nd'!K36) -> 14560.22 | L36: =SUM('1Wall#831:248-250W102nd'!L36) -> 3080.66 | M36: =SUM('1Wall#831:248-250W102nd'!M36) -> 3949.2 | N36: =SUM('1Wall#831:248-250W102nd'!N36) -> 4685.5 | O36: =SUM('1Wall#831:248-250W102nd'!O36) -> 4487.5 | ... S36: =SUM('1Wall#831:248-250W102nd'!S36) -> 7972.87 | U36: =SUM('1Wall#831:248-250W102nd'!U36) -> 8011.55 | V36: =SUM('1Wall#831:248-250W102nd'!V36) -> 7939.96 | W36: =SUM('1Wall#831:248-250W102nd'!W36) -> 9416.4 | X36: =SUM('1Wall#831:248-250W102nd'!X36) -> 9401.96 | Y36: =SUM('1Wall#831:248-250W102nd'!Y36) -> 7783.89 | Z36: =SUM('1Wall#831:248-250W102nd'!Z36) -> 9363.12 | AA36: =SUM('1Wall#831:248-250W102nd'!AA36) -> 9482.16 | AB36: =SUM('1Wall#831:248-250W102nd'!AB36) -> 8921.87 | ... AF36: =SUM('1Wall#831:248-250W102nd'!AF36) -> 0
A37: 諸経費(税金、募集経費等)(ドル) | C37: =SUM('1Wall#831:248-250W102nd'!C37) -> 2980.36 | D37: =SUM('1Wall#831:248-250W102nd'!D37) -> 15580.58 | E37: =SUM('1Wall#831:248-250W102nd'!E37) -> 7073.44 | F37: =SUM('1Wall#831:248-250W102nd'!F37) -> 12751.98 | H37: =SUM('1Wall#831:248-250W102nd'!H37) -> 14897.95 | I37: =SUM('1Wall#831:248-250W102nd'!I37) -> 11965.04 | J37: =SUM('1Wall#831:248-250W102nd'!J37) -> 19778.43 | K37: =SUM('1Wall#831:248-250W102nd'!K37) -> 22620.56 | L37: =SUM('1Wall#831:248-250W102nd'!L37) -> 28493.85 | M37: =SUM('1Wall#831:248-250W102nd'!M37) -> 21680.71 | N37: =SUM('1Wall#831:248-250W102nd'!N37) -> 34760.48 | O37: =SUM('1Wall#831:248-250W102nd'!O37) -> 36877.95 | ... S37: =SUM('1Wall#831:248-250W102nd'!S37) -> 60431.17 | U37: =SUM('1Wall#831:248-250W102nd'!U37) -> 76664.81 | V37: =SUM('1Wall#831:248-250W102nd'!V37) -> 84221.85 | W37: =SUM('1Wall#831:248-250W102nd'!W37) -> 95828.08 | X37: =SUM('1Wall#831:248-250W102nd'!X37) -> 62121.19 | Y37: =SUM('1Wall#831:248-250W102nd'!Y37) -> 63836.76 | Z37: =SUM('1Wall#831:248-250W102nd'!Z37) -> 79116.69 | AA37: =SUM('1Wall#831:248-250W102nd'!AA37) -> 70510.58 | AB37: =SUM('1Wall#831:248-250W102nd'!AB37) -> 27180.35 | ... AF37: =SUM('1Wall#831:248-250W102nd'!AF37) -> 0
A38: ネット賃貸収入利回り(円)
A39: ネット賃貸収入利回り(ドル)
A40: 取得時簿価利回り(円)
A41: 取得時簿価利回り(ドル)
A42: 残存簿価利回り(円)
A43: 残存簿価利回り(ドル)
A44: CF(円) | C44: =SUM(C30*C45) -> -665825.55 | D44: =SUM(D30*D45) -> -2385648.6 | E44: =SUM(E30*E45) -> -457992.88 | F44: =SUM(F30*F45) -> -266468.17 | G44: =SUM(C44:F44) -> -3775935.2 | H44: =SUM(H30*H45) -> -1006583 | I44: =SUM(I30*I45) -> 305701.97 | J44: =SUM(J30*J45) -> 337021.63 | K44: =SUM(K30*K45) -> -961021.77 | L44: =SUM(L30*L45) -> 1277518.6 | M44: =SUM(M30*M45) -> 4642121 | N44: =SUM(N30*N45) -> 4989927.5 | O44: =SUM(O30*O45) -> 3409257.9 | ... S44: =SUM(S30*S45) -> 9633908.6 | T44: =SUM(G44:S44) -> 39324379 | U44: =SUM(U30*U45) -> 7532717.7 | V44: =SUM(V30*V45) -> 6305014.4 | W44: =SUM(W30*W45) -> 8043032.2 | X44: =SUM(X30*X45) -> 14320972 | Y44: =SUM(Y30*Y45) -> 13266818 | Z44: =SUM(Z30*Z45) -> 10816183 | AA44: =SUM(AA30*AA45) -> 13502982 | AB44: =SUM(AB30*AB45) -> 18222053 | ... AF44: =SUM(AF30*AF45) -> 0 | AG44: =SUM(T44:AF44) -> 1.3007331e+08
A45: CF(ドル) | C45: =SUM('1Wall#831:248-250W102nd'!C45) -> -4243.63 | D45: =SUM('1Wall#831:248-250W102nd'!D45) -> -15220.42 | E45: =SUM('1Wall#831:248-250W102nd'!E45) -> -2843.44 | F45: =SUM('1Wall#831:248-250W102nd'!F45) -> -1748.02 | G45: =SUM(C45:F45) -> -24055.51 | H45: =SUM('1Wall#831:248-250W102nd'!H45) -> -6951.54 | I45: =SUM('1Wall#831:248-250W102nd'!I45) -> 2141.82 | J45: =SUM('1Wall#831:248-250W102nd'!J45) -> 2193.58 | K45: =SUM('1Wall#831:248-250W102nd'!K45) -> -6375.36 | L45: =SUM('1Wall#831:248-250W102nd'!L45) -> 8076.36 | M45: =SUM('1Wall#831:248-250W102nd'!M45) -> 30059.71 | N45: =SUM('1Wall#831:248-250W102nd'!N45) -> 33339.53 | O45: =SUM('1Wall#831:248-250W102nd'!O45) -> 22801.35 | ... S45: =SUM('1Wall#831:248-250W102nd'!S45) -> 64488.31 | T45: =SUM(G45:S45) -> 268040.21 | U45: =SUM('1Wall#831:248-250W102nd'!U45) -> 51270.88 | V45: =SUM('1Wall#831:248-250W102nd'!V45) -> 42349.64 | W45: =SUM('1Wall#831:248-250W102nd'!W45) -> 52193.59 | X45: =SUM('1Wall#831:248-250W102nd'!X45) -> 91431.86 | Y45: =SUM('1Wall#831:248-250W102nd'!Y45) -> 84739.51 | Z45: =SUM('1Wall#831:248-250W102nd'!Z45) -> 70390.36 | AA45: =SUM('1Wall#831:248-250W102nd'!AA45) -> 86663.13 | AB45: =SUM('1Wall#831:248-250W102nd'!AB45) -> 113973.31 | ... AF45: =SUM('1Wall#831:248-250W102nd'!AF45) -> 0 | AG45: =SUM(T45:AF45) -> 822915.77
A46: PL(円)
A47: PL(ドル)

Sheet 1Wall#831
A1: 1 Wall Street #831 | B1: 2024 | C1: 45412 | D1: 45443 | E1: 45473 | F1: 45504 | G1: 2025 | H1: 45535 | I1: 45565 | J1: 45596 | K1: 45626 | L1: 45657 | M1: 45688 | N1: 45716 | O1: 45747 | P1: 45777 | Q1: 45808 | R1: 45838 | S1: 45869 | T1: 2026 | U1: 45900 | V1: 45930 | W1: 45961 | X1: 45991 | Y1: 46022 | Z1: 46053 | AA1: 46081 | AB1: 46112 | AC1: 46142 | AD1: 46173 | AE1: 46203 | AF1: 46234
A2: 取得簿価(円) | B2: =B3*B5 -> 210000000
A3: 取得簿価(ドル) | B3: 1400000
A4: 賃料収入(円) | B4: =B6*B5 -> 975000 | C4: =C5*C6 -> 0 | D4: =D5*D6 -> 0 | E4: =E5*E6 -> 0 | F4: =F5*F6 -> 4573.2 | H4: =H5*H6 -> 0 | I4: =I5*I6 -> 465493.91 | J4: =J5*J6 -> 952568 | K4: =K5*K6 -> 934588 | L4: =L5*L6 -> 980716 | M4: =M5*M6 -> 957466 | N4: =N5*N6 -> 927954 | O4: =O5*O6 -> 927024 | ... S4: =S5*S6 -> 926218 | U4: =U5*U6 -> 718739.99 | V4: =V5*V6 -> 316228.56 | W4: =W5*W6 -> 395170.96 | X4: =X5*X6 -> 1020444.4 | Y4: =Y5*Y6 -> 1017640 | Z4: =Z5*Z6 -> 998790 | AA4: =AA5*AA6 -> 1012765 | AB4: =AB5*AB6 -> 1039220 | ... AF4: =AF5*AF6 -> 0
A5: 為替レート(ドル円)TTM | B5: 150 | C5: ='NY不動産(総計)'!C5 -> 156.9 | D5: ='NY不動産(総計)'!D5 -> 156.74 | E5: ='NY不動産(総計)'!E5 -> 161.07 | F5: ='NY不動産(総計)'!F5 -> 152.44 | H5: ='NY不動産(総計)'!H5 -> 144.8 | I5: ='NY不動産(総計)'!I5 -> 142.73 | J5: ='NY不動産(総計)'!J5 -> 153.64 | K5: ='NY不動産(総計)'!K5 -> 150.74 | L5: ='NY不動産(総計)'!L5 -> 158.18 | M5: ='NY不動産(総計)'!M5 -> 154.43 | N5: ='NY不動産(総計)'!N5 -> 149.67 | O5: ='NY不動産(総計)'!O5 -> 149.52 | ... S5: ='NY不動産(総計)'!S5 -> 149.39 | U5: ='NY不動産(総計)'!U5 -> 146.92 | V5: ='NY不動産(総計)'!V5 -> 148.88 | W5: ='NY不動産(総計)'!W5 -> 154.1 | X5: ='NY不動産(総計)'!X5 -> 156.63 | Y5: ='NY不動産(総計)'!Y5 -> 156.56 | Z5: ='NY不動産(総計)'!Z5 -> 153.66 | AA5: ='NY不動産(総計)'!AA5 -> 155.81 | AB5: ='NY不動産(総計)'!AB5 -> 159.88 | ... AF5: ='NY不動産(総計)'!AF5 -> 0
A6: 賃料収入(ドル) | B6: 6500 | C6: 0 | D6: 0 | E6: 0 | F6: 30 | H6: 0 | I6: 3261.36 | J6: 6200 | K6: 6200 | L6: 6200 | M6: 6200 | N6: 6200 | O6: 6200 | P6: 7549.88 | Q6: 6350.12 | R6: 6200 | S6: 6200 | U6: 4892.05 | V6: 2124.05 | W6: 2564.38 | X6: 6515 | Y6: 6500 | Z6: 6500 | AA6: 6500 | AB6: 6500
A7: 減価償却費(円) | B7: 190636233 | C7: 1779271 | D7: 1779271 | E7: 1779271 | F7: 1779273 | H7: 1779271 | I7: 1779271 | J7: 1779271 | K7: 1779271 | L7: 1779271 | M7: 1779274 | N7: 1779271 | O7: 1779271 | P7: 1779271 | Q7: 1779271 | R7: 1779271 | S7: 1779274 | U7: 1779271 | V7: 1779271 | W7: 1779271 | X7: 1779271 | Y7: 1779271 | Z7: 1779274 | AA7: 1779271 | AB7: 1779271 | AC7: 1779271 | AD7: 1779271 | AE7: 1779271 | AF7: 1779274
A8: 減価償却費(ドル)
A9: 残存簿価(円) | B9: =SUM(B7-C7) -> 188856962 | C9: =B9-C7 -> 187077691 | D9: =C9-D7 -> 185298420 | E9: =D9-E7 -> 183519149 | F9: =E9-F7 -> 181739876 | H9: =F9-H7 -> 179960605 | I9: =H9-I7 -> 178181334 | J9: =I9-J7 -> 176402063 | K9: =J9-K7 -> 174622792 | L9: =K9-L7 -> 172843521 | M9: =L9-M7 -> 171064247 | N9: =M9-N7 -> 169284976 | O9: =N9-O7 -> 167505705 | P9: =O9-P7 -> 165726434 | ... S9: =R9-S7 -> 160388618 | U9: =S9-U7 -> 158609347 | V9: =U9-V7 -> 156830076 | W9: =V9-W7 -> 155050805 | X9: =W9-X7 -> 153271534 | Y9: =X9-Y7 -> 151492263 | Z9: =Y9-Z7 -> 149712989 | AA9: =Z9-AA7 -> 147933718 | AB9: =AA9-AB7 -> 146154447 | AC9: =AB9-AC7 -> 144375176 | ... AF9: =AE9-AF7 -> 139037360
A10: 残存簿価(ドル)
A11: 管理費(ドル) | C11: 600 | D11: 100 | E11: 100 | F11: 100 | H11: 100 | I11: 6696 | J11: 496 | K11: 496 | L11: 496 | M11: 496 | N11: 496 | O11: 496 | P11: 496 | Q11: 496 | R11: 496 | S11: 434 | U11: 434 | V11: 217 | W11: 217 | X11: 455 | Y11: 455 | Z11: 455 | AA11: 455 | AB11: 455 | AG11: =SUM(C11:AF11) -> 15737 | AH11: 管理費
A12: 諸経費(税金、募集経費等)(ドル) | B12: -357.58 | C12: 1177.47 | D12: 4722.81 | E12: 6463.43 | F12: 1357.32 | H12: 2269.82 | I12: 16185.79 | J12: 1327.92 | K12: 1327.82 | L12: 2106.78 | M12: 1327.82 | N12: 2093.94 | O12: 1350.96 | P12: 1349.88 | Q12: 1350.3 | R12: 22239.29 | S12: 1350.31 | U12: 1350.26 | V12: 1350.26 | W12: 12157.45 | X12: 1365.21 | Y12: 1350.21 | Z12: 1363.76 | AA12: 1363.76 | AB12: 2112.71 | AG12: 20067.72 | AH12: コモンチャージ
A13: ネット賃貸収入利回り(円) | AG13: 45276.83 | AH13: 固定資産税
A14: ネット賃貸収入利回り(ドル) | AG14: 2657.11 | AH14: 修繕・雑費・その他支出
A15: 取得時簿価利回り(円) | B15: =B13/B2 -> 0 | AG15: =SUM(AG11:AG14) -> 83738.66 | AH15: 合計
A16: 取得時簿価利回り(ドル)
A17: 残存簿価利回り(円) | B17: =B13/B9 -> 0
A18: 残存簿価利回り(ドル)
A19: CF(円) | C19: =SUM(C5*C20) -> -278885.04 | D19: =SUM(D5*D20) -> -755927.24 | E19: =SUM(E5*E20) -> -1057171.7 | F19: =SUM(F5*F20) -> -217580.66 | H19: =SUM(H5*H20) -> -343149.94 | I19: =SUM(I5*I20) -> -2800424 | J19: =SUM(J5*J20) -> 672340.93 | K19: =SUM(K5*K20) -> 659665.37 | L19: =SUM(L5*L20) -> 569008.26 | M19: =SUM(M5*M20) -> 675813.48 | N19: =SUM(N5*N20) -> 540317.68 | O19: =SUM(O5*O20) -> 650866.54 | ... S19: =SUM(S5*S20) -> 659659.93 | U19: =SUM(U5*U20) -> 456596.51 | V19: =SUM(V5*V20) -> 82894.895 | W19: =SUM(W5*W20) -> -1511731.8 | X19: =SUM(X5*X20) -> 735344.96 | Y19: =SUM(Y5*Y20) -> 735016.32 | Z19: =SUM(Z5*Z20) -> 719319.34 | AA19: =SUM(AA5*AA20) -> 729384 | AB19: =SUM(AB5*AB20) -> 628694.53 | ... AF19: =SUM(AF5*AF20) -> 0
A20: CF(ドル) | C20: =SUM(C6-C11-C12) -> -1777.47 | D20: =SUM(D6-D11-D12) -> -4822.81 | E20: =SUM(E6-E11-E12) -> -6563.43 | F20: =SUM(F6-F11-F12) -> -1427.32 | H20: =SUM(H6-H11-H12) -> -2369.82 | I20: =SUM(I6-I11-I12) -> -19620.43 | J20: =SUM(J6-J11-J12) -> 4376.08 | K20: =SUM(K6-K11-K12) -> 4376.18 | L20: =SUM(L6-L11-L12) -> 3597.22 | M20: =SUM(M6-M11-M12) -> 4376.18 | N20: =SUM(N6-N11-N12) -> 3610.06 | O20: =SUM(O6-O11-O12) -> 4353.04 | ... S20: =SUM(S6-S11-S12) -> 4415.69 | U20: =SUM(U6-U11-U12) -> 3107.79 | V20: =SUM(V6-V11-V12) -> 556.79 | W20: =SUM(W6-W11-W12) -> -9810.07 | X20: =SUM(X6-X11-X12) -> 4694.79 | Y20: =SUM(Y6-Y11-Y12) -> 4694.79 | Z20: =SUM(Z6-Z11-Z12) -> 4681.24 | AA20: =SUM(AA6-AA11-AA12) -> 4681.24 | AB20: =SUM(AB6-AB11-AB12) -> 3932.29 | ... AF20: =SUM(AF6-AF11-AF12) -> 0
A21: PL(円)
A22: PL(ドル)
A23: 更新日 | B23: 46265
A24: 購入日 | B24: 45379
A25: 下記表は固都税を各月の諸経費に分散して計上した表です
A26: 1 Wall Street #831 | B26: 2024 | C26: 45412 | D26: 45443 | E26: 45473 | F26: 45504 | G26: 2025 | H26: 45535 | I26: 45565 | J26: 45596 | K26: 45626 | L26: 45657 | M26: 45688 | N26: 45716 | O26: 45747 | P26: 45777 | Q26: 45808 | R26: 45838 | S26: 45869 | T26: 2026 | U26: 45900 | V26: 45930 | W26: 45961 | X26: 45991 | Y26: 46022 | Z26: 46053 | AA26: 46081 | AB26: 46112 | AC26: 46142 | AD26: 46173 | AE26: 46203 | AF26: 46234
A27: 取得簿価(円) | B27: =B28*B30 -> 210000000
A28: 取得簿価(ドル) | B28: 1400000
A29: 賃料収入(円) | B29: =B31*B30 -> 930000 | C29: =C30*C31 -> 0 | D29: =D30*D31 -> 0 | E29: =E30*E31 -> 0 | F29: =F30*F31 -> 4573.2 | H29: =H30*H31 -> 0 | I29: =I30*I31 -> 465493.91 | J29: =J30*J31 -> 952568 | K29: =K30*K31 -> 934588 | L29: =L30*L31 -> 980716 | M29: =M30*M31 -> 957466 | N29: =N30*N31 -> 927954 | O29: =O30*O31 -> 927024 | ... S29: =S30*S31 -> 926218 | U29: =U30*U31 -> 718739.99 | V29: =V30*V31 -> 316228.56 | W29: =W30*W31 -> 395170.96 | X29: =X30*X31 -> 1020444.4 | Y29: =Y30*Y31 -> 1017640 | Z29: =Z30*Z31 -> 998790 | AA29: =AA30*AA31 -> 1012765 | AB29: =AB30*AB31 -> 1039220 | ... AF29: =AF30*AF31 -> 0
A30: 為替レート(ドル円)TTM | B30: ='NY不動産(総計)'!B30 -> 150 | C30: ='NY不動産(総計)'!C30 -> 156.9 | D30: ='NY不動産(総計)'!D30 -> 156.74 | E30: ='NY不動産(総計)'!E30 -> 161.07 | F30: ='NY不動産(総計)'!F30 -> 152.44 | H30: ='NY不動産(総計)'!H30 -> 144.8 | I30: ='NY不動産(総計)'!I30 -> 142.73 | J30: ='NY不動産(総計)'!J30 -> 153.64 | K30: ='NY不動産(総計)'!K30 -> 150.74 | L30: ='NY不動産(総計)'!L30 -> 158.18 | M30: ='NY不動産(総計)'!M30 -> 154.43 | N30: ='NY不動産(総計)'!N30 -> 149.67 | O30: ='NY不動産(総計)'!O30 -> 149.52 | ... S30: ='NY不動産(総計)'!S30 -> 149.39 | U30: ='NY不動産(総計)'!U30 -> 146.92 | V30: ='NY不動産(総計)'!V30 -> 148.88 | W30: ='NY不動産(総計)'!W30 -> 154.1 | X30: ='NY不動産(総計)'!X30 -> 156.63 | Y30: ='NY不動産(総計)'!Y30 -> 156.56 | Z30: ='NY不動産(総計)'!Z30 -> 153.66 | AA30: ='NY不動産(総計)'!AA30 -> 155.81 | AB30: ='NY不動産(総計)'!AB30 -> 159.88 | ... AF30: ='NY不動産(総計)'!AF30 -> 0
A31: 賃料収入(ドル) | B31: 6200 | C31: 0 | D31: 0 | E31: 0 | F31: 30 | H31: 0 | I31: 3261.36 | J31: 6200 | K31: 6200 | L31: 6200 | M31: 6200 | N31: 6200 | O31: 6200 | P31: 7549.88 | Q31: 6350.12 | R31: 6200 | S31: 6200 | U31: 4892.05 | V31: 2124.05 | W31: 2564.38 | X31: 6515 | Y31: 6500 | Z31: 6500 | AA31: 6500 | AB31: 6500
A32: 減価償却費(円) | B32: 190636233 | C32: 1779271 | D32: 1779271 | E32: 1779271 | F32: 1779273 | H32: 1779271 | I32: 1779271 | J32: 1779271 | K32: 1779271 | L32: 1779271 | M32: 1779274 | N32: 1779271 | O32: 1779271 | P32: 1779271 | Q32: 1779271 | R32: 1779271 | S32: 1779274 | U32: 1779271 | V32: 1779271 | W32: 1779271 | X32: 1779271 | Y32: 1779271 | Z32: 1779274 | AA32: 1779271 | AB32: 1779271 | AC32: 1779271 | AD32: 1779271 | AE32: 1779271 | AF32: 1779274
A33: 減価償却費(ドル)
A34: 残存簿価(円) | B34: =SUM(B32-C32) -> 188856962 | C34: =B34-C32 -> 187077691 | D34: =C34-D32 -> 185298420 | E34: =D34-E32 -> 183519149 | F34: =E34-F32 -> 181739876 | H34: =F34-H32 -> 179960605 | I34: =H34-I32 -> 178181334 | J34: =I34-J32 -> 176402063 | K34: =J34-K32 -> 174622792 | L34: =K34-L32 -> 172843521 | M34: =L34-M32 -> 171064247 | N34: =M34-N32 -> 169284976 | O34: =N34-O32 -> 167505705 | P34: =O34-P32 -> 165726434 | ... S34: =R34-S32 -> 160388618 | U34: =S34-U32 -> 158609347 | V34: =U34-V32 -> 156830076 | W34: =V34-W32 -> 155050805 | X34: =W34-X32 -> 153271534 | Y34: =X34-Y32 -> 151492263 | Z34: =Y34-Z32 -> 149712989 | AA34: =Z34-AA32 -> 147933718 | AB34: =AA34-AB32 -> 146154447 | AC34: =AB34-AC32 -> 144375176 | ... AF34: =AE34-AF32 -> 139037360
A35: 残存簿価(ドル)
A36: 管理費(ドル) | C36: 600 | D36: 100 | E36: 100 | F36: 100 | H36: 100 | I36: 6696 | J36: 496 | K36: 496 | L36: 496 | M36: 496 | N36: 496 | O36: 496 | P36: 496 | Q36: 496 | R36: 496 | S36: 434 | U36: 434 | V36: 217 | W36: 217 | X36: 455 | Y36: 455 | Z36: 455 | AA36: 455 | AB36: 455
A37: 諸経費(税金、募集経費等)(ドル) | B37: -357.58 | C37: 1177.47 | D37: 4722.81 | E37: 3039.35 | F37: 3069.36 | H37: 3981.86 | I37: 2978.75 | J37: 2978.8 | K37: 2978.7 | L37: 3757.66 | M37: 2978.7 | N37: 3744.82 | O37: 3001.84 | P37: 3000.76 | Q37: 3001.18 | R37: 3091.05 | S37: 3091.05 | U37: 3091.01 | V37: 3091.01 | W37: 13898.2 | X37: 3105.96 | Y37: 3090.96 | Z37: 3104.51 | AA37: 3104.51 | AB37: 1740.75 | AC37: 1740.75 | AD37: 1740.75
A38: ネット賃貸収入利回り(円)
A39: ネット賃貸収入利回り(ドル)
A40: 取得時簿価利回り(円) | B40: =B38/B27 -> 0
A41: 取得時簿価利回り(ドル)
A42: 残存簿価利回り(円) | B42: =B38/B34 -> 0
A43: 残存簿価利回り(ドル)
A44: CF(円) | C44: =SUM(C30*C45) -> -278885.04 | D44: =SUM(D30*D45) -> -755927.24 | E44: =SUM(E30*E45) -> -505655.1 | F44: =SUM(F30*F45) -> -478564.04 | H44: =SUM(H30*H45) -> -591053.33 | I44: =SUM(I30*I45) -> -915383.15 | J44: =SUM(J30*J45) -> 418699.73 | K44: =SUM(K30*K45) -> 410811.72 | L44: =SUM(L30*L45) -> 307872.06 | M44: =SUM(M30*M45) -> 420868.08 | N44: =SUM(N30*N45) -> 293230.47 | O44: =SUM(O30*O45) -> 404026.96 | ... S44: =SUM(S30*S45) -> 399610.78 | U44: =SUM(U30*U45) -> 200845.52 | V44: =SUM(V30*V45) -> -176267.96 | W44: =SUM(W30*W45) -> -1779981.4 | X44: =SUM(X30*X45) -> 462691.29 | Y44: =SUM(Y30*Y45) -> 462484.5 | Z44: =SUM(Z30*Z45) -> 451835.69 | AA44: =SUM(AA30*AA45) -> 458157.75 | AB44: =SUM(AB30*AB45) -> 688163.49 | ... AF44: =SUM(AF30*AF45) -> 0
A45: CF(ドル) | C45: =SUM(C31-C36-C37) -> -1777.47 | D45: =SUM(D31-D36-D37) -> -4822.81 | E45: =SUM(E31-E36-E37) -> -3139.35 | F45: =SUM(F31-F36-F37) -> -3139.36 | H45: =SUM(H31-H36-H37) -> -4081.86 | I45: =SUM(I31-I36-I37) -> -6413.39 | J45: =SUM(J31-J36-J37) -> 2725.2 | K45: =SUM(K31-K36-K37) -> 2725.3 | L45: =SUM(L31-L36-L37) -> 1946.34 | M45: =SUM(M31-M36-M37) -> 2725.3 | N45: =SUM(N31-N36-N37) -> 1959.18 | O45: =SUM(O31-O36-O37) -> 2702.16 | ... S45: =SUM(S31-S36-S37) -> 2674.95 | U45: =SUM(U31-U36-U37) -> 1367.04 | V45: =SUM(V31-V36-V37) -> -1183.96 | W45: =SUM(W31-W36-W37) -> -11550.82 | X45: =SUM(X31-X36-X37) -> 2954.04 | Y45: =SUM(Y31-Y36-Y37) -> 2954.04 | Z45: =SUM(Z31-Z36-Z37) -> 2940.49 | AA45: =SUM(AA31-AA36-AA37) -> 2940.49 | AB45: =SUM(AB31-AB36-AB37) -> 4304.25 | ... AF45: =SUM(AF31-AF36-AF37) -> 0
A46: PL(円)
A47: PL(ドル)
R52: 20888.98
R53: 1740.74
R54: 1740.74
R55: 1740.75
R56: 1740.75
R57: 1740.75
R58: 1740.75
R59: 1740.75
R60: 1740.75
R61: 1740.75
R62: 1740.75
R63: 1740.75
R64: 1740.75
R65: =SUM(R53:R64) -> 20888.98

Sheet 111W56th#34D
A1: 111 West 56th #34D | B1: 2024 | C1: 45412 | D1: 45443 | E1: 45473 | F1: 45504 | G1: 2025 | H1: 45535 | I1: 45565 | J1: 45596 | K1: 45626 | L1: 45657 | M1: 45688 | N1: 45716 | O1: 45747 | P1: 45777 | Q1: 45808 | R1: 45838 | S1: 45869 | T1: 2026 | U1: 45900 | V1: 45930 | W1: 45961 | X1: 45991 | Y1: 46022 | Z1: 46053 | AA1: 46081 | AB1: 46112 | AC1: 46142 | AD1: 46173 | AE1: 46203 | AF1: 46234
A2: 取得簿価(円) | B2: =B3*150 -> 168750000
A3: 取得簿価(ドル) | B3: 1125000
A4: 賃料収入(円) | B4: =B6*B5 -> 900000 | C4: =C5*C6 -> 0 | D4: =D5*D6 -> 2351.1 | E4: =E5*E6 -> 4832.1 | F4: =F5*F6 -> 4573.2 | H4: =H5*H6 -> 273731.37 | I4: =I5*I6 -> 820697.5 | J4: =J5*J6 -> 883430 | K4: =K5*K6 -> 866755 | L4: =L5*L6 -> 909535 | M4: =M5*M6 -> 895267.77 | N4: =N5*N6 -> 878812.85 | O4: =O5*O6 -> 870209.39 | ... S4: =S5*S6 -> 867736.3 | U4: =U5*U6 -> 250686.66 | V4: =V5*V6 -> 13988.765 | W4: =W5*W6 -> 925740.34 | X4: =X5*X6 -> 939780 | Y4: =Y5*Y6 -> 939360 | Z4: =Z5*Z6 -> 925666.28 | AA4: =AA5*AA6 -> 938668 | AB4: =AB5*AB6 -> 964476.1 | ... AF4: =AF5*AF6 -> 0
A5: 為替レート(ドル円)TTM | B5: 150 | C5: ='NY不動産(総計)'!C5 -> 156.9 | D5: ='NY不動産(総計)'!D5 -> 156.74 | E5: ='NY不動産(総計)'!E5 -> 161.07 | F5: ='NY不動産(総計)'!F5 -> 152.44 | H5: ='NY不動産(総計)'!H5 -> 144.8 | I5: ='NY不動産(総計)'!I5 -> 142.73 | J5: ='NY不動産(総計)'!J5 -> 153.64 | K5: ='NY不動産(総計)'!K5 -> 150.74 | L5: ='NY不動産(総計)'!L5 -> 158.18 | M5: ='NY不動産(総計)'!M5 -> 154.43 | N5: ='NY不動産(総計)'!N5 -> 149.67 | O5: ='NY不動産(総計)'!O5 -> 149.52 | ... S5: ='NY不動産(総計)'!S5 -> 149.39 | U5: ='NY不動産(総計)'!U5 -> 146.92 | V5: ='NY不動産(総計)'!V5 -> 148.88 | W5: ='NY不動産(総計)'!W5 -> 154.1 | X5: ='NY不動産(総計)'!X5 -> 156.63 | Y5: ='NY不動産(総計)'!Y5 -> 156.56 | Z5: ='NY不動産(総計)'!Z5 -> 153.66 | AA5: ='NY不動産(総計)'!AA5 -> 155.81 | AB5: ='NY不動産(総計)'!AB5 -> 159.88 | ... AF5: ='NY不動産(総計)'!AF5 -> 0
A6: 賃料収入(ドル) | B6: 6000 | C6: 0 | D6: 15 | E6: 30 | F6: 30 | H6: 1890.41 | I6: 5750 | J6: 5750 | K6: 5750 | L6: 5750 | M6: 5797.24 | N6: 5871.67 | O6: 5820.02 | P6: 5813.94 | Q6: 5849.56 | R6: 5837.73 | S6: 5808.53 | U6: 1706.28 | V6: 93.96 | W6: 6007.4 | X6: 6000 | Y6: 6000 | Z6: 6024.12 | AA6: 6024.44 | AB6: 6032.5
A7: 減価償却費(円) | B7: 87233222 | C7: 814176 | D7: 814176 | E7: 814176 | F7: 814179 | H7: 814176 | I7: 814176 | J7: 814176 | K7: 814176 | L7: 814176 | M7: 814180 | N7: 814176 | O7: 814176 | P7: 814176 | Q7: 814176 | R7: 814176 | S7: 814180 | U7: 814176 | V7: 814176 | W7: 814176 | X7: 814176 | Y7: 814176 | Z7: 814180 | AA7: 814176 | AB7: 814176 | AC7: 814176 | AD7: 814176 | AE7: 814176 | AF7: 814180
A8: 減価償却費(ドル)
A9: 残存簿価(円) | B9: =SUM(B7-C7) -> 86419046 | C9: =SUM(B9-C7) -> 85604870 | D9: =SUM(C9-D7) -> 84790694 | E9: =SUM(D9-E7) -> 83976518 | F9: =SUM(E9-F7) -> 83162339 | H9: =SUM(F9-H7) -> 82348163 | I9: =SUM(H9-I7) -> 81533987 | J9: =SUM(I9-J7) -> 80719811 | K9: =SUM(J9-K7) -> 79905635 | L9: =SUM(K9-L7) -> 79091459 | M9: =SUM(L9-M7) -> 78277279 | N9: =SUM(M9-N7) -> 77463103 | O9: =SUM(N9-O7) -> 76648927 | P9: =SUM(O9-P7) -> 75834751 | ... S9: =SUM(R9-S7) -> 73392219 | U9: =SUM(S9-U7) -> 72578043 | V9: =SUM(U9-V7) -> 71763867 | W9: =SUM(V9-W7) -> 70949691 | X9: =SUM(W9-X7) -> 70135515 | Y9: =SUM(X9-Y7) -> 69321339 | Z9: =SUM(Y9-Z7) -> 68507159 | AA9: =SUM(Z9-AA7) -> 67692983 | AB9: =SUM(AA9-AB7) -> 66878807 | AC9: =SUM(AB9-AC7) -> 66064631 | ... AF9: =SUM(AE9-AF7) -> 63622099
A10: 残存簿価(ドル)
A11: 管理費(ドル) | C11: 600 | D11: 100 | E11: 100 | F11: 100 | H11: 5980 | I11: 460 | J11: 460 | K11: 460 | L11: 460 | M11: 460 | N11: 460 | O11: 460 | P11: 460 | Q11: 460 | R11: 460 | S11: 402.5 | U11: 201.25 | V11: 201.25 | W11: 420 | X11: 420 | Y11: 420 | Z11: 420 | AA11: 420 | AB11: 420 | AG11: =SUM(C11:AF11) -> 14805 | AH11: 管理費
A12: 諸経費(税金、募集経費等)(ドル) | B12: 51904.57 | C12: 1173.44 | D12: 1091.12 | E12: 1194.44 | F12: 1191.44 | H12: 4190.76 | I12: 7929.68 | J12: 1232.81 | K12: 1189.2 | L12: 1205.54 | M12: 1202.44 | N12: 1713.14 | O12: 1145.04 | P12: 1180.08 | Q12: 1168.25 | R12: 10730.52 | S12: 1146.74 | U12: 1144.67 | V12: 1173.91 | W12: 7730.82 | X12: 3369.8 | Y12: 1109.42 | Z12: 1163.36 | AA12: 1161.42 | AB12: 1762.86 | AG12: 18055.1 | AH12: コモンチャージ
A13: ネット賃貸収入利回り(円) | AG13: 15631.24 | AH13: 固定資産税
A14: ネット賃貸収入利回り(ドル) | AG14: 4998.3 | AH14: 修繕・雑費・その他支出
A15: 取得時簿価利回り(円) | B15: =B13/B2 -> 0 | AG15: =SUM(AG11:AG14) -> 53489.64 | AH15: 合計
A16: 取得時簿価利回り(ドル)
A17: 残存簿価利回り(円) | B17: =B13/B9 -> 0
A18: 残存簿価利回り(ドル)
A19: CF(円) | C19: =SUM(C20*C5) -> -278252.74 | D19: =SUM(D20*D5) -> -184345.05 | E19: =SUM(E20*E5) -> -203663.35 | F19: =SUM(F20*F5) -> -192293.91 | H19: =SUM(H20*H5) -> -1198994.7 | I19: =SUM(I20*I5) -> -376761.53 | J19: =SUM(J20*J5) -> 623346.67 | K19: =SUM(K20*K5) -> 618154.59 | L19: =SUM(L20*L5) -> 646079.88 | M19: =SUM(M20*M5) -> 638537.16 | N19: =SUM(N20*N5) -> 553558.99 | O19: =SUM(O20*O5) -> 630223.81 | ... S19: =SUM(S20*S5) -> 636295.33 | U19: =SUM(U20*U5) -> 52944.091 | V19: =SUM(V20*V5) -> -190745.06 | W19: =SUM(W20*W5) -> -330301.02 | X19: =SUM(X20*X5) -> 346183.63 | Y19: =SUM(Y20*Y5) -> 699914 | Z19: =SUM(Z20*Z5) -> 682367.18 | AA19: =SUM(AA20*AA5) -> 692266.95 | AB19: =SUM(AB20*AB5) -> 615480.44 | ... AF19: =SUM(AF20*AF5) -> 0
A20: CF(ドル) | C20: =SUM(C6-C11-C12) -> -1773.44 | D20: =SUM(D6-D11-D12) -> -1176.12 | E20: =SUM(E6-E11-E12) -> -1264.44 | F20: =SUM(F6-F11-F12) -> -1261.44 | H20: =SUM(H6-H11-H12) -> -8280.35 | I20: =SUM(I6-I11-I12) -> -2639.68 | J20: =SUM(J6-J11-J12) -> 4057.19 | K20: =SUM(K6-K11-K12) -> 4100.8 | L20: =SUM(L6-L11-L12) -> 4084.46 | M20: =SUM(M6-M11-M12) -> 4134.8 | N20: =SUM(N6-N11-N12) -> 3698.53 | O20: =SUM(O6-O11-O12) -> 4214.98 | ... S20: =SUM(S6-S11-S12) -> 4259.29 | U20: =SUM(U6-U11-U12) -> 360.36 | V20: =SUM(V6-V11-V12) -> -1281.2 | W20: =SUM(W6-W11-W12) -> -2143.42 | X20: =SUM(X6-X11-X12) -> 2210.2 | Y20: =SUM(Y6-Y11-Y12) -> 4470.58 | Z20: =SUM(Z6-Z11-Z12) -> 4440.76 | AA20: =SUM(AA6-AA11-AA12) -> 4443.02 | AB20: =SUM(AB6-AB11-AB12) -> 3849.64 | ... AF20: =SUM(AF6-AF11-AF12) -> 0
A21: PL(円)
A22: PL(ドル)
A24: 購入日 | B24: 45380
A25: 下記表は固都税を各月の諸経費に分散して計上した表です
A26: 111 West 56th #34D | B26: 2024 | C26: 45412 | D26: 45443 | E26: 45473 | F26: 45504 | G26: 2025 | H26: 45535 | I26: 45565 | J26: 45596 | K26: 45626 | L26: 45657 | M26: 45688 | N26: 45716 | O26: 45747 | P26: 45777 | Q26: 45808 | R26: 45838 | S26: 45869 | T26: 2026 | U26: 45535 | V26: 45565 | W26: 45596 | X26: 45626 | Y26: 45657 | Z26: 45688 | AA26: 45716 | AB26: 45747 | AC26: 45777 | AD26: 45808 | AE26: 45838 | AF26: 45869
A27: 取得簿価(円) | B27: =B28*150 -> 168750000
A28: 取得簿価(ドル) | B28: 1125000
A29: 賃料収入(円) | B29: =B31*B30 -> 862500 | C29: =C30*C31 -> 0 | D29: =D30*D31 -> 2351.1 | E29: =E30*E31 -> 4832.1 | F29: =F30*F31 -> 4573.2 | H29: =H30*H31 -> 273731.37 | I29: =I30*I31 -> 820697.5 | J29: =J30*J31 -> 883430 | K29: =K30*K31 -> 866755 | L29: =L30*L31 -> 909535 | M29: =M30*M31 -> 895267.77 | N29: =N30*N31 -> 878812.85 | O29: =O30*O31 -> 870209.39 | ... S29: =S30*S31 -> 867736.3 | U29: =U30*U31 -> 250686.66 | V29: =V30*V31 -> 13988.765 | W29: =W30*W31 -> 925740.34 | X29: =X30*X31 -> 939780 | Y29: =Y30*Y31 -> 939360 | Z29: =Z30*Z31 -> 925666.28 | AA29: =AA30*AA31 -> 938668 | AB29: =AB30*AB31 -> 964476.1 | ... AF29: =AF30*AF31 -> 0
A30: 為替レート(ドル円)TTM | B30: 150 | C30: ='NY不動産(総計)'!C30 -> 156.9 | D30: ='NY不動産(総計)'!D30 -> 156.74 | E30: ='NY不動産(総計)'!E30 -> 161.07 | F30: ='NY不動産(総計)'!F30 -> 152.44 | H30: ='NY不動産(総計)'!H30 -> 144.8 | I30: ='NY不動産(総計)'!I30 -> 142.73 | J30: ='NY不動産(総計)'!J30 -> 153.64 | K30: ='NY不動産(総計)'!K30 -> 150.74 | L30: ='NY不動産(総計)'!L30 -> 158.18 | M30: ='NY不動産(総計)'!M30 -> 154.43 | N30: ='NY不動産(総計)'!N30 -> 149.67 | O30: ='NY不動産(総計)'!O30 -> 149.52 | ... S30: ='NY不動産(総計)'!S30 -> 149.39 | U30: ='NY不動産(総計)'!U30 -> 146.92 | V30: ='NY不動産(総計)'!V30 -> 148.88 | W30: ='NY不動産(総計)'!W30 -> 154.1 | X30: ='NY不動産(総計)'!X30 -> 156.63 | Y30: ='NY不動産(総計)'!Y30 -> 156.56 | Z30: ='NY不動産(総計)'!Z30 -> 153.66 | AA30: ='NY不動産(総計)'!AA30 -> 155.81 | AB30: ='NY不動産(総計)'!AB30 -> 159.88 | ... AF30: ='NY不動産(総計)'!AF30 -> 0
A31: 賃料収入(ドル) | B31: 5750 | C31: 0 | D31: 15 | E31: 30 | F31: 30 | H31: 1890.41 | I31: 5750 | J31: 5750 | K31: 5750 | L31: 5750 | M31: 5797.24 | N31: 5871.67 | O31: 5820.02 | P31: 5813.94 | Q31: 5849.56 | R31: 5837.73 | S31: 5808.53 | U31: 1706.28 | V31: 93.96 | W31: 6007.4 | X31: 6000 | Y31: 6000 | Z31: 6024.12 | AA31: 6024.44 | AB31: 6032.5
A32: 減価償却費(円) | B32: 87233222 | C32: 814176 | D32: 814176 | E32: 814176 | F32: 814179 | H32: 814176 | I32: 814176 | J32: 814176 | K32: 814176 | L32: 814176 | M32: 814180 | N32: 814176 | O32: 814176 | P32: 814176 | Q32: 814176 | R32: 814176 | S32: 814180 | U32: 814176 | V32: 814176 | W32: 814176 | X32: 814176 | Y32: 814176 | Z32: 814180 | AA32: 814176 | AB32: 814176 | AC32: 814176 | AD32: 814176 | AE32: 814176 | AF32: 814180
A33: 減価償却費(ドル)
A34: 残存簿価(円) | B34: =SUM(B32-C32) -> 86419046 | C34: =SUM(B34-C32) -> 85604870 | D34: =SUM(C34-D32) -> 84790694 | E34: =SUM(D34-E32) -> 83976518 | F34: =SUM(E34-F32) -> 83162339 | H34: =SUM(F34-H32) -> 82348163 | I34: =SUM(H34-I32) -> 81533987 | J34: =SUM(I34-J32) -> 80719811 | K34: =SUM(J34-K32) -> 79905635 | L34: =SUM(K34-L32) -> 79091459 | M34: =SUM(L34-M32) -> 78277279 | N34: =SUM(M34-N32) -> 77463103 | O34: =SUM(N34-O32) -> 76648927 | P34: =SUM(O34-P32) -> 75834751 | ... S34: =SUM(R34-S32) -> 73392219 | U34: =SUM(S34-U32) -> 72578043 | V34: =SUM(U34-V32) -> 71763867 | W34: =SUM(V34-W32) -> 70949691 | X34: =SUM(W34-X32) -> 70135515 | Y34: =SUM(X34-Y32) -> 69321339 | Z34: =SUM(Y34-Z32) -> 68507159 | AA34: =SUM(Z34-AA32) -> 67692983 | AB34: =SUM(AA34-AB32) -> 66878807 | AC34: =SUM(AB34-AC32) -> 66064631 | ... AF34: =SUM(AE34-AF32) -> 63622099
A35: 残存簿価(ドル)
A36: 管理費(ドル) | C36: 600 | D36: 100 | E36: 100 | F36: 100 | H36: 5980 | I36: 460 | J36: 460 | K36: 460 | L36: 460 | M36: 460 | N36: 460 | O36: 460 | P36: 460 | Q36: 460 | R36: 460 | S36: 402.5 | U36: 201.25 | V36: 201.25 | W36: 420 | X36: 420 | Y36: 420 | Z36: 420 | AA36: 420
A37: 諸経費(税金、募集経費等)(ドル) | B37: 51904.57 | C37: 1173.44 | D37: 1091.12 | E37: 1191.44 | F37: 1191.44 | H37: 4190.76 | I37: 2251.28 | J37: 1942.61 | K37: 1899 | L37: 1915.34 | M37: 1912.24 | N37: 2422.94 | O37: 1854.84 | P37: 1889.88 | Q37: 1878.05 | R37: 2257.66 | S37: 1917 | U37: 1914.93 | V37: 1944.17 | W37: 8501.08 | X37: 4140.06 | Y37: 1879.68 | Z37: 1933.62 | AA37: 1931.68 | AB37: 770.26 | AC37: 770.26 | AD37: 770.26
A38: ネット賃貸収入利回り(円)
A39: ネット賃貸収入利回り(ドル)
A40: 取得時簿価利回り(円) | B40: =B38/B27 -> 0
A41: 取得時簿価利回り(ドル)
A42: 残存簿価利回り(円) | B42: =B38/B34 -> 0
A43: 残存簿価利回り(ドル)
A44: CF(円) | C44: =SUM(C45*C30) -> -278252.74 | D44: =SUM(D45*D30) -> -184345.05 | E44: =SUM(E45*E30) -> -203180.14 | F44: =SUM(F45*F30) -> -192293.91 | H44: =SUM(H45*H30) -> -1198994.7 | I44: =SUM(I45*I30) -> 433716.51 | J44: =SUM(J45*J30) -> 514293 | K44: =SUM(K45*K30) -> 511159.34 | L44: =SUM(L45*L30) -> 533803.72 | M44: =SUM(M45*M30) -> 528922.75 | N44: =SUM(N45*N30) -> 447323.22 | O44: =SUM(O45*O30) -> 524094.51 | ... S44: =SUM(S45*S30) -> 521226.19 | U44: =SUM(U45*U30) -> -60222.508 | V44: =SUM(V45*V30) -> -305421.36 | W44: =SUM(W45*W30) -> -448998.09 | X44: =SUM(X45*X30) -> 225537.8 | Y44: =SUM(Y45*Y30) -> 579322.1 | Z44: =SUM(Z45*Z30) -> 564009.03 | AA44: =SUM(AA45*AA30) -> 572252.74 | AB44: =SUM(AB45*AB30) -> 841326.93 | ... AF44: =SUM(AF45*AF30) -> 0
A45: CF(ドル) | C45: =SUM(C31-C36-C37) -> -1773.44 | D45: =SUM(D31-D36-D37) -> -1176.12 | E45: =SUM(E31-E36-E37) -> -1261.44 | F45: =SUM(F31-F36-F37) -> -1261.44 | H45: =SUM(H31-H36-H37) -> -8280.35 | I45: =SUM(I31-I36-I37) -> 3038.72 | J45: =SUM(J31-J36-J37) -> 3347.39 | K45: =SUM(K31-K36-K37) -> 3391 | L45: =SUM(L31-L36-L37) -> 3374.66 | M45: =SUM(M31-M36-M37) -> 3425 | N45: =SUM(N31-N36-N37) -> 2988.73 | O45: =SUM(O31-O36-O37) -> 3505.18 | ... S45: =SUM(S31-S36-S37) -> 3489.03 | U45: =SUM(U31-U36-U37) -> -409.9 | V45: =SUM(V31-V36-V37) -> -2051.46 | W45: =SUM(W31-W36-W37) -> -2913.68 | X45: =SUM(X31-X36-X37) -> 1439.94 | Y45: =SUM(Y31-Y36-Y37) -> 3700.32 | Z45: =SUM(Z31-Z36-Z37) -> 3670.5 | AA45: =SUM(AA31-AA36-AA37) -> 3672.76 | AB45: =SUM(AB31-AB36-AB37) -> 5262.24 | ... AF45: =SUM(AF31-AF36-AF37) -> 0
A46: PL(円)
A47: PL(ドル)
R51: 9243.07
Q52: 1 | R52: 770.21
Q53: 2 | R53: 770.26
Q54: 3 | R54: 770.26
Q55: 4 | R55: 770.26
Q56: 5 | R56: 770.26
Q57: 6 | R57: 770.26
Q58: 7 | R58: 770.26
Q59: 8 | R59: 770.26
Q60: 9 | R60: 770.26
Q61: 10 | R61: 770.26
Q62: 11 | R62: 770.26
Q63: 12 | R63: 770.26
R64: =SUM(R52:R63) -> 9243.07

Sheet 88Gr#1512
A1: 88 Greenwich #1512 | B1: 2024 | C1: 45412 | D1: 45443 | E1: 45473 | F1: 45504 | G1: 2025 | H1: 45535 | I1: 45565 | J1: 45596 | K1: 45626 | L1: 45657 | M1: 45688 | N1: 45716 | O1: 45747 | P1: 45777 | Q1: 45808 | R1: 45838 | S1: 45869 | T1: 2026 | U1: 45900 | V1: 45930 | W1: 45961 | X1: 45991 | Y1: 46022 | Z1: 46053 | AA1: 46081 | AB1: 46112 | AC1: 46142 | AD1: 46173 | AE1: 46203 | AF1: 46234
A2: 取得簿価(円) | B2: =B3*150 -> 126225000
A3: 取得簿価(ドル) | B3: 841500
A4: 賃料収入(円) | B4: =B6*B5 -> 660000 | C4: =C5*C6 -> 0 | D4: =D5*D6 -> 78370 | E4: =E5*E6 -> 0 | F4: =F5*F6 -> 655492 | H4: =H5*H6 -> 622640 | I4: =I5*I6 -> 613739 | J4: =J5*J6 -> 660652 | K4: =K5*K6 -> 648182 | L4: =L5*L6 -> 680174 | M4: =M5*M6 -> 664049 | N4: =N5*N6 -> 643581 | O4: =O5*O6 -> 642936 | ... S4: =S5*S6 -> 657316 | U4: =U5*U6 -> 646448 | V4: =V5*V6 -> 655072 | W4: =W5*W6 -> 678040 | X4: =X5*X6 -> 689172 | Y4: =Y5*Y6 -> 688864 | Z4: =Z5*Z6 -> 676104 | AA4: =AA5*AA6 -> 685564 | AB4: =AB5*AB6 -> 703472 | ... AF4: =AF5*AF6 -> 0
A5: 為替レート(ドル円)TTM | B5: 150 | C5: ='NY不動産(総計)'!C5 -> 156.9 | D5: ='NY不動産(総計)'!D5 -> 156.74 | E5: ='NY不動産(総計)'!E5 -> 161.07 | F5: ='NY不動産(総計)'!F5 -> 152.44 | H5: ='NY不動産(総計)'!H5 -> 144.8 | I5: ='NY不動産(総計)'!I5 -> 142.73 | J5: ='NY不動産(総計)'!J5 -> 153.64 | K5: ='NY不動産(総計)'!K5 -> 150.74 | L5: ='NY不動産(総計)'!L5 -> 158.18 | M5: ='NY不動産(総計)'!M5 -> 154.43 | N5: ='NY不動産(総計)'!N5 -> 149.67 | O5: ='NY不動産(総計)'!O5 -> 149.52 | ... S5: ='NY不動産(総計)'!S5 -> 149.39 | U5: ='NY不動産(総計)'!U5 -> 146.92 | V5: ='NY不動産(総計)'!V5 -> 148.88 | W5: ='NY不動産(総計)'!W5 -> 154.1 | X5: ='NY不動産(総計)'!X5 -> 156.63 | Y5: ='NY不動産(総計)'!Y5 -> 156.56 | Z5: ='NY不動産(総計)'!Z5 -> 153.66 | AA5: ='NY不動産(総計)'!AA5 -> 155.81 | AB5: ='NY不動産(総計)'!AB5 -> 159.88 | ... AF5: ='NY不動産(総計)'!AF5 -> 0
A6: 賃料収入(ドル) | B6: 4400 | C6: 0 | D6: 500 | E6: 0 | F6: 4300 | H6: 4300 | I6: 4300 | J6: 4300 | K6: 4300 | L6: 4300 | M6: 4300 | N6: 4300 | O6: 4300 | P6: 4300 | Q6: 4300 | R6: 4300 | S6: 4400 | U6: 4400 | V6: 4400 | W6: 4400 | X6: 4400 | Y6: 4400 | Z6: 4400 | AA6: 4400 | AB6: 4400 | AC6: 4400
A7: 減価償却費(円) | B7: 115159974 | C7: 1074826 | D7: 1074826 | E7: 1074826 | F7: 1074827 | H7: 1074826 | I7: 1074826 | J7: 1074826 | K7: 1074826 | L7: 1074826 | M7: 1074828 | N7: 1074826 | O7: 1074826 | P7: 1074826 | Q7: 1074826 | R7: 1074826 | S7: 1074829 | U7: 1074826 | V7: 1074826 | W7: 1074826 | X7: 1074826 | Y7: 1074826 | Z7: 1074828 | AA7: 1074826 | AB7: 1074826 | AC7: 1074826 | AD7: 1074826 | AE7: 1074826 | AF7: 1074829
A8: 減価償却費(ドル)
A9: 残存簿価(円) | B9: 115159974 | C9: =SUM(B7-C7) -> 114085148 | D9: =SUM(C9-D7) -> 113010322 | E9: =SUM(D9-E7) -> 111935496 | F9: =SUM(E9-F7) -> 110860669 | H9: =SUM(F9-H7) -> 109785843 | I9: =SUM(H9-I7) -> 108711017 | J9: =SUM(I9-J7) -> 107636191 | K9: =SUM(J9-K7) -> 106561365 | L9: =SUM(K9-L7) -> 105486539 | M9: =SUM(L9-M7) -> 104411711 | N9: =SUM(M9-N7) -> 103336885 | O9: =SUM(N9-O7) -> 102262059 | P9: =SUM(O9-P7) -> 101187233 | ... S9: =SUM(R9-S7) -> 97962752 | U9: =SUM(S9-U7) -> 96887926 | V9: =SUM(U9-V7) -> 95813100 | W9: =SUM(V9-W7) -> 94738274 | X9: =SUM(W9-X7) -> 93663448 | Y9: =SUM(X9-Y7) -> 92588622 | Z9: =SUM(Y9-Z7) -> 91513794 | AA9: =SUM(Z9-AA7) -> 90438968 | AB9: =SUM(AA9-AB7) -> 89364142 | AC9: =SUM(AB9-AC7) -> 88289316 | ... AF9: =SUM(AE9-AF7) -> 85064835
A10: 残存簿価(ドル)
A11: 管理費(ドル) | C11: 63.27 | D11: 100 | E11: 100 | F11: 258 | H11: 258 | I11: 258 | J11: 258 | K11: 258 | L11: 258 | M11: 258 | N11: 258 | O11: 258 | P11: 258 | Q11: 258 | R11: 258 | S11: 264 | U11: 264 | V11: 264 | W11: 264 | X11: 264 | Y11: 264 | Z11: 264 | AA11: 264 | AB11: 264 | AC11: 264 | AG11: =SUM(C11:AF11) -> 5999.27 | AH11: 管理費
A12: 諸経費(税金、募集経費等)(ドル) | B12: 13867.33 | C12: 629.45 | D12: 9730.09 | E12: 1709.27 | F12: 6857.32 | H12: 1960.99 | I12: 9204.75 | J12: 1043 | K12: 1043 | L12: 1043 | M12: 1043 | N12: 1043 | O12: 1147.3 | P12: 1147.3 | Q12: 1147.3 | R12: 12390.93 | S12: 4703.98 | U12: 1193.96 | V12: 1193.96 | W12: 1263.96 | X12: 1395.55 | Y12: 1395.55 | Z12: 1395.55 | AA12: 1395.55 | AB12: 1395.55 | AC12: 1395.55 | AG12: 16077.93 | AH12: コモンチャージ
A13: ネット賃貸収入利回り(円) | AG13: 19156.25 | AH13: 固定資産税
A14: ネット賃貸収入利回り(ドル) | AG14: 20609.5 | AH14: 修繕・雑費・その他支出
A15: 取得時簿価利回り(円) | B15: =B13/B2 -> 0 | AG15: =SUM(AG11:AG14) -> 61842.95 | AH15: 合計
A16: 取得時簿価利回り(ドル)
A17: 残存簿価利回り(円) | B17: =B13/B9 -> 0
A18: 残存簿価利回り(ドル)
A19: CF(円) | C19: =SUM(C20*C5) -> -108687.77 | D19: =SUM(D20*D5) -> -1462398.3 | E19: =SUM(E20*E5) -> -291419.12 | F19: =SUM(F20*F5) -> -429167.38 | H19: =SUM(H20*H5) -> 301330.25 | I19: =SUM(I20*I5) -> -736879.31 | J19: =SUM(J20*J5) -> 460766.36 | K19: =SUM(K20*K5) -> 452069.26 | L19: =SUM(L20*L5) -> 474381.82 | M19: =SUM(M20*M5) -> 463135.57 | N19: =SUM(N20*N5) -> 448860.33 | O19: =SUM(O20*O5) -> 432815.54 | ... S19: =SUM(S20*S5) -> -84850.532 | U19: =SUM(U20*U5) -> 432244.52 | V19: =SUM(V20*V5) -> 438010.92 | W19: =SUM(W20*W5) -> 442581.36 | X19: =SUM(X20*X5) -> 429236.68 | Y19: =SUM(Y20*Y5) -> 429044.85 | Z19: =SUM(Z20*Z5) -> 421097.55 | AA19: =SUM(AA20*AA5) -> 426989.51 | AB19: =SUM(AB20*AB5) -> 438143.15 | ... AF19: =SUM(AF20*AF5) -> 0
A20: CF(ドル) | C20: =SUM(C6-C11-C12) -> -692.72 | D20: =SUM(D6-D11-D12) -> -9330.09 | E20: =SUM(E6-E11-E12) -> -1809.27 | F20: =SUM(F6-F11-F12) -> -2815.32 | H20: =SUM(H6-H11-H12) -> 2081.01 | I20: =SUM(I6-I11-I12) -> -5162.75 | J20: =SUM(J6-J11-J12) -> 2999 | K20: =SUM(K6-K11-K12) -> 2999 | L20: =SUM(L6-L11-L12) -> 2999 | M20: =SUM(M6-M11-M12) -> 2999 | N20: =SUM(N6-N11-N12) -> 2999 | O20: =SUM(O6-O11-O12) -> 2894.7 | ... S20: =SUM(S6-S11-S12) -> -567.98 | U20: =SUM(U6-U11-U12) -> 2942.04 | V20: =SUM(V6-V11-V12) -> 2942.04 | W20: =SUM(W6-W11-W12) -> 2872.04 | X20: =SUM(X6-X11-X12) -> 2740.45 | Y20: =SUM(Y6-Y11-Y12) -> 2740.45 | Z20: =SUM(Z6-Z11-Z12) -> 2740.45 | AA20: =SUM(AA6-AA11-AA12) -> 2740.45 | AB20: =SUM(AB6-AB11-AB12) -> 2740.45 | ... AF20: =SUM(AF6-AF11-AF12) -> 0
A21: PL(円)
A22: PL(ドル)
A24: 購入日 | B24: 45394
A25: 下記表は固都税を各月の諸経費に分散して計上した表です
A26: 88 Greenwich #1512 | B26: 2024 | C26: 45412 | D26: 45443 | E26: 45473 | F26: 45504 | G26: 2025 | H26: 45535 | I26: 45565 | J26: 45596 | K26: 45626 | L26: 45657 | M26: 45688 | N26: 45716 | O26: 45747 | P26: 45777 | Q26: 45808 | R26: 45838 | S26: 45869 | T26: 2026 | U26: 45535 | V26: 45565 | W26: 45596 | X26: 45626 | Y26: 45657 | Z26: 45688 | AA26: 45716 | AB26: 45747 | AC26: 45777 | AD26: 45808 | AE26: 45838 | AF26: 45869
A27: 取得簿価(円) | B27: =B28*150 -> 126225000
A28: 取得簿価(ドル) | B28: 841500
A29: 賃料収入(円) | B29: =B31*B30 -> 645000 | C29: =C30*C31 -> 0 | D29: =D30*D31 -> 78370 | E29: =E30*E31 -> 0 | F29: =F30*F31 -> 655492 | H29: =H30*H31 -> 622640 | I29: =I30*I31 -> 613739 | J29: =J30*J31 -> 660652 | K29: =K30*K31 -> 648182 | L29: =L30*L31 -> 680174 | M29: =M30*M31 -> 664049 | N29: =N30*N31 -> 643581 | O29: =O30*O31 -> 642936 | ... S29: =S30*S31 -> 657316 | U29: =U30*U31 -> 646448 | V29: =V30*V31 -> 655072 | W29: =W30*W31 -> 678040 | X29: =X30*X31 -> 689172 | Y29: =Y30*Y31 -> 688864 | Z29: =Z30*Z31 -> 676104 | AA29: =AA30*AA31 -> 685564 | AB29: =AB30*AB31 -> 703472 | ... AF29: =AF30*AF31 -> 0
A30: 為替レート(ドル円)TTM | B30: 150 | C30: ='NY不動産(総計)'!C30 -> 156.9 | D30: ='NY不動産(総計)'!D30 -> 156.74 | E30: ='NY不動産(総計)'!E30 -> 161.07 | F30: ='NY不動産(総計)'!F30 -> 152.44 | H30: ='NY不動産(総計)'!H30 -> 144.8 | I30: ='NY不動産(総計)'!I30 -> 142.73 | J30: ='NY不動産(総計)'!J30 -> 153.64 | K30: ='NY不動産(総計)'!K30 -> 150.74 | L30: ='NY不動産(総計)'!L30 -> 158.18 | M30: ='NY不動産(総計)'!M30 -> 154.43 | N30: ='NY不動産(総計)'!N30 -> 149.67 | O30: ='NY不動産(総計)'!O30 -> 149.52 | ... S30: ='NY不動産(総計)'!S30 -> 149.39 | U30: ='NY不動産(総計)'!U30 -> 146.92 | V30: ='NY不動産(総計)'!V30 -> 148.88 | W30: ='NY不動産(総計)'!W30 -> 154.1 | X30: ='NY不動産(総計)'!X30 -> 156.63 | Y30: ='NY不動産(総計)'!Y30 -> 156.56 | Z30: ='NY不動産(総計)'!Z30 -> 153.66 | AA30: ='NY不動産(総計)'!AA30 -> 155.81 | AB30: ='NY不動産(総計)'!AB30 -> 159.88 | ... AF30: ='NY不動産(総計)'!AF30 -> 0
A31: 賃料収入(ドル) | B31: 4300 | C31: 0 | D31: 500 | E31: 0 | F31: 4300 | H31: 4300 | I31: 4300 | J31: 4300 | K31: 4300 | L31: 4300 | M31: 4300 | N31: 4300 | O31: 4300 | P31: 4300 | Q31: 4300 | R31: 4300 | S31: 4400 | U31: 4400 | V31: 4400 | W31: 4400 | X31: 4400 | Y31: 4400 | Z31: 4400 | AA31: 4400 | AB31: 4400 | AC31: 4400
A32: 減価償却費(円) | B32: 115159974 | C32: 1074826 | D32: 1074826 | E32: 1074826 | F32: 1074827 | H32: 1074826 | I32: 1074826 | J32: 1074826 | K32: 1074826 | L32: 1074826 | M32: 1074828 | N32: 1074826 | O32: 1074826 | P32: 1074826 | Q32: 1074826 | R32: 1074826 | S32: 1074829 | U32: 1074826 | V32: 1074826 | W32: 1074826 | X32: 1074826 | Y32: 1074826 | Z32: 1074828 | AA32: 1074826 | AB32: 1074826 | AC32: 1074826 | AD32: 1074826 | AE32: 1074826 | AF32: 1074829
A33: 減価償却費(ドル)
A34: 残存簿価(円) | B34: 115159974 | C34: =SUM(B32-C32) -> 114085148 | D34: =SUM(C34-D32) -> 113010322 | E34: =SUM(D34-E32) -> 111935496 | F34: =SUM(E34-F32) -> 110860669 | H34: =SUM(F34-H32) -> 109785843 | I34: =SUM(H34-I32) -> 108711017 | J34: =SUM(I34-J32) -> 107636191 | K34: =SUM(J34-K32) -> 106561365 | L34: =SUM(K34-L32) -> 105486539 | M34: =SUM(L34-M32) -> 104411711 | N34: =SUM(M34-N32) -> 103336885 | O34: =SUM(N34-O32) -> 102262059 | P34: =SUM(O34-P32) -> 101187233 | ... S34: =SUM(R34-S32) -> 97962752 | U34: =SUM(S34-U32) -> 96887926 | V34: =SUM(U34-V32) -> 95813100 | W34: =SUM(V34-W32) -> 94738274 | X34: =SUM(W34-X32) -> 93663448 | Y34: =SUM(X34-Y32) -> 92588622 | Z34: =SUM(Y34-Z32) -> 91513794 | AA34: =SUM(Z34-AA32) -> 90438968 | AB34: =SUM(AA34-AB32) -> 89364142 | AC34: =SUM(AB34-AC32) -> 88289316 | ... AF34: =SUM(AE34-AF32) -> 85064835
A35: 残存簿価(ドル)
A36: 管理費(ドル) | C36: 63.27 | D36: 100 | E36: 100 | F36: 258 | H36: 258 | I36: 258 | J36: 258 | K36: 258 | L36: 258 | M36: 258 | N36: 258 | O36: 258 | P36: 258 | Q36: 258 | R36: 258 | S36: 264 | U36: 264 | V36: 264 | W36: 264 | X36: 264 | Y36: 264 | Z36: 264 | AA36: 264 | AB36: 264 | AC36: 264
A37: 諸経費(税金、募集経費等)(ドル) | B37: 13867.33 | C37: 629.45 | D37: 9730.09 | E37: 1709.27 | F37: 6857.32 | H37: 1960.99 | I37: 1993.47 | J37: 1944.41 | K37: 1944.41 | L37: 1944.41 | M37: 1944.41 | N37: 1944.41 | O37: 2048.71 | P37: 2048.71 | Q37: 2048.71 | R37: 2267.63 | S37: 5624.28 | U37: 2114.26 | V37: 2114.26 | W37: 2184.26 | X37: 2315.85 | Y37: 2315.85 | Z37: 2315.85 | AA37: 2315.85 | AB37: 920.3 | AC37: 920.3 | AD37: 920.3
A38: ネット賃貸収入利回り(円)
A39: ネット賃貸収入利回り(ドル)
A40: 取得時簿価利回り(円) | B40: =B38/B27 -> 0
A41: 取得時簿価利回り(ドル)
A42: 残存簿価利回り(円) | B42: =B38/B34 -> 0
A43: 残存簿価利回り(ドル)
A44: CF(円) | C44: =SUM(C45*C30) -> -108687.77 | D44: =SUM(D45*D30) -> -1462398.3 | E44: =SUM(E45*E30) -> -291419.12 | F44: =SUM(F45*F30) -> -429167.38 | H44: =SUM(H45*H30) -> 301330.25 | I44: =SUM(I45*I30) -> 292386.69 | J44: =SUM(J45*J30) -> 322273.73 | K44: =SUM(K45*K30) -> 316190.72 | L44: =SUM(L45*L30) -> 331796.79 | M44: =SUM(M45*M30) -> 323930.82 | N44: =SUM(N45*N30) -> 313946.3 | O44: =SUM(O45*O30) -> 298036.72 | ... S44: =SUM(S45*S30) -> -222334.15 | U44: =SUM(U45*U30) -> 297034.04 | V44: =SUM(V45*V30) -> 300996.65 | W44: =SUM(W45*W30) -> 300763.13 | X44: =SUM(X45*X30) -> 285090.09 | Y44: =SUM(Y45*Y30) -> 284962.68 | Z44: =SUM(Z45*Z30) -> 279684.25 | AA44: =SUM(AA45*AA30) -> 283597.57 | AB44: =SUM(AB45*AB30) -> 514126.12 | ... AF44: =SUM(AF45*AF30) -> 0
A45: CF(ドル) | C45: =SUM(C31-C36-C37) -> -692.72 | D45: =SUM(D31-D36-D37) -> -9330.09 | E45: =SUM(E31-E36-E37) -> -1809.27 | F45: =SUM(F31-F36-F37) -> -2815.32 | H45: =SUM(H31-H36-H37) -> 2081.01 | I45: =SUM(I31-I36-I37) -> 2048.53 | J45: =SUM(J31-J36-J37) -> 2097.59 | K45: =SUM(K31-K36-K37) -> 2097.59 | L45: =SUM(L31-L36-L37) -> 2097.59 | M45: =SUM(M31-M36-M37) -> 2097.59 | N45: =SUM(N31-N36-N37) -> 2097.59 | O45: =SUM(O31-O36-O37) -> 1993.29 | ... S45: =SUM(S31-S36-S37) -> -1488.28 | U45: =SUM(U31-U36-U37) -> 2021.74 | V45: =SUM(V31-V36-V37) -> 2021.74 | W45: =SUM(W31-W36-W37) -> 1951.74 | X45: =SUM(X31-X36-X37) -> 1820.15 | Y45: =SUM(Y31-Y36-Y37) -> 1820.15 | Z45: =SUM(Z31-Z36-Z37) -> 1820.15 | AA45: =SUM(AA31-AA36-AA37) -> 1820.15 | AB45: =SUM(AB31-AB36-AB37) -> 3215.7 | ... AF45: =SUM(AF31-AF36-AF37) -> 0
A46: PL(円)
A47: PL(ドル)
R50: 920.33
R51: 920.3
R52: 920.3
R53: 920.3
R54: 920.3
R55: 920.3
R56: 920.3
R57: 920.3
R58: 920.3
R59: 920.3
R60: 920.3
R61: 920.3
R62: =SUM(R50:R61) -> 11043.63

Sheet 88Gr#3101
A1: 88 Greenwich #3101 | B1: 2024 | C1: 45412 | D1: 45443 | E1: 45473 | F1: 45504 | G1: 2025 | H1: 45535 | I1: 45565 | J1: 45596 | K1: 45626 | L1: 45657 | M1: 45688 | N1: 45716 | O1: 45747 | P1: 45777 | Q1: 45808 | R1: 45838 | S1: 45869 | T1: 2026 | U1: 45900 | V1: 45930 | W1: 45961 | X1: 45991 | Y1: 46022 | Z1: 46053 | AA1: 46081 | AB1: 46112 | AC1: 46142 | AD1: 46173 | AE1: 46203 | AF1: 46234
A2: 取得簿価(円) | B2: =B3*150 -> 149850000
A3: 取得簿価(ドル) | B3: 999000
A4: 賃料収入(円) | B4: =B6*B5 -> 697500 | C4: =C5*C6 -> 0 | D4: =D5*D6 -> 22752.378 | E4: =E5*E6 -> 724815 | F4: =F5*F6 -> 685980 | H4: =H5*H6 -> 651600 | I4: =I5*I6 -> 652989.75 | J4: =J5*J6 -> 702903 | K4: =K5*K6 -> 689635.5 | L4: =L5*L6 -> 723673.5 | M4: =M5*M6 -> 706517.25 | N4: =N5*N6 -> 684740.25 | O4: =O5*O6 -> 684054 | ... S4: =S5*S6 -> 683459.25 | U4: =U5*U6 -> 672159 | V4: =V5*V6 -> 692292 | W4: =W5*W6 -> 716565 | X4: =X5*X6 -> 728329.5 | Y4: =Y5*Y6 -> 728004 | Z4: =Z5*Z6 -> 714519 | AA4: =AA5*AA6 -> 724516.5 | AB4: =AB5*AB6 -> 743442 | ... AF4: =AF5*AF6 -> 0
A5: 為替レート(ドル円)TTM | B5: 150 | C5: ='NY不動産(総計)'!C5 -> 156.9 | D5: ='NY不動産(総計)'!D5 -> 156.74 | E5: ='NY不動産(総計)'!E5 -> 161.07 | F5: ='NY不動産(総計)'!F5 -> 152.44 | H5: ='NY不動産(総計)'!H5 -> 144.8 | I5: ='NY不動産(総計)'!I5 -> 142.73 | J5: ='NY不動産(総計)'!J5 -> 153.64 | K5: ='NY不動産(総計)'!K5 -> 150.74 | L5: ='NY不動産(総計)'!L5 -> 158.18 | M5: ='NY不動産(総計)'!M5 -> 154.43 | N5: ='NY不動産(総計)'!N5 -> 149.67 | O5: ='NY不動産(総計)'!O5 -> 149.52 | ... S5: ='NY不動産(総計)'!S5 -> 149.39 | U5: ='NY不動産(総計)'!U5 -> 146.92 | V5: ='NY不動産(総計)'!V5 -> 148.88 | W5: ='NY不動産(総計)'!W5 -> 154.1 | X5: ='NY不動産(総計)'!X5 -> 156.63 | Y5: ='NY不動産(総計)'!Y5 -> 156.56 | Z5: ='NY不動産(総計)'!Z5 -> 153.66 | AA5: ='NY不動産(総計)'!AA5 -> 155.81 | AB5: ='NY不動産(総計)'!AB5 -> 159.88 | ... AF5: ='NY不動産(総計)'!AF5 -> 0
A6: 賃料収入(ドル) | B6: 4650 | D6: 145.16 | E6: 4500 | F6: 4500 | H6: 4500 | I6: 4575 | J6: 4575 | K6: 4575 | L6: 4575 | M6: 4575 | N6: 4575 | O6: 4575 | P6: 4575 | Q6: 4575 | R6: 4575 | S6: 4575 | U6: 4575 | V6: 4650 | W6: 4650 | X6: 4650 | Y6: 4650 | Z6: 4650 | AA6: 4650 | AB6: 4650 | AC6: 4650
A7: 減価償却費(円) | B7: 136057268 | D7: 1269867 | E7: 1269867 | F7: 1269869 | H7: 1269867 | I7: 1269867 | J7: 1269867 | K7: 1269867 | L7: 1269867 | M7: 1269872 | N7: 1269867 | O7: 1269867 | P7: 1269867 | Q7: 1269867 | R7: 1269867 | S7: 1269872 | U7: 1269867 | V7: 1269867 | W7: 1269867 | X7: 1269867 | Y7: 1269867 | Z7: 1269872 | AA7: 1269867 | AB7: 1269867 | AC7: 1269867 | AD7: 1269867 | AE7: 1269867 | AF7: 1269872
A8: 減価償却費(ドル)
A9: 残存簿価(円) | B9: 136057268 | D9: =SUM(B9-D7) -> 134787401 | E9: =SUM(D9-E7) -> 133517534 | F9: =SUM(E9-F7) -> 132247665 | H9: =SUM(F9-H7) -> 130977798 | I9: =SUM(H9-I7) -> 129707931 | J9: =SUM(I9-J7) -> 128438064 | K9: =SUM(J9-K7) -> 127168197 | L9: =SUM(K9-L7) -> 125898330 | M9: =SUM(L9-M7) -> 124628458 | N9: =SUM(M9-N7) -> 123358591 | O9: =SUM(N9-O7) -> 122088724 | P9: =SUM(O9-P7) -> 120818857 | ... S9: =SUM(R9-S7) -> 117009251 | U9: =SUM(S9-U7) -> 115739384 | V9: =SUM(U9-V7) -> 114469517 | W9: =SUM(V9-W7) -> 113199650 | X9: =SUM(W9-X7) -> 111929783 | Y9: =SUM(X9-Y7) -> 110659916 | Z9: =SUM(Y9-Z7) -> 109390044 | AA9: =SUM(Z9-AA7) -> 108120177 | AB9: =SUM(AA9-AB7) -> 106850310 | AC9: =SUM(AB9-AC7) -> 105580443 | ... AF9: =SUM(AE9-AF7) -> 101770837
A10: 残存簿価(ドル)
A11: 管理費(ドル) | F11: 270 | H11: 270 | I11: 274.5 | J11: 274.5 | K11: 274.5 | L11: 274.5 | M11: 274.5 | N11: 274.5 | O11: 274.5 | P11: 274.5 | Q11: 274.5 | R11: 274.5 | S11: 274.5 | U11: 274.5 | V11: 279 | W11: 279 | X11: 279 | Y11: 279 | Z11: 279 | AA11: 279 | AB11: 279 | AC11: 279 | AG11: =SUM(C36:AF36) -> 6066 | AH11: 管理費
A12: 諸経費(税金、募集経費等)(ドル) | B12: 16101.33 | D12: 36.56 | E12: 1133.38 | F12: 1176.9 | H12: 3932 | I12: 10500.82 | J12: 1489.41 | K12: 1189.41 | L12: 1189.41 | M12: 1189.41 | N12: 1189.41 | O12: 1308.35 | P12: 1847.28 | Q12: 1308.35 | R12: 25883.43 | S12: 1308.35 | U12: 2307 | V12: 1361.56 | W12: 1431.56 | X12: 1591.44 | Y12: 1591.44 | Z12: 1591.44 | AA12: 1591.44 | AB12: 1591.44 | AC12: 1591.44 | AG12: 16520.21 | AH12: コモンチャージ
A13: ネット賃貸収入利回り(円) | AG13: 21854.74 | AH13: 固定資産税
A14: ネット賃貸収入利回り(ドル) | AG14: 16307.52 | AH14: 修繕・雑費・その他支出
A15: 取得時簿価利回り(円) | B15: =B13/B2 -> 0 | AG15: =SUM(AG11:AG14) -> 60748.47 | AH15: 合計
A16: 取得時簿価利回り(ドル)
A17: 残存簿価利回り(円) | B17: =B13/B9 -> 0
A18: 残存簿価利回り(ドル)
A19: CF(円) | C19: =SUM(C5*C20) -> 0 | D19: =SUM(D5*D20) -> 17021.964 | E19: =SUM(E5*E20) -> 542261.48 | F19: =SUM(F5*F20) -> 465414.56 | H19: =SUM(H5*H20) -> 43150.4 | I19: =SUM(I5*I20) -> -884971.67 | J19: =SUM(J5*J20) -> 431895.87 | K19: =SUM(K5*K20) -> 468965.71 | L19: =SUM(L5*L20) -> 492112.22 | M19: =SUM(M5*M20) -> 480445.63 | N19: =SUM(N5*N20) -> 465636.84 | O19: =SUM(O5*O20) -> 447386.27 | ... S19: =SUM(S5*S20) -> 446997.29 | U19: =SUM(U5*U20) -> 292885.02 | V19: =SUM(V5*V20) -> 448045.43 | W19: =SUM(W5*W20) -> 452967.7 | X19: =SUM(X5*X20) -> 435362.48 | Y19: =SUM(Y5*Y20) -> 435167.91 | Z19: =SUM(Z5*Z20) -> 427107.19 | AA19: =SUM(AA5*AA20) -> 433083.24 | AB19: =SUM(AB5*AB20) -> 444396.05 | ... AF19: =SUM(AF5*AF20) -> 0
A20: CF(ドル) | C20: =SUM(C6-C11-C12) -> 0 | D20: =SUM(D6-D11-D12) -> 108.6 | E20: =SUM(E6-E11-E12) -> 3366.62 | F20: =SUM(F6-F11-F12) -> 3053.1 | H20: =SUM(H6-H11-H12) -> 298 | I20: =SUM(I6-I11-I12) -> -6200.32 | J20: =SUM(J6-J11-J12) -> 2811.09 | K20: =SUM(K6-K11-K12) -> 3111.09 | L20: =SUM(L6-L11-L12) -> 3111.09 | M20: =SUM(M6-M11-M12) -> 3111.09 | N20: =SUM(N6-N11-N12) -> 3111.09 | O20: =SUM(O6-O11-O12) -> 2992.15 | ... S20: =SUM(S6-S11-S12) -> 2992.15 | U20: =SUM(U6-U11-U12) -> 1993.5 | V20: =SUM(V6-V11-V12) -> 3009.44 | W20: =SUM(W6-W11-W12) -> 2939.44 | X20: =SUM(X6-X11-X12) -> 2779.56 | Y20: =SUM(Y6-Y11-Y12) -> 2779.56 | Z20: =SUM(Z6-Z11-Z12) -> 2779.56 | AA20: =SUM(AA6-AA11-AA12) -> 2779.56 | AB20: =SUM(AB6-AB11-AB12) -> 2779.56 | ... AF20: =SUM(AF6-AF11-AF12) -> 0
A21: PL(円)
A22: PL(ドル)
A24: 購入日 | B24: 45443
A25: 下記表は固都税を各月の諸経費に分散して計上した表です
A26: 88 Greenwich #3101 | B26: 2024 | C26: 45412 | D26: 45443 | E26: 45473 | F26: 45504 | G26: 2025 | H26: 45535 | I26: 45565 | J26: 45596 | K26: 45626 | L26: 45657 | M26: 45688 | N26: 45716 | O26: 45747 | P26: 45777 | Q26: 45808 | R26: 45838 | S26: 45869 | T26: 2026 | U26: 45900 | V26: 45930 | W26: 45961 | X26: 45991 | Y26: 46022 | Z26: 46053 | AA26: 46081 | AB26: 46112 | AC26: 46142 | AD26: 46173 | AE26: 46203 | AF26: 46234
A27: 取得簿価(円) | B27: =B28*150 -> 149850000
A28: 取得簿価(ドル) | B28: 999000
A29: 賃料収入(円) | B29: =B31*B30 -> 686250 | C29: =C30*C31 -> 0 | D29: =D30*D31 -> 22752.378 | E29: =E30*E31 -> 724815 | F29: =F30*F31 -> 685980 | H29: =H30*H31 -> 651600 | I29: =I30*I31 -> 652989.75 | J29: =J30*J31 -> 702903 | K29: =K30*K31 -> 689635.5 | L29: =L30*L31 -> 723673.5 | M29: =M30*M31 -> 706517.25 | N29: =N30*N31 -> 684740.25 | O29: =O30*O31 -> 684054 | ... S29: =S30*S31 -> 683459.25 | U29: =U30*U31 -> 672159 | V29: =V30*V31 -> 692292 | W29: =W30*W31 -> 716565 | X29: =X30*X31 -> 728329.5 | Y29: =Y30*Y31 -> 728004 | Z29: =Z30*Z31 -> 714519 | AA29: =AA30*AA31 -> 724516.5 | AB29: =AB30*AB31 -> 743442 | ... AF29: =AF30*AF31 -> 0
A30: 為替レート(ドル円)TTM | B30: 150 | C30: ='NY不動産(総計)'!C30 -> 156.9 | D30: ='NY不動産(総計)'!D30 -> 156.74 | E30: ='NY不動産(総計)'!E30 -> 161.07 | F30: ='NY不動産(総計)'!F30 -> 152.44 | H30: ='NY不動産(総計)'!H30 -> 144.8 | I30: ='NY不動産(総計)'!I30 -> 142.73 | J30: ='NY不動産(総計)'!J30 -> 153.64 | K30: ='NY不動産(総計)'!K30 -> 150.74 | L30: ='NY不動産(総計)'!L30 -> 158.18 | M30: ='NY不動産(総計)'!M30 -> 154.43 | N30: ='NY不動産(総計)'!N30 -> 149.67 | O30: ='NY不動産(総計)'!O30 -> 149.52 | ... S30: ='NY不動産(総計)'!S30 -> 149.39 | U30: ='NY不動産(総計)'!U30 -> 146.92 | V30: ='NY不動産(総計)'!V30 -> 148.88 | W30: ='NY不動産(総計)'!W30 -> 154.1 | X30: ='NY不動産(総計)'!X30 -> 156.63 | Y30: ='NY不動産(総計)'!Y30 -> 156.56 | Z30: ='NY不動産(総計)'!Z30 -> 153.66 | AA30: ='NY不動産(総計)'!AA30 -> 155.81 | AB30: ='NY不動産(総計)'!AB30 -> 159.88 | ... AF30: ='NY不動産(総計)'!AF30 -> 0
A31: 賃料収入(ドル) | B31: 4575 | D31: 145.16 | E31: 4500 | F31: 4500 | H31: 4500 | I31: 4575 | J31: 4575 | K31: 4575 | L31: 4575 | M31: 4575 | N31: 4575 | O31: 4575 | P31: 4575 | Q31: 4575 | R31: 4575 | S31: 4575 | U31: 4575 | V31: 4650 | W31: 4650 | X31: 4650 | Y31: 4650 | Z31: 4650 | AA31: 4650 | AB31: 4650 | AC31: 4650
A32: 減価償却費(円) | B32: 136057268 | D32: 1269867 | E32: 1269867 | F32: 1269869 | H32: 1269867 | I32: 1269867 | J32: 1269867 | K32: 1269867 | L32: 1269867 | M32: 1269872 | N32: 1269867 | O32: 1269867 | P32: 1269867 | Q32: 1269867 | R32: 1269867 | S32: 1269872 | U32: 1269867 | V32: 1269867 | W32: 1269867 | X32: 1269867 | Y32: 1269867 | Z32: 1269872 | AA32: 1269867 | AB32: 1269867 | AC32: 1269867 | AD32: 1269867 | AE32: 1269867 | AF32: 1269872
A33: 減価償却費(ドル)
A34: 残存簿価(円) | B34: 136057268 | D34: =SUM(B34-D32) -> 134787401 | E34: =SUM(D34-E32) -> 133517534 | F34: =SUM(E34-F32) -> 132247665 | H34: =SUM(F34-H32) -> 130977798 | I34: =SUM(H34-I32) -> 129707931 | J34: =SUM(I34-J32) -> 128438064 | K34: =SUM(J34-K32) -> 127168197 | L34: =SUM(K34-L32) -> 125898330 | M34: =SUM(L34-M32) -> 124628458 | N34: =SUM(M34-N32) -> 123358591 | O34: =SUM(N34-O32) -> 122088724 | P34: =SUM(O34-P32) -> 120818857 | ... S34: =SUM(R34-S32) -> 117009251 | U34: =SUM(S34-U32) -> 115739384 | V34: =SUM(U34-V32) -> 114469517 | W34: =SUM(V34-W32) -> 113199650 | X34: =SUM(W34-X32) -> 111929783 | Y34: =SUM(X34-Y32) -> 110659916 | Z34: =SUM(Y34-Z32) -> 109390044 | AA34: =SUM(Z34-AA32) -> 108120177 | AB34: =SUM(AA34-AB32) -> 106850310 | AC34: =SUM(AB34-AC32) -> 105580443 | ... AF34: =SUM(AE34-AF32) -> 101770837
A35: 残存簿価(ドル)
A36: 管理費(ドル) | F36: 270 | H36: 270 | I36: 274.5 | J36: 274.5 | K36: 274.5 | L36: 274.5 | M36: 274.5 | N36: 274.5 | O36: 274.5 | P36: 274.5 | Q36: 274.5 | R36: 274.5 | S36: 274.5 | U36: 274.5 | V36: 279 | W36: 279 | X36: 279 | Y36: 279 | Z36: 279 | AA36: 279 | AB36: 279 | AC36: 279
A37: 諸経費(税金、募集経費等)(ドル) | B37: 16101.33 | D37: 36.56 | E37: 1133.38 | F37: 1176.9 | H37: 3932 | I37: 2273.78 | J37: 2517.79 | K37: 2217.79 | L37: 2217.79 | M37: 2217.79 | N37: 2217.79 | O37: 2336.73 | P37: 2875.66 | Q37: 2336.73 | R37: 14333.98 | S37: 2358.3 | U37: 3356.95 | V37: 2411.51 | W37: 2481.51 | X37: 2641.39 | Y37: 2641.39 | Z37: 2641.39 | AA37: 2641.39 | AB37: 1049.95 | AC37: 1049.95 | AD37: 1049.95
A38: ネット賃貸収入利回り(円)
A39: ネット賃貸収入利回り(ドル)
A40: 取得時簿価利回り(円) | B40: =B38/B27 -> 0
A41: 取得時簿価利回り(ドル)
A42: 残存簿価利回り(円) | B42: =B38/B34 -> 0
A43: 残存簿価利回り(ドル)
A44: CF(円) | C44: =SUM(C30*C45) -> 0 | D44: =SUM(D30*D45) -> 17021.964 | E44: =SUM(E30*E45) -> 542261.48 | F44: =SUM(F30*F45) -> 465414.56 | H44: =SUM(H30*H45) -> 43150.4 | I44: =SUM(I30*I45) -> 289273.75 | J44: =SUM(J30*J45) -> 273895.56 | K44: =SUM(K30*K45) -> 313947.71 | L44: =SUM(L30*L45) -> 329443.07 | M44: =SUM(M30*M45) -> 321632.91 | N44: =SUM(N30*N45) -> 311719.21 | O44: =SUM(O30*O45) -> 293622.89 | ... S44: =SUM(S30*S45) -> 290145.26 | U44: =SUM(U30*U45) -> 138626.37 | V44: =SUM(V30*V45) -> 291728.87 | W44: =SUM(W30*W45) -> 291170.41 | X44: =SUM(X30*X45) -> 270908.81 | Y44: =SUM(Y30*Y45) -> 270787.74 | Z44: =SUM(Z30*Z45) -> 265771.87 | AA44: =SUM(AA30*AA45) -> 269490.53 | AB44: =SUM(AB30*AB45) -> 530969.47 | ... AF44: =SUM(AF30*AF45) -> 0
A45: CF(ドル) | C45: =SUM(C31-C36-C37) -> 0 | D45: =SUM(D31-D36-D37) -> 108.6 | E45: =SUM(E31-E36-E37) -> 3366.62 | F45: =SUM(F31-F36-F37) -> 3053.1 | H45: =SUM(H31-H36-H37) -> 298 | I45: =SUM(I31-I36-I37) -> 2026.72 | J45: =SUM(J31-J36-J37) -> 1782.71 | K45: =SUM(K31-K36-K37) -> 2082.71 | L45: =SUM(L31-L36-L37) -> 2082.71 | M45: =SUM(M31-M36-M37) -> 2082.71 | N45: =SUM(N31-N36-N37) -> 2082.71 | O45: =SUM(O31-O36-O37) -> 1963.77 | ... S45: =SUM(S31-S36-S37) -> 1942.2 | U45: =SUM(U31-U36-U37) -> 943.55 | V45: =SUM(V31-V36-V37) -> 1959.49 | W45: =SUM(W31-W36-W37) -> 1889.49 | X45: =SUM(X31-X36-X37) -> 1729.61 | Y45: =SUM(Y31-Y36-Y37) -> 1729.61 | Z45: =SUM(Z31-Z36-Z37) -> 1729.61 | AA45: =SUM(AA31-AA36-AA37) -> 1729.61 | AB45: =SUM(AB31-AB36-AB37) -> 3321.05 | ... AF45: =SUM(AF31-AF36-AF37) -> 0
A46: PL(円)
A47: PL(ドル)
R51: 1050.02 | S51: 1049.91
R52: 1049.94 | S52: 1049.95
R53: 1049.94 | S53: 1049.95
R54: 1049.94 | S54: 1049.95
R55: 1049.94 | S55: 1049.95
R56: 1049.94 | S56: 1049.95
R57: 1049.94 | S57: 1049.95
R58: 1049.94 | S58: 1049.95
R59: 1049.94 | S59: 1049.95
R60: 1049.94 | S60: 1049.95
R61: 1049.94 | S61: 1049.95
R62: 1049.94 | S62: 1049.95
R63: =SUM(R51:R62) -> 12599.36 | S63: =SUM(S51:S62) -> 12599.36

Sheet 93Worth#206
A1: 93 Worth Street #206 | B1: 2024 | C1: 45412 | D1: 45443 | E1: 45473 | F1: 45504 | G1: 2025 | H1: 45535 | I1: 45565 | J1: 45596 | K1: 45626 | L1: 45657 | M1: 45688 | N1: 45716 | O1: 45747 | P1: 45777 | Q1: 45808 | R1: 45838 | S1: 45869 | T1: 2026 | U1: 45900 | V1: 45930 | W1: 45961 | X1: 45991 | Y1: 46022 | Z1: 46053 | AA1: 46081 | AB1: 46112 | AC1: 46142 | AD1: 46173 | AE1: 46203 | AF1: 46234
A2: 取得簿価(円) | B2: =B3*150 -> 146559000
A3: 取得簿価(ドル) | B3: 977060
A4: 賃料収入(円) | B4: =B6*B5 -> 652500 | F4: =F5*F6 -> 509448.38 | H4: =H5*H6 -> 608160 | I4: =I5*I6 -> 599466 | J4: =J5*J6 -> 654116.15 | K4: =K5*K6 -> 644520.53 | L4: =L5*L6 -> 673462.42 | M4: =M5*M6 -> 656647.17 | N4: =N5*N6 -> 634790.88 | O4: =O5*O6 -> 633652.3 | ... S4: =S5*S6 -> 655819.11 | U4: =U5*U6 -> 650730.72 | V4: =V5*V6 -> 661249.03 | W4: =W5*W6 -> 685210.27 | X4: =X5*X6 -> 694937.55 | Y4: =Y5*Y6 -> 695344.02 | Z4: =Z5*Z6 -> 676409.78 | AA4: =AA5*AA6 -> 685749.41 | AB4: =AB5*AB6 -> 702511.12 | ... AF4: =AF5*AF6 -> 0
A5: 為替レート(ドル円)TTM | B5: ='NY不動産(総計)'!B5 -> 150 | C5: ='NY不動産(総計)'!C5 -> 156.9 | D5: ='NY不動産(総計)'!D5 -> 156.74 | E5: ='NY不動産(総計)'!E5 -> 161.07 | F5: ='NY不動産(総計)'!F5 -> 152.44 | H5: ='NY不動産(総計)'!H5 -> 144.8 | I5: ='NY不動産(総計)'!I5 -> 142.73 | J5: ='NY不動産(総計)'!J5 -> 153.64 | K5: ='NY不動産(総計)'!K5 -> 150.74 | L5: ='NY不動産(総計)'!L5 -> 158.18 | M5: ='NY不動産(総計)'!M5 -> 154.43 | N5: ='NY不動産(総計)'!N5 -> 149.67 | O5: ='NY不動産(総計)'!O5 -> 149.52 | ... S5: ='NY不動産(総計)'!S5 -> 149.39 | U5: ='NY不動産(総計)'!U5 -> 146.92 | V5: ='NY不動産(総計)'!V5 -> 148.88 | W5: ='NY不動産(総計)'!W5 -> 154.1 | X5: ='NY不動産(総計)'!X5 -> 156.63 | Y5: ='NY不動産(総計)'!Y5 -> 156.56 | Z5: ='NY不動産(総計)'!Z5 -> 153.66 | AA5: ='NY不動産(総計)'!AA5 -> 155.81 | AB5: ='NY不動産(総計)'!AB5 -> 159.88 | ... AF5: ='NY不動産(総計)'!AF5 -> 0
A6: 賃料収入(ドル) | B6: 4350 | C6: 0 | D6: 0 | E6: 0 | F6: 3341.96 | H6: 4200 | I6: 4200 | J6: 4257.46 | K6: 4275.71 | L6: 4257.57 | M6: 4252.07 | N6: 4241.27 | O6: 4237.91 | P6: 4379.46 | Q6: 4389.11 | R6: 4385.38 | S6: 4389.98 | U6: 4429.15 | V6: 4441.49 | W6: 4446.53 | X6: 4436.81 | Y6: 4441.39 | Z6: 4401.99 | AA6: 4401.19 | AB6: 4393.99 | AF6: 0
A7: 減価償却費(円) | B7: 132753513 | F7: 1239032 | H7: 1239032 | I7: 1239032 | J7: 1239032 | K7: 1239032 | L7: 1239032 | M7: 1239036 | N7: 1239032 | O7: 1239032 | P7: 1239032 | Q7: 1239032 | R7: 1239032 | S7: 1239037 | U7: 1239032 | V7: 1239032 | W7: 1239032 | X7: 1239032 | Y7: 1239032 | Z7: 1239036 | AA7: 1239032 | AB7: 1239032 | AC7: 1239032 | AD7: 1239032 | AE7: 1239032 | AF7: 1239037
A8: 減価償却費(ドル)
A9: 残存簿価(円) | B9: 132753513 | F9: =SUM(B9-F7) -> 131514481 | H9: =SUM(F9-H7) -> 130275449 | I9: =SUM(H9-I7) -> 129036417 | J9: =SUM(I9-J7) -> 127797385 | K9: =SUM(J9-K7) -> 126558353 | L9: =SUM(K9-L7) -> 125319321 | M9: =SUM(L9-M7) -> 124080285 | N9: =SUM(M9-N7) -> 122841253 | O9: =SUM(N9-O7) -> 121602221 | P9: =SUM(O9-P7) -> 120363189 | ... S9: =SUM(R9-S7) -> 116646088 | U9: =SUM(S9-U7) -> 115407056 | V9: =SUM(U9-V7) -> 114168024 | W9: =SUM(V9-W7) -> 112928992 | X9: =SUM(W9-X7) -> 111689960 | Y9: =SUM(X9-Y7) -> 110450928 | Z9: =SUM(Y9-Z7) -> 109211892 | AA9: =SUM(Z9-AA7) -> 107972860 | AB9: =SUM(AA9-AB7) -> 106733828 | AC9: =SUM(AB9-AC7) -> 105494796 | ... AF9: =SUM(AE9-AF7) -> 101777695
A10: 残存簿価(ドル)
A11: 管理費(ドル) | F11: 500 | H11: 336 | I11: 336 | J11: 336 | K11: 336 | L11: 336 | M11: 336 | N11: 336 | O11: 336 | P11: 348 | Q11: 348 | R11: 348 | S11: 304.5 | U11: 304.5 | V11: 304.5 | W11: 304.5 | X11: 304.5 | Y11: 304.5 | Z11: 304.5 | AA11: 304.5 | AB11: 304.5 | AG11: =SUM(C36:AF36) -> 6972.5 | AH11: 管理費
A12: 諸経費(税金、募集経費等)(ドル) | B12: 30144.37 | F12: 456.96 | H12: 832.34 | I12: 7379.16 | J12: 910.57 | K12: 892.43 | L12: 886.93 | M12: 893.37 | N12: 890.01 | O12: 1131.56 | P12: 1326.21 | Q12: 887.48 | R12: 10070.21 | S12: 931.25 | U12: 1266.95 | V12: 948.63 | W12: 938.91 | X12: 943.49 | Y12: 1484.95 | Z12: 957.1 | AA12: 949.9 | AB12: 960.43 | AG12: 7462.64 | AH12: コモンチャージ
A13: ネット賃貸収入利回り(円) | AG13: 15074.99 | AH13: 固定資産税
A14: ネット賃貸収入利回り(ドル) | AG14: 4950.85 | AH14: 修繕・雑費・その他支出
A15: 取得時簿価利回り(円) | B15: =B13/B2 -> 0 | AG15: =SUM(AG11:AG14) -> 34460.98 | AH15: 合計
A16: 取得時簿価利回り(ドル)
A17: 残存簿価利回り(円) | B17: =B13/B9 -> 0
A18: 残存簿価利回り(ドル)
A19: CF(円) | C19: =C20*C5 -> 0 | D19: =D20*D5 -> 0 | E19: =E20*E5 -> 0 | F19: =F20*F5 -> 363569.4 | H19: =H20*H5 -> 438984.37 | I19: =I20*I5 -> -501718.79 | J19: =J20*J5 -> 462593.14 | K19: =K20*K5 -> 459346.99 | L19: =L20*L5 -> 480019.36 | M19: =M20*M5 -> 466795.56 | N19: =N20*N5 -> 451293.96 | O19: =O20*O5 -> 414222.73 | ... S19: =S20*S5 -> 471210.42 | U19: =U20*U5 -> 419853.28 | V19: =V20*V5 -> 474683.04 | W19: =W20*W5 -> 493600.79 | X19: =X20*X5 -> 499464.88 | Y19: =Y20*Y5 -> 415187.73 | Z19: =Z20*Z5 -> 482552.33 | AA19: =AA20*AA5 -> 490301.35 | AB19: =AB20*AB5 -> 500274.11 | ... AF19: =AF20*AF5 -> 0
A20: CF(ドル) | C20: =SUM(C6-C11-C12) -> 0 | D20: =SUM(D6-D11-D12) -> 0 | E20: =SUM(E6-E11-E12) -> 0 | F20: =SUM(F6-F11-F12) -> 2385 | H20: =SUM(H6-H11-H12) -> 3031.66 | I20: =SUM(I6-I11-I12) -> -3515.16 | J20: =SUM(J6-J11-J12) -> 3010.89 | K20: =SUM(K6-K11-K12) -> 3047.28 | L20: =SUM(L6-L11-L12) -> 3034.64 | M20: =SUM(M6-M11-M12) -> 3022.7 | N20: =SUM(N6-N11-N12) -> 3015.26 | O20: =SUM(O6-O11-O12) -> 2770.35 | ... S20: =SUM(S6-S11-S12) -> 3154.23 | U20: =SUM(U6-U11-U12) -> 2857.7 | V20: =SUM(V6-V11-V12) -> 3188.36 | W20: =SUM(W6-W11-W12) -> 3203.12 | X20: =SUM(X6-X11-X12) -> 3188.82 | Y20: =SUM(Y6-Y11-Y12) -> 2651.94 | Z20: =SUM(Z6-Z11-Z12) -> 3140.39 | AA20: =SUM(AA6-AA11-AA12) -> 3146.79 | AB20: =SUM(AB6-AB11-AB12) -> 3129.06 | ... AF20: =SUM(AF6-AF11-AF12) -> 0
A21: PL(円)
A22: PL(ドル)
A24: 購入日 | B24: 45481
A25: 下記表は固都税を各月の諸経費に分散して計上した表です
A26: 93 Worth Street #206 | B26: 2024 | C26: 45412 | D26: 45443 | E26: 45473 | F26: 45504 | G26: 2025 | H26: 45535 | I26: 45565 | J26: 45596 | K26: 45626 | L26: 45657 | M26: 45688 | N26: 45716 | O26: 45747 | P26: 45777 | Q26: 45808 | R26: 45838 | S26: 45869 | T26: 2026 | U26: 45900 | V26: 45930 | W26: 45961 | X26: 45991 | Y26: 46022 | Z26: 46053 | AA26: 46081 | AB26: 46112 | AC26: 46142 | AD26: 46173 | AE26: 46203 | AF26: 46234
A27: 取得簿価(円) | B27: =B28*150 -> 146559000
A28: 取得簿価(ドル) | B28: 977060
A29: 賃料収入(円) | B29: =B31*B30 -> 652500 | F29: =F30*F31 -> 509448.38 | H29: =H30*H31 -> 608160 | I29: =I30*I31 -> 599466 | J29: =J30*J31 -> 654116.15 | K29: =K30*K31 -> 644520.53 | L29: =L30*L31 -> 673462.42 | M29: =M30*M31 -> 656647.17 | N29: =N30*N31 -> 634790.88 | O29: =O30*O31 -> 633652.3 | ... S29: =S30*S31 -> 655819.11 | U29: =U30*U31 -> 650730.72 | V29: =V30*V31 -> 661249.03 | W29: =W30*W31 -> 685210.27 | X29: =X30*X31 -> 694937.55 | Y29: =Y30*Y31 -> 695344.02 | Z29: =Z30*Z31 -> 676409.78 | AA29: =AA30*AA31 -> 685749.41 | AB29: =AB30*AB31 -> 702511.12 | ... AF29: =AF30*AF31 -> 0
A30: 為替レート(ドル円)TTM | B30: ='NY不動産(総計)'!B30 -> 150 | C30: ='NY不動産(総計)'!C30 -> 156.9 | D30: ='NY不動産(総計)'!D30 -> 156.74 | E30: ='NY不動産(総計)'!E30 -> 161.07 | F30: ='NY不動産(総計)'!F30 -> 152.44 | H30: ='NY不動産(総計)'!H30 -> 144.8 | I30: ='NY不動産(総計)'!I30 -> 142.73 | J30: ='NY不動産(総計)'!J30 -> 153.64 | K30: ='NY不動産(総計)'!K30 -> 150.74 | L30: ='NY不動産(総計)'!L30 -> 158.18 | M30: ='NY不動産(総計)'!M30 -> 154.43 | N30: ='NY不動産(総計)'!N30 -> 149.67 | O30: ='NY不動産(総計)'!O30 -> 149.52 | ... S30: ='NY不動産(総計)'!S30 -> 149.39 | U30: ='NY不動産(総計)'!U30 -> 146.92 | V30: ='NY不動産(総計)'!V30 -> 148.88 | W30: ='NY不動産(総計)'!W30 -> 154.1 | X30: ='NY不動産(総計)'!X30 -> 156.63 | Y30: ='NY不動産(総計)'!Y30 -> 156.56 | Z30: ='NY不動産(総計)'!Z30 -> 153.66 | AA30: ='NY不動産(総計)'!AA30 -> 155.81 | AB30: ='NY不動産(総計)'!AB30 -> 159.88 | ... AF30: ='NY不動産(総計)'!AF30 -> 0
A31: 賃料収入(ドル) | B31: 4350 | C31: 0 | D31: 0 | E31: 0 | F31: 3341.96 | H31: 4200 | I31: 4200 | J31: 4257.46 | K31: 4275.71 | L31: 4257.57 | M31: 4252.07 | N31: 4241.27 | O31: 4237.91 | P31: 4379.46 | Q31: 4389.11 | R31: 4385.38 | S31: 4389.98 | U31: 4429.15 | V31: 4441.49 | W31: 4446.53 | X31: 4436.81 | Y31: 4441.39 | Z31: 4401.99 | AA31: 4401.19 | AB31: 4393.99
A32: 減価償却費(円) | B32: 132753513 | F32: 1239032 | H32: 1239032 | I32: 1239032 | J32: 1239032 | K32: 1239032 | L32: 1239032 | M32: 1239036 | N32: 1239032 | O32: 1239032 | P32: 1239032 | Q32: 1239032 | R32: 1239032 | S32: 1239037 | U32: 1239032 | V32: 1239032 | W32: 1239032 | X32: 1239032 | Y32: 1239032 | Z32: 1239036 | AA32: 1239032 | AB32: 1239032 | AC32: 1239032 | AD32: 1239032 | AE32: 1239032 | AF32: 1239037
A33: 減価償却費(ドル)
A34: 残存簿価(円) | B34: 132753513 | F34: =SUM(B34-F32) -> 131514481 | H34: =SUM(F34-H32) -> 130275449 | I34: =SUM(H34-I32) -> 129036417 | J34: =SUM(I34-J32) -> 127797385 | K34: =SUM(J34-K32) -> 126558353 | L34: =SUM(K34-L32) -> 125319321 | M34: =SUM(L34-M32) -> 124080285 | N34: =SUM(M34-N32) -> 122841253 | O34: =SUM(N34-O32) -> 121602221 | P34: =SUM(O34-P32) -> 120363189 | ... S34: =SUM(R34-S32) -> 116646088 | U34: =SUM(S34-U32) -> 115407056 | V34: =SUM(U34-V32) -> 114168024 | W34: =SUM(V34-W32) -> 112928992 | X34: =SUM(W34-X32) -> 111689960 | Y34: =SUM(X34-Y32) -> 110450928 | Z34: =SUM(Y34-Z32) -> 109211892 | AA34: =SUM(Z34-AA32) -> 107972860 | AB34: =SUM(AA34-AB32) -> 106733828 | AC34: =SUM(AB34-AC32) -> 105494796 | ... AF34: =SUM(AE34-AF32) -> 101777695
A35: 残存簿価(ドル)
A36: 管理費(ドル) | F36: 500 | H36: 336 | I36: 336 | J36: 336 | K36: 336 | L36: 336 | M36: 336 | N36: 336 | O36: 336 | P36: 348 | Q36: 348 | R36: 348 | S36: 304.5 | U36: 304.5 | V36: 304.5 | W36: 304.5 | X36: 304.5 | Y36: 304.5 | Z36: 304.5 | AA36: 304.5 | AB36: 304.5
A37: 諸経費(税金、募集経費等)(ドル) | B37: 30144.37 | F37: 456.96 | H37: 832.34 | I37: 1645.88 | J37: 1627.23 | K37: 1609.09 | L37: 1603.59 | M37: 1610.03 | N37: 1606.67 | O37: 1848.22 | P37: 2042.87 | Q37: 1604.14 | R37: 2163.85 | S37: 1650.01 | U37: 1985.71 | V37: 1667.39 | W37: 1657.67 | X37: 1662.25 | Y37: 2203.71 | Z37: 1675.86 | AA37: 1668.66 | AB37: 718.76 | AC37: 718.76 | AD37: 718.76
A38: ネット賃貸収入利回り(円)
A39: ネット賃貸収入利回り(ドル)
A40: 取得時簿価利回り(円) | B40: =B38/B27 -> 0
A41: 取得時簿価利回り(ドル)
A42: 残存簿価利回り(円) | B42: =B38/B34 -> 0
A43: 残存簿価利回り(ドル)
A44: CF(円) | C44: =C45*C30 -> 0 | D44: =D45*D30 -> 0 | E44: =E45*E30 -> 0 | F44: =F45*F30 -> 363569.4 | H44: =H45*H30 -> 438984.37 | I44: =I45*I30 -> 316592.27 | J44: =J45*J30 -> 352485.5 | K44: =K45*K30 -> 351317.66 | L44: =L45*L30 -> 366658.08 | M44: =M45*M30 -> 356121.76 | N44: =N45*N30 -> 344031.46 | O44: =O45*O30 -> 307067.73 | ... S44: =S45*S30 -> 363834.86 | U44: =U45*U30 -> 314253.06 | V44: =V45*V30 -> 367674.05 | W44: =W45*W30 -> 382839.88 | X44: =X45*X30 -> 386885.5 | Y44: =Y45*Y30 -> 302658.66 | Z44: =Z45*Z30 -> 372107.67 | AA44: =AA45*AA30 -> 378311.35 | AB44: =AB45*AB30 -> 538912.31 | ... AF44: =AF45*AF30 -> 0
A45: CF(ドル) | C45: =SUM(C31-C36-C37) -> 0 | D45: =SUM(D31-D36-D37) -> 0 | E45: =SUM(E31-E36-E37) -> 0 | F45: =SUM(F31-F36-F37) -> 2385 | H45: =SUM(H31-H36-H37) -> 3031.66 | I45: =SUM(I31-I36-I37) -> 2218.12 | J45: =SUM(J31-J36-J37) -> 2294.23 | K45: =SUM(K31-K36-K37) -> 2330.62 | L45: =SUM(L31-L36-L37) -> 2317.98 | M45: =SUM(M31-M36-M37) -> 2306.04 | N45: =SUM(N31-N36-N37) -> 2298.6 | O45: =SUM(O31-O36-O37) -> 2053.69 | ... S45: =SUM(S31-S36-S37) -> 2435.47 | U45: =SUM(U31-U36-U37) -> 2138.94 | V45: =SUM(V31-V36-V37) -> 2469.6 | W45: =SUM(W31-W36-W37) -> 2484.36 | X45: =SUM(X31-X36-X37) -> 2470.06 | Y45: =SUM(Y31-Y36-Y37) -> 1933.18 | Z45: =SUM(Z31-Z36-Z37) -> 2421.63 | AA45: =SUM(AA31-AA36-AA37) -> 2428.03 | AB45: =SUM(AB31-AB36-AB37) -> 3370.73 | ... AF45: =SUM(AF31-AF36-AF37) -> 0
A46: PL(円)
A47: PL(ドル)
R50: 8625.13
R51: 718.77
R52: 718.76
R53: 718.76
R54: 718.76
R55: 718.76
R56: 718.76
R57: 718.76
R58: 718.76
R59: 718.76
R60: 718.76
R61: 718.76
R62: 718.76
R63: =SUM(R51:R62) -> 8625.13

Sheet 159W53rd#21F
A1: 159 West 53rd Street #21F | B1: 2024 | C1: 45412 | D1: 45443 | E1: 45473 | F1: 45504 | G1: 2025 | H1: 45535 | I1: 45565 | J1: 45596 | K1: 45626 | L1: 45657 | M1: 45688 | N1: 45716 | O1: 45747 | P1: 45777 | Q1: 45808 | R1: 45838 | S1: 45869 | T1: 2026 | U1: 45900 | V1: 45930 | W1: 45961 | X1: 45991 | Y1: 46022 | Z1: 46053 | AA1: 46081 | AB1: 46112 | AC1: 46142 | AD1: 46173 | AE1: 46203 | AF1: 46234
A2: 取得簿価(円) | B2: =B3*150 -> 135000000
A3: 取得簿価(ドル) | B3: 900000
A4: 賃料収入(円) | B4: =B5*B6 -> 697500 | J4: =J5*J6 -> 4609.2 | K4: =K5*K6 -> 478733.66 | L4: =L5*L6 -> 738431.69 | M4: =M5*M6 -> 725445.74 | N4: =N5*N6 -> 703085.3 | O4: =O5*O6 -> 702380.67 | P4: =P5*P6 -> 669732.55 | Q4: =Q5*Q6 -> 675839.4 | ... S4: =S5*S6 -> 701769.98 | U4: =U5*U6 -> 690166.98 | V4: =V5*V6 -> 699374.22 | W4: =W5*W6 -> 723895.54 | X4: =X5*X6 -> 728329.5 | Y4: =Y5*Y6 -> 743279.56 | Z4: =Z5*Z6 -> 729511.61 | AA4: =AA5*AA6 -> 739718.88 | AB4: =AB5*AB6 -> 759041.49 | ... AF4: =AF5*AF6 -> 0
A5: 為替レート(ドル円)TTM | B5: ='NY不動産(総計)'!B5 -> 150 | C5: ='NY不動産(総計)'!C5 -> 156.9 | D5: ='NY不動産(総計)'!D5 -> 156.74 | E5: ='NY不動産(総計)'!E5 -> 161.07 | F5: ='NY不動産(総計)'!F5 -> 152.44 | H5: ='NY不動産(総計)'!H5 -> 144.8 | I5: ='NY不動産(総計)'!I5 -> 142.73 | J5: ='NY不動産(総計)'!J5 -> 153.64 | K5: ='NY不動産(総計)'!K5 -> 150.74 | L5: ='NY不動産(総計)'!L5 -> 158.18 | M5: ='NY不動産(総計)'!M5 -> 154.43 | N5: ='NY不動産(総計)'!N5 -> 149.67 | O5: ='NY不動産(総計)'!O5 -> 149.52 | ... S5: ='NY不動産(総計)'!S5 -> 149.39 | U5: ='NY不動産(総計)'!U5 -> 146.92 | V5: ='NY不動産(総計)'!V5 -> 148.88 | W5: ='NY不動産(総計)'!W5 -> 154.1 | X5: ='NY不動産(総計)'!X5 -> 156.63 | Y5: ='NY不動産(総計)'!Y5 -> 156.56 | Z5: ='NY不動産(総計)'!Z5 -> 153.66 | AA5: ='NY不動産(総計)'!AA5 -> 155.81 | AB5: ='NY不動産(総計)'!AB5 -> 159.88 | ... AF5: ='NY不動産(総計)'!AF5 -> 0
A6: 賃料収入(ドル) | B6: 4650 | C6: 0 | D6: 0 | E6: 0 | F6: 0 | H6: 0 | I6: 0 | J6: 30 | K6: 3175.89 | L6: 4668.3 | M6: 4697.57 | N6: 4697.57 | O6: 4697.57 | P6: 4697.57 | Q6: 4697.57 | R6: 4697.57 | S6: 4697.57 | U6: 4697.57 | V6: 4697.57 | W6: 4697.57 | X6: 4650 | Y6: 4747.57 | Z6: 4747.57 | AA6: 4747.57 | AB6: 4747.57
A7: 減価償却費(円) | B7: 104765846 | I7: 977814 | J7: 977814 | K7: 977814 | L7: 977814 | M7: 977816 | N7: 977814 | O7: 977814 | P7: 977814 | Q7: 977814 | R7: 977814 | S7: 977817 | U7: 977814 | V7: 977814 | W7: 977814 | X7: 977814 | Y7: 977814 | Z7: 977817 | AA7: 977814 | AB7: 977814 | AC7: 977814 | AD7: 977814 | AE7: 977814 | AF7: 977817
A8: 減価償却費(ドル)
A9: 残存簿価(円) | B9: 104765846 | I9: =SUM(B9-I7) -> 103788032 | J9: =SUM(I9-J7) -> 102810218 | K9: =SUM(J9-K7) -> 101832404 | L9: =SUM(K9-L7) -> 100854590 | M9: =SUM(L9-M7) -> 99876774 | N9: =SUM(M9-N7) -> 98898960 | O9: =SUM(N9-O7) -> 97921146 | P9: =SUM(O9-P7) -> 96943332 | Q9: =SUM(P9-Q7) -> 95965518 | ... S9: =SUM(R9-S7) -> 94009887 | U9: =SUM(S9-U7) -> 93032073 | V9: =SUM(U9-V7) -> 92054259 | W9: =SUM(V9-W7) -> 91076445 | X9: =SUM(W9-X7) -> 90098631 | Y9: =SUM(X9-Y7) -> 89120817 | Z9: =SUM(Y9-Z7) -> 88143000 | AA9: =SUM(Z9-AA7) -> 87165186 | AB9: =SUM(AA9-AB7) -> 86187372 | AC9: =SUM(AB9-AC7) -> 85209558 | ... AF9: =SUM(AE9-AF7) -> 82276113
A10: 残存簿価(ドル)
A11: 管理費(ドル) | J11: 600 | K11: 5635.72 | L11: 368 | M11: 368 | N11: 368 | O11: 368 | P11: 368 | Q11: 368 | R11: 368 | S11: 322 | U11: 322 | V11: 322 | W11: 322 | X11: 325.5 | Y11: 325.5 | Z11: 325.5 | AA11: 325.5 | AG11: =SUM(C36:AF36) -> 11401.72 | AH11: 管理費
A12: 諸経費(税金、募集経費等)(ドル) | B12: 36181.22 | I12: 168.33 | J12: 5219.87 | K12: 7424.99 | L12: 4360.76 | M12: 1163.02 | N12: 1163.02 | O12: 1009.97 | P12: 1009.97 | Q12: 1009.97 | R12: 14563.26 | S12: 1109.97 | U12: 1760.3 | V12: 1009.97 | W12: 1009.97 | X12: 1474.97 | Y12: 912.4 | Z12: 1009.97 | AA12: 1009.97 | AG12: 9542.95 | AH12: コモンチャージ
A13: ネット賃貸収入利回り(円) | AG13: 19121.71 | AH13: 固定資産税
A14: ネット賃貸収入利回り(ドル) | AG14: 9538.47 | AH14: 修繕・雑費・その他支出
A15: 取得時簿価利回り(円) | B15: =B13/B2 -> 0 | AG15: =SUM(AG11:AG14) -> 49604.85 | AH15: 合計
A16: 取得時簿価利回り(ドル)
A17: 残存簿価利回り(円) | B17: =B13/B9 -> 0
A18: 残存簿価利回り(ドル)
A19: CF(円) | C19: =SUM(C5*C20) -> 0 | D19: =SUM(D5*D20) -> 0 | E19: =SUM(E5*E20) -> 0 | F19: =SUM(F5*F20) -> 0 | H19: =SUM(H5*H20) -> 0 | I19: =SUM(I5*I20) -> -24025.741 | J19: =SUM(J5*J20) -> -889555.63 | K19: =SUM(K5*K20) -> -1490037.8 | L19: =SUM(L5*L20) -> -9563.5628 | M19: =SUM(M5*M20) -> 489010.32 | N19: =SUM(N5*N20) -> 473937.54 | O19: =SUM(O5*O20) -> 496346.59 | ... S19: =SUM(S5*S20) -> 487847.98 | U19: =SUM(U5*U20) -> 384235.47 | V19: =SUM(V5*V20) -> 501070.53 | W19: =SUM(W5*W20) -> 518638.96 | X19: =SUM(X5*X20) -> 446321.88 | Y19: =SUM(Y5*Y20) -> 549473.94 | Z19: =SUM(Z5*Z20) -> 524303.29 | AA19: =SUM(AA5*AA20) -> 531639.3 | AB19: =SUM(AB5*AB20) -> 759041.49 | ... AF19: =SUM(AF5*AF20) -> 0
A20: CF(ドル) | C20: =SUM(C6-C11-C12) -> 0 | D20: =SUM(D6-D11-D12) -> 0 | E20: =SUM(E6-E11-E12) -> 0 | F20: =SUM(F6-F11-F12) -> 0 | H20: =SUM(H6-H11-H12) -> 0 | I20: =SUM(I6-I11-I12) -> -168.33 | J20: =SUM(J6-J11-J12) -> -5789.87 | K20: =SUM(K6-K11-K12) -> -9884.82 | L20: =SUM(L6-L11-L12) -> -60.46 | M20: =SUM(M6-M11-M12) -> 3166.55 | N20: =SUM(N6-N11-N12) -> 3166.55 | O20: =SUM(O6-O11-O12) -> 3319.6 | ... S20: =SUM(S6-S11-S12) -> 3265.6 | U20: =SUM(U6-U11-U12) -> 2615.27 | V20: =SUM(V6-V11-V12) -> 3365.6 | W20: =SUM(W6-W11-W12) -> 3365.6 | X20: =SUM(X6-X11-X12) -> 2849.53 | Y20: =SUM(Y6-Y11-Y12) -> 3509.67 | Z20: =SUM(Z6-Z11-Z12) -> 3412.1 | AA20: =SUM(AA6-AA11-AA12) -> 3412.1 | AB20: =SUM(AB6-AB11-AB12) -> 4747.57 | ... AF20: =SUM(AF6-AF11-AF12) -> 0
A21: PL(円)
A22: PL(ドル)
A24: 購入日 | B24: 45561
A25: 下記表は固都税を各月の諸経費に分散して計上した表です
A26: 159 West 53rd Street #21F | B26: 2024 | C26: 45412 | D26: 45443 | E26: 45473 | F26: 45504 | G26: 2025 | H26: 45535 | I26: 45565 | J26: 45596 | K26: 45626 | L26: 45657 | M26: 45688 | N26: 45716 | O26: 45747 | P26: 45777 | Q26: 45808 | R26: 45838 | S26: 45869 | T26: 2026 | U26: 45900 | V26: 45930 | W26: 45961 | X26: 45991 | Y26: 46022 | Z26: 46053 | AA26: 46081 | AB26: 46112 | AC26: 46142 | AD26: 46173 | AE26: 46203 | AF26: 46234
A27: 取得簿価(円) | B27: =B28*150 -> 135000000
A28: 取得簿価(ドル) | B28: 900000
A29: 賃料収入(円) | B29: =B30*B31 -> 690000 | J29: =J30*J31 -> 4609.2 | K29: =K30*K31 -> 478733.66 | L29: =L30*L31 -> 738431.69 | M29: =M30*M31 -> 725445.74 | N29: =N30*N31 -> 703085.3 | O29: =O30*O31 -> 702380.67 | P29: =P30*P31 -> 669732.55 | Q29: =Q30*Q31 -> 675839.4 | ... S29: =S30*S31 -> 701769.98 | U29: =U30*U31 -> 690166.98 | V29: =V30*V31 -> 699374.22 | W29: =W30*W31 -> 723895.54 | X29: =X30*X31 -> 728329.5 | Y29: =Y30*Y31 -> 743279.56 | Z29: =Z30*Z31 -> 729511.61 | AA29: =AA30*AA31 -> 739718.88 | AB29: =AB30*AB31 -> 0 | ... AF29: =AF30*AF31 -> 0
A30: 為替レート(ドル円)TTM | B30: ='NY不動産(総計)'!B30 -> 150 | C30: ='NY不動産(総計)'!C30 -> 156.9 | D30: ='NY不動産(総計)'!D30 -> 156.74 | E30: ='NY不動産(総計)'!E30 -> 161.07 | F30: ='NY不動産(総計)'!F30 -> 152.44 | H30: ='NY不動産(総計)'!H30 -> 144.8 | I30: ='NY不動産(総計)'!I30 -> 142.73 | J30: ='NY不動産(総計)'!J30 -> 153.64 | K30: ='NY不動産(総計)'!K30 -> 150.74 | L30: ='NY不動産(総計)'!L30 -> 158.18 | M30: ='NY不動産(総計)'!M30 -> 154.43 | N30: ='NY不動産(総計)'!N30 -> 149.67 | O30: ='NY不動産(総計)'!O30 -> 149.52 | ... S30: ='NY不動産(総計)'!S30 -> 149.39 | U30: ='NY不動産(総計)'!U30 -> 146.92 | V30: ='NY不動産(総計)'!V30 -> 148.88 | W30: ='NY不動産(総計)'!W30 -> 154.1 | X30: ='NY不動産(総計)'!X30 -> 156.63 | Y30: ='NY不動産(総計)'!Y30 -> 156.56 | Z30: ='NY不動産(総計)'!Z30 -> 153.66 | AA30: ='NY不動産(総計)'!AA30 -> 155.81 | AB30: ='NY不動産(総計)'!AB30 -> 159.88 | ... AF30: ='NY不動産(総計)'!AF30 -> 0
A31: 賃料収入(ドル) | B31: 4600 | C31: 0 | D31: 0 | E31: 0 | F31: 0 | H31: 0 | I31: 0 | J31: 30 | K31: 3175.89 | L31: 4668.3 | M31: 4697.57 | N31: 4697.57 | O31: 4697.57 | P31: 4697.57 | Q31: 4697.57 | R31: 4697.57 | S31: 4697.57 | U31: 4697.57 | V31: 4697.57 | W31: 4697.57 | X31: 4650 | Y31: 4747.57 | Z31: 4747.57 | AA31: 4747.57
A32: 減価償却費(円) | B32: 104765846 | I32: 977814 | J32: 977814 | K32: 977814 | L32: 977814 | M32: 977816 | N32: 977814 | O32: 977814 | P32: 977814 | Q32: 977814 | R32: 977814 | S32: 977817 | U32: 977814 | V32: 977814 | W32: 977814 | X32: 977814 | Y32: 977814 | Z32: 977817 | AA32: 977814 | AB32: 977814 | AC32: 977814 | AD32: 977814 | AE32: 977814 | AF32: 977817
A33: 減価償却費(ドル)
A34: 残存簿価(円) | B34: 104765846 | I34: =SUM(B34-I32) -> 103788032 | J34: =SUM(I34-J32) -> 102810218 | K34: =SUM(J34-K32) -> 101832404 | L34: =SUM(K34-L32) -> 100854590 | M34: =SUM(L34-M32) -> 99876774 | N34: =SUM(M34-N32) -> 98898960 | O34: =SUM(N34-O32) -> 97921146 | P34: =SUM(O34-P32) -> 96943332 | Q34: =SUM(P34-Q32) -> 95965518 | ... S34: =SUM(R34-S32) -> 94009887 | U34: =SUM(S34-U32) -> 93032073 | V34: =SUM(U34-V32) -> 92054259 | W34: =SUM(V34-W32) -> 91076445 | X34: =SUM(W34-X32) -> 90098631 | Y34: =SUM(X34-Y32) -> 89120817 | Z34: =SUM(Y34-Z32) -> 88143000 | AA34: =SUM(Z34-AA32) -> 87165186 | AB34: =SUM(AA34-AB32) -> 86187372 | AC34: =SUM(AB34-AC32) -> 85209558 | ... AF34: =SUM(AE34-AF32) -> 82276113
A35: 残存簿価(ドル)
A36: 管理費(ドル) | J36: 600 | K36: 5635.72 | L36: 368 | M36: 368 | N36: 368 | O36: 368 | P36: 368 | Q36: 368 | R36: 368 | S36: 322 | U36: 322 | V36: 322 | W36: 322 | X36: 325.5 | Y36: 325.5 | Z36: 325.5 | AA36: 325.5
A37: 諸経費(税金、募集経費等)(ドル) | B37: 36181.22 | I37: 168.33 | J37: 3359.97 | K37: 8354.94 | L37: 2512.14 | M37: 2089.21 | N37: 2089.21 | O37: 1936.16 | P37: 1009.97 | Q37: 1009.97 | R37: 2139.42 | S37: 2239.41 | U37: 2889.74 | V37: 2139.41 | W37: 2139.41 | X37: 2604.41 | Y37: 2041.84 | Z37: 2139.41 | AA37: 2139.41 | AB37: 1129.44 | AC37: 1129.44 | AD37: 1129.44
A38: ネット賃貸収入利回り(円)
A39: ネット賃貸収入利回り(ドル)
A40: 取得時簿価利回り(円) | B40: =B38/B27 -> 0
A41: 取得時簿価利回り(ドル)
A42: 残存簿価利回り(円) | B42: =B38/B34 -> 0
A43: 残存簿価利回り(ドル)
A44: CF(円) | C44: =SUM(C30*C45) -> 0 | D44: =SUM(D30*D45) -> 0 | E44: =SUM(E30*E45) -> 0 | F44: =SUM(F30*F45) -> 0 | H44: =SUM(H30*H45) -> 0 | I44: =SUM(I30*I45) -> -24025.741 | J44: =SUM(J30*J45) -> -603800.59 | K44: =SUM(K30*K45) -> -1630218.4 | L44: =SUM(L30*L45) -> 282851.15 | M44: =SUM(M30*M45) -> 345978.79 | N44: =SUM(N30*N45) -> 335314.68 | O44: =SUM(O30*O45) -> 357862.66 | ... S44: =SUM(S30*S45) -> 319120.94 | U44: =SUM(U30*U45) -> 218298.14 | V44: =SUM(V30*V45) -> 332919.5 | W44: =SUM(W30*W45) -> 344592.26 | X44: =SUM(X30*X45) -> 269417.7 | Y44: =SUM(Y30*Y45) -> 372648.81 | Z44: =SUM(Z30*Z45) -> 350753.54 | AA44: =SUM(AA30*AA45) -> 355661.25 | AB44: =SUM(AB30*AB45) -> -180574.87 | ... AF44: =SUM(AF30*AF45) -> 0
A45: CF(ドル) | C45: =SUM(C31-C36-C37) -> 0 | D45: =SUM(D31-D36-D37) -> 0 | E45: =SUM(E31-E36-E37) -> 0 | F45: =SUM(F31-F36-F37) -> 0 | H45: =SUM(H31-H36-H37) -> 0 | I45: =SUM(I31-I36-I37) -> -168.33 | J45: =SUM(J31-J36-J37) -> -3929.97 | K45: =SUM(K31-K36-K37) -> -10814.77 | L45: =SUM(L31-L36-L37) -> 1788.16 | M45: =SUM(M31-M36-M37) -> 2240.36 | N45: =SUM(N31-N36-N37) -> 2240.36 | O45: =SUM(O31-O36-O37) -> 2393.41 | ... S45: =SUM(S31-S36-S37) -> 2136.16 | U45: =SUM(U31-U36-U37) -> 1485.83 | V45: =SUM(V31-V36-V37) -> 2236.16 | W45: =SUM(W31-W36-W37) -> 2236.16 | X45: =SUM(X31-X36-X37) -> 1720.09 | Y45: =SUM(Y31-Y36-Y37) -> 2380.23 | Z45: =SUM(Z31-Z36-Z37) -> 2282.66 | AA45: =SUM(AA31-AA36-AA37) -> 2282.66 | AB45: =SUM(AB31-AB36-AB37) -> -1129.44 | ... AF45: =SUM(AF31-AF36-AF37) -> 0
A46: PL(円)
A47: PL(ドル)
R50: 13553.29
Q51: 1 | R51: 1129.45
Q52: 2 | R52: 1129.44
Q53: 3 | R53: 1129.44
Q54: 4 | R54: 1129.44
Q55: 5 | R55: 1129.44
Q56: 6 | R56: 1129.44
Q57: 7 | R57: 1129.44
Q58: 8 | R58: 1129.44
Q59: 9 | R59: 1129.44
Q60: 10 | R60: 1129.44
Q61: 11 | R61: 1129.44
Q62: 12 | R62: 1129.44
R63: =SUM(R51:R62) -> 13553.29

Sheet 159W53rd#35A
A1: 159 West 53rd Street #35A | B1: 2024 | C1: 45412 | D1: 45443 | E1: 45473 | F1: 45504 | G1: 2025 | H1: 45535 | I1: 45565 | J1: 45596 | K1: 45626 | L1: 45657 | M1: 45688 | N1: 45716 | O1: 45747 | P1: 45777 | Q1: 45808 | R1: 45838 | S1: 45869 | T1: 2026 | U1: 45900 | V1: 45930 | W1: 45961 | X1: 45991 | Y1: 46022 | Z1: 46053 | AA1: 46081 | AB1: 46112 | AC1: 46142 | AD1: 46173 | AE1: 46203 | AF1: 46234
A2: 取得簿価(円) | B2: =B3*150 -> 87750000
A3: 取得簿価(ドル) | B3: 585000
A4: 賃料収入(円) | B4: =B6*B5 -> 540000 | C4: =C5*C6 -> 0 | D4: =D5*D6 -> 0 | E4: =E5*E6 -> 0 | F4: =F5*F6 -> 0 | H4: =H5*H6 -> 0 | I4: =I5*I6 -> 0 | J4: =J5*J6 -> 0 | K4: =K5*K6 -> 187917.01 | L4: =L5*L6 -> 537812 | M4: =M5*M6 -> 525062 | N4: =N5*N6 -> 508878 | O4: =O5*O6 -> 508368 | ... S4: =S5*S6 -> 2439.5387 | U4: =U5*U6 -> 6611.4 | V4: =V5*V6 -> 511003.8 | W4: =W5*W6 -> 554760 | X4: =X5*X6 -> 563868 | Y4: =Y5*Y6 -> 563616 | Z4: =Z5*Z6 -> 553176 | AA4: =AA5*AA6 -> 636940.37 | AB4: =AB5*AB6 -> 575568 | ... AF4: =AF5*AF6 -> 0
A5: 為替レート(ドル円)TTM | B5: ='NY不動産(総計)'!B5 -> 150 | C5: ='NY不動産(総計)'!C5 -> 156.9 | D5: ='NY不動産(総計)'!D5 -> 156.74 | E5: ='NY不動産(総計)'!E5 -> 161.07 | F5: ='NY不動産(総計)'!F5 -> 152.44 | H5: ='NY不動産(総計)'!H5 -> 144.8 | I5: ='NY不動産(総計)'!I5 -> 142.73 | J5: ='NY不動産(総計)'!J5 -> 153.64 | K5: ='NY不動産(総計)'!K5 -> 150.74 | L5: ='NY不動産(総計)'!L5 -> 158.18 | M5: ='NY不動産(総計)'!M5 -> 154.43 | N5: ='NY不動産(総計)'!N5 -> 149.67 | O5: ='NY不動産(総計)'!O5 -> 149.52 | ... S5: ='NY不動産(総計)'!S5 -> 149.39 | U5: ='NY不動産(総計)'!U5 -> 146.92 | V5: ='NY不動産(総計)'!V5 -> 148.88 | W5: ='NY不動産(総計)'!W5 -> 154.1 | X5: ='NY不動産(総計)'!X5 -> 156.63 | Y5: ='NY不動産(総計)'!Y5 -> 156.56 | Z5: ='NY不動産(総計)'!Z5 -> 153.66 | AA5: ='NY不動産(総計)'!AA5 -> 155.81 | AB5: ='NY不動産(総計)'!AB5 -> 159.88 | ... AF5: ='NY不動産(総計)'!AF5 -> 0
A6: 賃料収入(ドル) | B6: 3600 | K6: 1246.63 | L6: 3400 | M6: 3400 | N6: 3400 | O6: 3400 | P6: 3400 | Q6: 3400 | R6: 3018.08 | S6: 16.33 | U6: 45 | V6: 3432.32 | W6: 3600 | X6: 3600 | Y6: 3600 | Z6: 3600 | AA6: 4087.93 | AB6: 3600
A7: 減価償却費(円) | B7: 70451659 | H7: 0 | I7: 0 | J7: 0 | K7: 657548 | L7: 657548 | M7: 657551 | N7: 657548 | O7: 657548 | P7: 657548 | Q7: 657548 | R7: 657548 | S7: 657551 | U7: 657548 | V7: 657548 | W7: 657548 | X7: 657548 | Y7: 657548 | Z7: 657552 | AA7: 657548 | AB7: 657548 | AC7: 657548 | AD7: 657548 | AE7: 657548 | AF7: 657553
A8: 減価償却費(ドル)
A9: 残存簿価(円) | B9: 70451659 | K9: =B9-K7 -> 69794111 | L9: =K9-L7 -> 69136563 | M9: =L9-M7 -> 68479012 | N9: =M9-N7 -> 67821464 | O9: =N9-O7 -> 67163916 | P9: =O9-P7 -> 66506368 | Q9: =P9-Q7 -> 65848820 | R9: =Q9-R7 -> 65191272 | S9: =R9-S7 -> 64533721 | U9: =S9-U7 -> 63876173 | V9: =U9-V7 -> 63218625 | W9: =V9-W7 -> 62561077 | X9: =W9-X7 -> 61903529 | Y9: =X9-Y7 -> 61245981 | Z9: =Y9-Z7 -> 60588429 | AA9: =Z9-AA7 -> 59930881 | AB9: =AA9-AB7 -> 59273333 | AC9: =AB9-AC7 -> 58615785 | ... AF9: =AE9-AF7 -> 56643136
A10: 残存簿価(ドル)
A11: 管理費(ドル) | K11: 500 | L11: 238 | M11: 238 | N11: 238 | O11: 238 | P11: 238 | Q11: 238 | R11: 238 | S11: 119 | U11: 119 | V11: 252 | W11: 252 | X11: 252 | Y11: 252 | Z11: 252 | AA11: 252 | AB11: 252 | AG11: =SUM(C36:AF36) -> 4168 | AH11: 管理費
A12: 諸経費(税金、募集経費等)(ドル) | B12: 27127.79 | K12: 348.82 | L12: 6640.02 | M12: 1170.99 | N12: 1170.99 | O12: 1016.89 | P12: 1016.89 | Q12: 1016.89 | R12: 14597.64 | S12: 1611.86 | U12: 8986.86 | V12: 5263.48 | W12: 1553.89 | X12: 1016.89 | Y12: 1016.89 | Z12: 1016.89 | AA12: 1016.89 | AB12: 1104.57 | AG12: 7938.36 | AH12: コモンチャージ
A13: ネット賃貸収入利回り(円) | AG13: 19049.78 | AH13: 固定資産税
A14: ネット賃貸収入利回り(ドル) | AG14: 5986.52 | AH14: 修繕・雑費・その他支出
A15: 取得時簿価利回り(円) | B15: =B13/B2 -> 0 | AG15: =SUM(AG11:AG14) -> 37142.66 | AH15: 合計
A16: 取得時簿価利回り(ドル)
A17: 残存簿価利回り(円) | B17: =B13/B9 -> 0
A18: 残存簿価利回り(ドル)
A19: CF(円) | C19: =SUM(C5*C20) -> 0 | D19: =SUM(D5*D20) -> 0 | E19: =SUM(E5*E20) -> 0 | F19: =SUM(F5*F20) -> 0 | H19: =SUM(H5*H20) -> 0 | I19: =SUM(I5*I20) -> 0 | J19: =SUM(J5*J20) -> 0 | K19: =SUM(K5*K20) -> 59965.879 | L19: =SUM(L5*L20) -> -550153.2 | M19: =SUM(M5*M20) -> 307471.67 | N19: =SUM(N5*N20) -> 297994.47 | O19: =SUM(O5*O20) -> 320736.85 | ... S19: =SUM(S5*S20) -> -256133.64 | U19: =SUM(U5*U20) -> -1331221.6 | V19: =SUM(V5*V20) -> -310140.86 | W19: =SUM(W5*W20) -> 276472.35 | X19: =SUM(X5*X20) -> 365121.76 | Y19: =SUM(Y5*Y20) -> 364958.58 | Z19: =SUM(Z5*Z20) -> 358198.36 | AA19: =SUM(AA5*AA20) -> 439234.62 | AB19: =SUM(AB5*AB20) -> 358679.59 | ... AF19: =SUM(AF5*AF20) -> 0
A20: CF(ドル) | C20: =SUM(C6-C11-C12) -> 0 | D20: =SUM(D6-D11-D12) -> 0 | E20: =SUM(E6-E11-E12) -> 0 | F20: =SUM(F6-F11-F12) -> 0 | H20: =SUM(H6-H11-H12) -> 0 | I20: =SUM(I6-I11-I12) -> 0 | J20: =SUM(J6-J11-J12) -> 0 | K20: =SUM(K6-K11-K12) -> 397.81 | L20: =SUM(L6-L11-L12) -> -3478.02 | M20: =SUM(M6-M11-M12) -> 1991.01 | N20: =SUM(N6-N11-N12) -> 1991.01 | O20: =SUM(O6-O11-O12) -> 2145.11 | ... S20: =SUM(S6-S11-S12) -> -1714.53 | U20: =SUM(U6-U11-U12) -> -9060.86 | V20: =SUM(V6-V11-V12) -> -2083.16 | W20: =SUM(W6-W11-W12) -> 1794.11 | X20: =SUM(X6-X11-X12) -> 2331.11 | Y20: =SUM(Y6-Y11-Y12) -> 2331.11 | Z20: =SUM(Z6-Z11-Z12) -> 2331.11 | AA20: =SUM(AA6-AA11-AA12) -> 2819.04 | AB20: =SUM(AB6-AB11-AB12) -> 2243.43 | ... AF20: =SUM(AF6-AF11-AF12) -> 0
A21: PL(円)
A22: PL(ドル) | S22: =SUM(B22:R22) -> 0 | AF22: =SUM(O22:AE22) -> 0
A24: 購入日 | B24: 45616
A25: 下記表は固都税を各月の諸経費に分散して計上した表です
A26: 159 West 53rd Street #35A | B26: 2024 | C26: 45412 | D26: 45443 | E26: 45473 | F26: 45504 | G26: 2025 | H26: 45535 | I26: 45565 | J26: 45596 | K26: 45626 | L26: 45657 | M26: 45688 | N26: 45716 | O26: 45747 | P26: 45777 | Q26: 45808 | R26: 45838 | S26: 45869 | T26: 2026 | U26: 45900 | V26: 45930 | W26: 45961 | X26: 45991 | Y26: 46022 | Z26: 46053 | AA26: 46081 | AB26: 46112 | AC26: 46142 | AD26: 46173 | AE26: 46203 | AF26: 46234
A27: 取得簿価(円) | B27: =B28*150 -> 87750000
A28: 取得簿価(ドル) | B28: 585000
A29: 賃料収入(円) | B29: =B31*B30 -> 510000 | C29: =C30*C31 -> 0 | D29: =D30*D31 -> 0 | E29: =E30*E31 -> 0 | F29: =F30*F31 -> 0 | H29: =H30*H31 -> 0 | I29: =I30*I31 -> 0 | J29: =J30*J31 -> 0 | K29: =K30*K31 -> 187917.01 | L29: =L30*L31 -> 537812 | M29: =M30*M31 -> 525062 | N29: =N30*N31 -> 508878 | O29: =O30*O31 -> 508368 | ... S29: =S30*S31 -> 2439.5387 | U29: =U30*U31 -> 6611.4 | V29: =V30*V31 -> 511003.8 | W29: =W30*W31 -> 554760 | X29: =X30*X31 -> 563868 | Y29: =Y30*Y31 -> 563616 | Z29: =Z30*Z31 -> 553176 | AA29: =AA30*AA31 -> 636940.37 | AB29: =AB30*AB31 -> 575568 | ... AF29: =AF30*AF31 -> 0
A30: 為替レート(ドル円)TTM | B30: ='NY不動産(総計)'!B30 -> 150 | C30: ='NY不動産(総計)'!C30 -> 156.9 | D30: ='NY不動産(総計)'!D30 -> 156.74 | E30: ='NY不動産(総計)'!E30 -> 161.07 | F30: ='NY不動産(総計)'!F30 -> 152.44 | H30: ='NY不動産(総計)'!H30 -> 144.8 | I30: ='NY不動産(総計)'!I30 -> 142.73 | J30: ='NY不動産(総計)'!J30 -> 153.64 | K30: ='NY不動産(総計)'!K30 -> 150.74 | L30: ='NY不動産(総計)'!L30 -> 158.18 | M30: ='NY不動産(総計)'!M30 -> 154.43 | N30: ='NY不動産(総計)'!N30 -> 149.67 | O30: ='NY不動産(総計)'!O30 -> 149.52 | ... S30: ='NY不動産(総計)'!S30 -> 149.39 | U30: ='NY不動産(総計)'!U30 -> 146.92 | V30: ='NY不動産(総計)'!V30 -> 148.88 | W30: ='NY不動産(総計)'!W30 -> 154.1 | X30: ='NY不動産(総計)'!X30 -> 156.63 | Y30: ='NY不動産(総計)'!Y30 -> 156.56 | Z30: ='NY不動産(総計)'!Z30 -> 153.66 | AA30: ='NY不動産(総計)'!AA30 -> 155.81 | AB30: ='NY不動産(総計)'!AB30 -> 159.88 | ... AF30: ='NY不動産(総計)'!AF30 -> 0
A31: 賃料収入(ドル) | B31: 3400 | K31: 1246.63 | L31: 3400 | M31: 3400 | N31: 3400 | O31: 3400 | P31: 3400 | Q31: 3400 | R31: 3018.08 | S31: 16.33 | U31: 45 | V31: 3432.32 | W31: 3600 | X31: 3600 | Y31: 3600 | Z31: 3600 | AA31: 4087.93 | AB31: 3600
A32: 減価償却費(円) | B32: 70451659 | K32: 657548 | L32: 657548 | M32: 657551 | N32: 657548 | O32: 657548 | P32: 657548 | Q32: 657548 | R32: 657548 | S32: 657551 | U32: 657548 | V32: 657548 | W32: 657548 | X32: 657548 | Y32: 657548 | Z32: 657552 | AA32: 657548 | AB32: 657548 | AC32: 657548 | AD32: 657548 | AE32: 657548 | AF32: 657553
A33: 減価償却費(ドル)
A34: 残存簿価(円) | B34: 70451659 | K34: =B34-K32 -> 69794111 | L34: =K34-L32 -> 69136563 | M34: =L34-M32 -> 68479012 | N34: =M34-N32 -> 67821464 | O34: =N34-O32 -> 67163916 | P34: =O34-P32 -> 66506368 | Q34: =P34-Q32 -> 65848820 | R34: =Q34-R32 -> 65191272 | S34: =R34-S32 -> 64533721 | U34: =S34-U32 -> 63876173 | V34: =U34-V32 -> 63218625 | W34: =V34-W32 -> 62561077 | X34: =W34-X32 -> 61903529 | Y34: =X34-Y32 -> 61245981 | Z34: =Y34-Z32 -> 60588429 | AA34: =Z34-AA32 -> 59930881 | AB34: =AA34-AB32 -> 59273333 | AC34: =AB34-AC32 -> 58615785 | ... AF34: =AE34-AF32 -> 56643136
A35: 残存簿価(ドル)
A36: 管理費(ドル) | K36: 500 | L36: 238 | M36: 238 | N36: 238 | O36: 238 | P36: 238 | Q36: 238 | R36: 238 | S36: 119 | U36: 119 | V36: 252 | W36: 252 | X36: 252 | Y36: 252 | Z36: 252 | AA36: 252 | AB36: 252
A37: 諸経費(税金、募集経費等)(ドル) | B37: 27127.79 | K37: 348.82 | L37: 2082.52 | M37: 2082.49 | N37: 2082.49 | O37: 1928.39 | P37: 1928.39 | Q37: 1928.39 | R37: 2148.61 | S37: 2743.59 | U37: 10118.59 | V37: 6395.21 | W37: 2685.62 | X37: 2148.62 | Y37: 2148.62 | Z37: 2148.62 | AA37: 2148.62 | AB37: 1131.73 | AC37: 1131.73 | AD37: 1131.73
A38: ネット賃貸収入利回り(円)
A39: ネット賃貸収入利回り(ドル)
A40: 取得時簿価利回り(円) | B40: =B38/B27 -> 0
A41: 取得時簿価利回り(ドル)
A42: 残存簿価利回り(円) | B42: =B38/B34 -> 0
A43: 残存簿価利回り(ドル)
A44: CF(円) | C44: =SUM(C30*C45) -> 0 | D44: =SUM(D30*D45) -> 0 | E44: =SUM(E30*E45) -> 0 | F44: =SUM(F30*F45) -> 0 | H44: =SUM(H30*H45) -> 0 | I44: =SUM(I30*I45) -> 0 | J44: =SUM(J30*J45) -> 0 | K44: =SUM(K30*K45) -> 59965.879 | L44: =SUM(L30*L45) -> 170752.15 | M44: =SUM(M30*M45) -> 166708.73 | N44: =SUM(N30*N45) -> 161570.26 | O44: =SUM(O30*O45) -> 184449.37 | ... S44: =SUM(S30*S45) -> -425202.78 | U44: =SUM(U30*U45) -> -1497495.3 | V44: =SUM(V30*V45) -> -478632.82 | W44: =SUM(W30*W45) -> 102072.76 | X44: =SUM(X30*X45) -> 187858.89 | Y44: =SUM(Y30*Y45) -> 187774.93 | Z44: =SUM(Z30*Z45) -> 184296.73 | AA44: =SUM(AA30*AA45) -> 262899.77 | AB44: =SUM(AB30*AB45) -> 354337.25 | ... AF44: =SUM(AF30*AF45) -> 0
A45: CF(ドル) | C45: =SUM(C31-C36-C37) -> 0 | D45: =SUM(D31-D36-D37) -> 0 | E45: =SUM(E31-E36-E37) -> 0 | F45: =SUM(F31-F36-F37) -> 0 | H45: =SUM(H31-H36-H37) -> 0 | I45: =SUM(I31-I36-I37) -> 0 | J45: =SUM(J31-J36-J37) -> 0 | K45: =SUM(K31-K36-K37) -> 397.81 | L45: =SUM(L31-L36-L37) -> 1079.48 | M45: =SUM(M31-M36-M37) -> 1079.51 | N45: =SUM(N31-N36-N37) -> 1079.51 | O45: =SUM(O31-O36-O37) -> 1233.61 | ... S45: =SUM(S31-S36-S37) -> -2846.26 | U45: =SUM(U31-U36-U37) -> -10192.59 | V45: =SUM(V31-V36-V37) -> -3214.89 | W45: =SUM(W31-W36-W37) -> 662.38 | X45: =SUM(X31-X36-X37) -> 1199.38 | Y45: =SUM(Y31-Y36-Y37) -> 1199.38 | Z45: =SUM(Z31-Z36-Z37) -> 1199.38 | AA45: =SUM(AA31-AA36-AA37) -> 1687.31 | AB45: =SUM(AB31-AB36-AB37) -> 2216.27 | ... AF45: =SUM(AF31-AF36-AF37) -> 0
A46: PL(円)
A47: PL(ドル) | AF47: =SUM(O47:AE47) -> 0
R50: 13580.75
Q51: 1 | R51: 1131.72
Q52: 2 | R52: 1131.73
Q53: 3 | R53: 1131.73
Q54: 4 | R54: 1131.73
Q55: 5 | R55: 1131.73
Q56: 6 | R56: 1131.73
Q57: 7 | R57: 1131.73
Q58: 8 | R58: 1131.73
Q59: 9 | R59: 1131.73
Q60: 10 | R60: 1131.73
Q61: 11 | R61: 1131.73
Q62: 12 | R62: 1131.73
R63: =SUM(R51:R62) -> 13580.75

Sheet 1Wall#1810
A1: 1 Wall Street #1810 | B1: 2024 | C1: 45412 | D1: 45443 | E1: 45473 | F1: 45504 | G1: 2025 | H1: 45535 | I1: 45565 | J1: 45596 | K1: 45626 | L1: 45657 | M1: 45688 | N1: 45716 | O1: 45747 | P1: 45777 | Q1: 45808 | R1: 45838 | S1: 45869 | T1: 2026 | U1: 45535 | V1: 45565 | W1: 45596 | X1: 45626 | Y1: 45657 | Z1: 45688 | AA1: 45716 | AB1: 45747 | AC1: 45777 | AD1: 45808 | AE1: 45838 | AF1: 45869
A2: 取得簿価(円) | B2: =B3*160 -> 224000000
A3: 取得簿価(ドル) | B3: 1400000
A4: 賃料収入(円) | B4: =B6*B5 -> 990000 | C4: =C5*C6 -> 0 | D4: =D5*D6 -> 0 | E4: =E5*E6 -> 0 | F4: =F5*F6 -> 4573.2 | H4: =H5*H6 -> 0 | I4: =I5*I6 -> 6422.85 | J4: =J5*J6 -> 0 | K4: =K5*K6 -> 193277.32 | L4: =L5*L6 -> 1028170 | M4: =M5*M6 -> 1003795 | N4: =N5*N6 -> 972855 | O4: =O5*O6 -> 1007211.6 | ... S4: =S5*S6 -> 979710.08 | U4: =U5*U6 -> 965089.57 | V4: =V5*V6 -> 991479.76 | W4: =W5*W6 -> 1028107.4 | X4: =X5*X6 -> 1044225.6 | Y4: =Y5*Y6 -> 1047226.7 | Z4: =Z5*Z6 -> 1021722.2 | AA4: =AA5*AA6 -> 1038391.1 | AB4: =AB5*AB6 -> 1068228.6 | ... AF4: =AF5*AF6 -> 0
A5: 為替レート(ドル円)TTM | B5: ='NY不動産(総計)'!B5 -> 150 | C5: ='NY不動産(総計)'!C5 -> 156.9 | D5: ='NY不動産(総計)'!D5 -> 156.74 | E5: ='NY不動産(総計)'!E5 -> 161.07 | F5: ='NY不動産(総計)'!F5 -> 152.44 | H5: ='NY不動産(総計)'!H5 -> 144.8 | I5: ='NY不動産(総計)'!I5 -> 142.73 | J5: ='NY不動産(総計)'!J5 -> 153.64 | K5: ='NY不動産(総計)'!K5 -> 150.74 | L5: ='NY不動産(総計)'!L5 -> 158.18 | M5: ='NY不動産(総計)'!M5 -> 154.43 | N5: ='NY不動産(総計)'!N5 -> 149.67 | O5: ='NY不動産(総計)'!O5 -> 149.52 | ... S5: ='NY不動産(総計)'!S5 -> 149.39 | U5: ='NY不動産(総計)'!U5 -> 146.92 | V5: ='NY不動産(総計)'!V5 -> 148.88 | W5: ='NY不動産(総計)'!W5 -> 154.1 | X5: ='NY不動産(総計)'!X5 -> 156.63 | Y5: ='NY不動産(総計)'!Y5 -> 156.56 | Z5: ='NY不動産(総計)'!Z5 -> 153.66 | AA5: ='NY不動産(総計)'!AA5 -> 155.81 | AB5: ='NY不動産(総計)'!AB5 -> 159.88 | ... AF5: ='NY不動産(総計)'!AF5 -> 0
A6: 賃料収入(ドル) | B6: 6600 | C6: 0 | D6: 0 | E6: 0 | F6: 30 | H6: 0 | I6: 45 | J6: 0 | K6: 1282.19 | L6: 6500 | M6: 6500 | N6: 6500 | O6: 6736.3 | P6: 7966.27 | Q6: 6695.07 | R6: 6539.15 | S6: 6558.07 | U6: 6568.81 | V6: 6659.59 | W6: 6671.69 | X6: 6666.83 | Y6: 6688.98 | Z6: 6649.24 | AA6: 6664.47 | AB6: 6681.44
A7: 減価償却費(円) | B7: 182968579 | I7: 1707706 | J7: 1707706 | K7: 1707706 | L7: 1707706 | M7: 1707709 | N7: 1707706 | O7: 1707706 | P7: 1707706 | Q7: 1707706 | R7: 1707706 | S7: 1707710 | U7: 1707706 | V7: 1707706 | W7: 1707706 | X7: 1707706 | Y7: 1707706 | Z7: 1707710 | AA7: 1707706 | AB7: 1707706 | AC7: 1707706 | AD7: 1707706 | AE7: 1707706 | AF7: 1707710
A8: 減価償却費(ドル)
A9: 残存簿価(円) | B9: 182968579 | I9: =B9-I7 -> 181260873 | J9: =I9-J7 -> 179553167 | K9: =J9-K7 -> 177845461 | L9: =K9-L7 -> 176137755 | M9: =L9-M7 -> 174430046 | N9: =M9-N7 -> 172722340 | O9: =N9-O7 -> 171014634 | P9: =O9-P7 -> 169306928 | Q9: =P9-Q7 -> 167599222 | ... S9: =R9-S7 -> 164183806 | U9: =S9-U7 -> 162476100 | V9: =U9-V7 -> 160768394 | W9: =V9-W7 -> 159060688 | X9: =W9-X7 -> 157352982 | Y9: =X9-Y7 -> 155645276 | Z9: =Y9-Z7 -> 153937566 | AA9: =Z9-AA7 -> 152229860 | AB9: =AA9-AB7 -> 150522154 | AC9: =AB9-AC7 -> 148814448 | ... AF9: =AE9-AF7 -> 143691326
A10: 残存簿価(ドル)
A11: 管理費(ドル) | J11: 715.95 | K11: 6600 | L11: 455 | M11: 455 | N11: 455 | O11: 455 | P11: 455 | Q11: 455 | R11: 455 | S11: 455 | U11: 455 | V11: 455 | W11: 455 | X11: 462 | Y11: 462 | Z11: 462 | AA11: 462 | AB11: 462 | AG11: =SUM(C36:AF36) -> 14630.95 | AH11: 管理費
A12: 諸経費(税金、募集経費等)(ドル) | B12: 1854.83 | I12: 653.55 | J12: 8502.6 | K12: 1555.81 | L12: 11195.25 | M12: 1400.86 | N12: 1432.63 | O12: 1398.54 | P12: 1373.16 | Q12: 1344.51 | R12: 21561.57 | S12: 1787.9 | U12: 2177.9 | V12: 1477 | W12: 1389.07 | X12: 2054.24 | Y12: 1354.5 | Z12: 1382.83 | AA12: 1399.8 | AB12: 1440.64 | AG12: 13603.61 | AH12: コモンチャージ
A13: ネット賃貸収入利回り(円) | AG13: 34429.17 | AH13: 固定資産税
A14: ネット賃貸収入利回り(ドル) | AG14: 4173.6 | AH14: 修繕・雑費・その他支出
A15: 取得時簿価利回り(円) | B15: =B13/B2 -> 0 | AG15: =SUM(AG11:AG14) -> 66837.33 | AH15: 合計
A16: 取得時簿価利回り(ドル)
A17: 残存簿価利回り(円) | B17: =B13/B9 -> 0
A18: 残存簿価利回り(ドル)
A19: CF(円) | C19: =SUM(C5*C20) -> 0 | D19: =SUM(D5*D20) -> 0 | E19: =SUM(E5*E20) -> 0 | F19: =SUM(F5*F20) -> 4573.2 | H19: =SUM(H5*H20) -> 0 | I19: =SUM(I5*I20) -> -86858.341 | J19: =SUM(J5*J20) -> -1416338 | K19: =SUM(K5*K20) -> -1036129.5 | L19: =SUM(L5*L20) -> -814666.55 | M19: =SUM(M5*M20) -> 717194.54 | N19: =SUM(N5*N20) -> 690333.42 | O19: =SUM(O5*O20) -> 730070.28 | ... S19: =SUM(S5*S20) -> 644643.25 | U19: =SUM(U5*U20) -> 578263.9 | V19: =SUM(V5*V20) -> 703843.6 | W19: =SUM(W5*W20) -> 743936.24 | X19: =SUM(X5*X20) -> 650106.91 | Y19: =SUM(Y5*Y20) -> 762835.47 | Z19: =SUM(Z5*Z20) -> 738245.64 | AA19: =SUM(AA5*AA20) -> 748304.01 | AB19: =SUM(AB5*AB20) -> 764034.54 | ... AF19: =SUM(AF5*AF20) -> 0
A20: CF(ドル) | C20: =SUM(C6-C11-C12) -> 0 | D20: =SUM(D6-D11-D12) -> 0 | E20: =SUM(E6-E11-E12) -> 0 | F20: =SUM(F6-F11-F12) -> 30 | H20: =SUM(H6-H11-H12) -> 0 | I20: =SUM(I6-I11-I12) -> -608.55 | J20: =SUM(J6-J11-J12) -> -9218.55 | K20: =SUM(K6-K11-K12) -> -6873.62 | L20: =SUM(L6-L11-L12) -> -5150.25 | M20: =SUM(M6-M11-M12) -> 4644.14 | N20: =SUM(N6-N11-N12) -> 4612.37 | O20: =SUM(O6-O11-O12) -> 4882.76 | ... S20: =SUM(S6-S11-S12) -> 4315.17 | U20: =SUM(U6-U11-U12) -> 3935.91 | V20: =SUM(V6-V11-V12) -> 4727.59 | W20: =SUM(W6-W11-W12) -> 4827.62 | X20: =SUM(X6-X11-X12) -> 4150.59 | Y20: =SUM(Y6-Y11-Y12) -> 4872.48 | Z20: =SUM(Z6-Z11-Z12) -> 4804.41 | AA20: =SUM(AA6-AA11-AA12) -> 4802.67 | AB20: =SUM(AB6-AB11-AB12) -> 4778.8 | ... AF20: =SUM(AF6-AF11-AF12) -> 0
A21: PL(円)
A22: PL(ドル)
A24: 購入日 | B24: 45551
A25: 下記表は固都税を各月の諸経費に分散して計上した表です
A26: 1 Wall Street #1810 | B26: 2024 | C26: 45412 | D26: 45443 | E26: 45473 | F26: 45504 | G26: 2025 | H26: 45535 | I26: 45565 | J26: 45596 | K26: 45626 | L26: 45657 | M26: 45688 | N26: 45716 | O26: 45747 | P26: 45777 | Q26: 45808 | R26: 45838 | S26: 45869 | T26: 2026 | U26: 45535 | V26: 45565 | W26: 45596 | X26: 45626 | Y26: 45657 | Z26: 45688 | AA26: 45716 | AB26: 45747 | AC26: 45777 | AD26: 45808 | AE26: 45838 | AF26: 45869
A27: 取得簿価(円) | B27: =B28*160 -> 224000000
A28: 取得簿価(ドル) | B28: 1400000
A29: 賃料収入(円) | B29: =B31*B30 -> 975000 | C29: =C30*C31 -> 0 | D29: =D30*D31 -> 0 | E29: =E30*E31 -> 0 | F29: =F30*F31 -> 4573.2 | H29: =H30*H31 -> 0 | I29: =I30*I31 -> 6422.85 | J29: =J30*J31 -> 0 | K29: =K30*K31 -> 193277.32 | L29: =L30*L31 -> 1028170 | M29: =M30*M31 -> 1003795 | N29: =N30*N31 -> 972855 | O29: =O30*O31 -> 1007211.6 | ... S29: =S30*S31 -> 979710.08 | U29: =U30*U31 -> 965089.57 | V29: =V30*V31 -> 991479.76 | W29: =W30*W31 -> 1028107.4 | X29: =X30*X31 -> 1044225.6 | Y29: =Y30*Y31 -> 1047226.7 | Z29: =Z30*Z31 -> 1021722.2 | AA29: =AA30*AA31 -> 1038391.1 | AB29: =AB30*AB31 -> 1068228.6 | ... AF29: =AF30*AF31 -> 0
A30: 為替レート(ドル円)TTM | B30: ='NY不動産(総計)'!B30 -> 150 | C30: ='NY不動産(総計)'!C30 -> 156.9 | D30: ='NY不動産(総計)'!D30 -> 156.74 | E30: ='NY不動産(総計)'!E30 -> 161.07 | F30: ='NY不動産(総計)'!F30 -> 152.44 | H30: ='NY不動産(総計)'!H30 -> 144.8 | I30: ='NY不動産(総計)'!I30 -> 142.73 | J30: ='NY不動産(総計)'!J30 -> 153.64 | K30: ='NY不動産(総計)'!K30 -> 150.74 | L30: ='NY不動産(総計)'!L30 -> 158.18 | M30: ='NY不動産(総計)'!M30 -> 154.43 | N30: ='NY不動産(総計)'!N30 -> 149.67 | O30: ='NY不動産(総計)'!O30 -> 149.52 | ... S30: ='NY不動産(総計)'!S30 -> 149.39 | U30: ='NY不動産(総計)'!U30 -> 146.92 | V30: ='NY不動産(総計)'!V30 -> 148.88 | W30: ='NY不動産(総計)'!W30 -> 154.1 | X30: ='NY不動産(総計)'!X30 -> 156.63 | Y30: ='NY不動産(総計)'!Y30 -> 156.56 | Z30: ='NY不動産(総計)'!Z30 -> 153.66 | AA30: ='NY不動産(総計)'!AA30 -> 155.81 | AB30: ='NY不動産(総計)'!AB30 -> 159.88 | ... AF30: ='NY不動産(総計)'!AF30 -> 0
A31: 賃料収入(ドル) | B31: 6500 | C31: 0 | D31: 0 | E31: 0 | F31: 30 | H31: 0 | I31: 45 | J31: 0 | K31: 1282.19 | L31: 6500 | M31: 6500 | N31: 6500 | O31: 6736.3 | P31: 7966.27 | Q31: 6695.07 | R31: 6539.15 | S31: 6558.07 | U31: 6568.81 | V31: 6659.59 | W31: 6671.69 | X31: 6666.83 | Y31: 6688.98 | Z31: 6649.24 | AA31: 6664.47 | AB31: 6681.44
A32: 減価償却費(円) | B32: 182968579 | I32: 1707706 | J32: 1707706 | K32: 1707706 | L32: 1707706 | M32: 1707709 | N32: 1707706 | O32: 1707706 | P32: 1707706 | Q32: 1707706 | R32: 1707706 | S32: 1707710 | U32: 1707706 | V32: 1707706 | W32: 1707706 | X32: 1707706 | Y32: 1707706 | Z32: 1707710 | AA32: 1707706 | AB32: 1707706 | AC32: 1707706 | AD32: 1707706 | AE32: 1707706 | AF32: 1707710
A33: 減価償却費(ドル)
A34: 残存簿価(円) | B34: 182968579 | I34: =B34-I32 -> 181260873 | J34: =I34-J32 -> 179553167 | K34: =J34-K32 -> 177845461 | L34: =K34-L32 -> 176137755 | M34: =L34-M32 -> 174430046 | N34: =M34-N32 -> 172722340 | O34: =N34-O32 -> 171014634 | P34: =O34-P32 -> 169306928 | Q34: =P34-Q32 -> 167599222 | ... S34: =R34-S32 -> 164183806 | U34: =S34-U32 -> 162476100 | V34: =U34-V32 -> 160768394 | W34: =V34-W32 -> 159060688 | X34: =W34-X32 -> 157352982 | Y34: =X34-Y32 -> 155645276 | Z34: =Y34-Z32 -> 153937566 | AA34: =Z34-AA32 -> 152229860 | AB34: =AA34-AB32 -> 150522154 | AC34: =AB34-AC32 -> 148814448 | ... AF34: =AE34-AF32 -> 143691326
A35: 残存簿価(ドル)
A36: 管理費(ドル) | J36: 715.95 | K36: 6600 | L36: 455 | M36: 455 | N36: 455 | O36: 455 | P36: 455 | Q36: 455 | R36: 455 | S36: 455 | U36: 455 | V36: 455 | W36: 455 | X36: 462 | Y36: 462 | Z36: 462 | AA36: 462 | AB36: 462
A37: 諸経費(税金、募集経費等)(ドル) | B37: 1854.83 | I37: 653.55 | J37: 5407.62 | K37: 3103.3 | L37: 4752.29 | M37: 2998.95 | N37: 3030.72 | O37: 2996.63 | P37: 2971.25 | Q37: 2942.6 | R37: 3046.59 | S37: 3471.08 | U37: 3861.08 | V37: 3160.18 | W37: 3072.25 | X37: 3737.42 | Y37: 3037.68 | Z37: 3066.01 | AA37: 3082.98 | AB37: 1683.18 | AC37: 1683.18 | AD37: 1683.18
A38: ネット賃貸収入利回り(円)
A39: ネット賃貸収入利回り(ドル)
A40: 取得時簿価利回り(円) | B40: =B38/B27 -> 0
A41: 取得時簿価利回り(ドル)
A42: 残存簿価利回り(円) | B42: =B38/B34 -> 0
A43: 残存簿価利回り(ドル)
A44: CF(円) | C44: =SUM(C30*C45) -> 0 | D44: =SUM(D30*D45) -> 0 | E44: =SUM(E30*E45) -> 0 | F44: =SUM(F30*F45) -> 4573.2 | H44: =SUM(H30*H45) -> 0 | I44: =SUM(I30*I45) -> -86858.341 | J44: =SUM(J30*J45) -> -940825.29 | K44: =SUM(K30*K45) -> -1269398.1 | L44: =SUM(L30*L45) -> 204480.87 | M44: =SUM(M30*M45) -> 470401.5 | N44: =SUM(N30*N45) -> 451147.29 | O44: =SUM(O30*O45) -> 491123.86 | ... S44: =SUM(S30*S45) -> 393192.99 | U44: =SUM(U30*U45) -> 330971.09 | V44: =SUM(V30*V45) -> 453251.76 | W44: =SUM(W30*W45) -> 484558.2 | X44: =SUM(X30*X45) -> 386470.43 | Y44: =SUM(Y30*Y45) -> 499316.81 | Z44: =SUM(Z30*Z45) -> 479608.2 | AA44: =SUM(AA30*AA45) -> 486047.74 | AB44: =SUM(AB30*AB45) -> 725257.25 | ... AF44: =SUM(AF30*AF45) -> 0
A45: CF(ドル) | C45: =SUM(C31-C36-C37) -> 0 | D45: =SUM(D31-D36-D37) -> 0 | E45: =SUM(E31-E36-E37) -> 0 | F45: =SUM(F31-F36-F37) -> 30 | H45: =SUM(H31-H36-H37) -> 0 | I45: =SUM(I31-I36-I37) -> -608.55 | J45: =SUM(J31-J36-J37) -> -6123.57 | K45: =SUM(K31-K36-K37) -> -8421.11 | L45: =SUM(L31-L36-L37) -> 1292.71 | M45: =SUM(M31-M36-M37) -> 3046.05 | N45: =SUM(N31-N36-N37) -> 3014.28 | O45: =SUM(O31-O36-O37) -> 3284.67 | ... S45: =SUM(S31-S36-S37) -> 2631.99 | U45: =SUM(U31-U36-U37) -> 2252.73 | V45: =SUM(V31-V36-V37) -> 3044.41 | W45: =SUM(W31-W36-W37) -> 3144.44 | X45: =SUM(X31-X36-X37) -> 2467.41 | Y45: =SUM(Y31-Y36-Y37) -> 3189.3 | Z45: =SUM(Z31-Z36-Z37) -> 3121.23 | AA45: =SUM(AA31-AA36-AA37) -> 3119.49 | AB45: =SUM(AB31-AB36-AB37) -> 4536.26 | ... AF45: =SUM(AF31-AF36-AF37) -> 0
A46: PL(円)
A47: PL(ドル)
R50: 20198.14
Q51: 1 | R51: 1683.16
Q52: 2 | R52: 1683.18
Q53: 3 | R53: 1683.18
Q54: 4 | R54: 1683.18
Q55: 5 | R55: 1683.18
Q56: 6 | R56: 1683.18
Q57: 7 | R57: 1683.18
Q58: 8 | R58: 1683.18
Q59: 9 | R59: 1683.18
Q60: 10 | R60: 1683.18
Q61: 11 | R61: 1683.18
Q62: 12 | R62: 1683.18
R63: =SUM(R51:R62) -> 20198.14

Sheet 20W#40B
A1: 20 West Street Unit 40B(DT Athletic Club) | B1: 2024 | C1: 45412 | D1: 45443 | E1: 45473 | F1: 45504 | G1: 2025 | H1: 45535 | I1: 45565 | J1: 45596 | K1: 45626 | L1: 45657 | M1: 45688 | N1: 45716 | O1: 45747 | P1: 45777 | Q1: 45808 | R1: 45838 | S1: 45869 | T1: 2026 | U1: 45900 | V1: 45930 | W1: 45961 | X1: 45991 | Y1: 46022 | Z1: 46053 | AA1: 46081 | AB1: 46112 | AC1: 46142 | AD1: 46173 | AE1: 46203 | AF1: 46234
A2: Acquisition Cost (JPY) | B2: 120000000
A3: Acquisition Cost (USD) | B3: 800000
A4: Rental Income (JPY) | B4: 652500 | F4: 0 | H4: 0 | I4: 0 | J4: 0 | K4: 0 | L4: 0 | M4: 0 | N4: 0 | O4: 0 | P4: 0 | Q4: 625834.5 | R4: 629923.5 | S4: 649846.5 | U4: 639102 | V4: 647628 | W4: 670335 | X4: 681340.5 | Y4: 681036 | Z4: 668421 | AA4: 677773.5 | AB4: 695478 | AC4: 697696.5 | AD4: 0 | AE4: 0 | AF4: 0
A5: Exchange Rate (USD/JPY) TTM | B5: 150 | C5: 156.9 | D5: 156.74 | E5: 161.07 | F5: 152.44 | H5: 144.8 | I5: 142.73 | J5: 153.64 | K5: 150.74 | L5: 158.18 | M5: 154.43 | N5: 149.67 | O5: 149.52 | P5: 142.57 | Q5: 143.87 | R5: 144.81 | S5: 149.39 | U5: 146.92 | V5: 148.88 | W5: 154.1 | X5: 156.63 | Y5: 156.56 | Z5: 153.66 | AA5: 155.81 | AB5: 159.88 | AC5: 160.39 | AD5: 0 | AE5: 0 | AF5: 0
A6: Rental Income (USD) | B6: 4350 | Q6: 4350 | R6: 4350 | S6: 4350 | U6: 4350 | V6: 4350 | W6: 4350 | X6: 4350 | Y6: 4350 | Z6: 4350 | AA6: 4350 | AB6: 4350 | AC6: 4350 | AD6: 4350
A7: Depreciation (JPY) | B7: 108892921 | K7: 1016333 | L7: 1016333 | M7: 1016337 | N7: 1016333 | O7: 1016333 | P7: 1016333 | Q7: 1016333 | R7: 1016333 | S7: 1016337 | U7: 1016333 | V7: 1016333 | W7: 1016333 | X7: 1016333 | Y7: 1016333 | Z7: 1016338 | AA7: 1016333 | AB7: 1016333 | AC7: 1016333 | AD7: 1016333 | AE7: 1016333 | AF7: 1016339
A8: Depreciation (USD)
A9: Remaining Book Value (JPY) | B9: 108892921 | K9: 107876588 | L9: 106860255 | M9: 105843918 | N9: 104827585 | O9: 103811252 | P9: 102794919 | Q9: 101778586 | R9: 100762253 | S9: 99745916 | U9: 98729583 | V9: 97713250 | W9: 96696917 | X9: 95680584 | Y9: 94664251 | Z9: 93647913 | AA9: 92631580 | AB9: 91615247 | AC9: 90598914 | AD9: 89582581 | AE9: 88566248 | AF9: 87549909
A10: Remaining Book Value (USD)
A11: Management Fee (USD) | L11: 150 | M11: 150 | N11: 150 | O11: 150 | P11: 150 | Q11: 150 | R11: 261 | S11: 261 | U11: 261 | V11: 261 | W11: 261 | X11: 261 | Y11: 261 | Z11: 261 | AA11: 261 | AB11: 261 | AC11: 261 | AD11: 261 | AG11: 4032 | AH11: Management Fee
A12: Other Expenses (Tax, Recruitment Costs, etc.) (USD) | B12: 13172.52 | K12: 164.51 | L12: 6574.17 | M12: 4814.93 | N12: 1064.92 | O12: 3798.17 | P12: 1063.21 | Q12: 1058.39 | R12: 19266.2 | S12: 1161.79 | U12: 1016.69 | V12: 1016.69 | W12: 1016.69 | X12: 1646.69 | Y12: 1036.69 | Z12: 1108.7 | AA12: 1102.84 | AB12: 1102.84 | AC12: 1102.84 | AD12: 1102.84 | AG12: 9285.11 | AH12: Common Charge
A13: Net Rental Yield (JPY) | AG13: 18631.13 | AH13: Property Tax
A14: Net Rental Yield (USD) | AG14: 11050.05 | AH14: Repairs/Misc/Other Expenses
A15: Acquisition Book Value Yield (JPY) | B15: 0 | AG15: 42998.29 | AH15: Total
A16: Acquisition Book Value Yield (USD)
A17: Remaining Book Value Yield (JPY) | B17: 0
A18: Remaining Book Value Yield (USD)
A19: Cash Flow (JPY) | C19: 0 | D19: 0 | E19: 0 | F19: 0 | H19: 0 | I19: 0 | J19: 0 | K19: -24798.237 | L19: -1063629.2 | M19: -766734.14 | N19: -181837.08 | O19: -590330.38 | P19: -172967.35 | Q19: 451983.43 | R19: -2197810.3 | S19: 437295.9 | U19: 451383.79 | V19: 457405.51 | W19: 473442.97 | X19: 382539.02 | Y19: 477869.65 | Z19: 457952.9 | AA19: 465273.59 | AB19: 477427.26 | AC19: 478950.2 | AD19: 0 | AE19: 0 | AF19: 0
A20: Cash Flow (USD) | C20: 0 | D20: 0 | E20: 0 | F20: 0 | H20: 0 | I20: 0 | J20: 0 | K20: -164.51 | L20: -6724.17 | M20: -4964.93 | N20: -1214.92 | O20: -3948.17 | P20: -1213.21 | Q20: 3141.61 | R20: -15177.2 | S20: 2927.21 | U20: 3072.31 | V20: 3072.31 | W20: 3072.31 | X20: 2442.31 | Y20: 3052.31 | Z20: 2980.3 | AA20: 2986.16 | AB20: 2986.16 | AC20: 2986.16 | AD20: 2986.16 | AE20: 0 | AF20: 0
A21: P&L (JPY)
A22: P&L (USD)
A24: Purchase Date | B24: 45622
A25: The table below shows property tax distributed across monthly expenses
A26: Downtown Athletic Club Building #40B | B26: 2024 | C26: 45412 | D26: 45443 | E26: 45473 | F26: 45504 | G26: 2025 | H26: 45535 | I26: 45565 | J26: 45596 | K26: 45626 | L26: 45657 | M26: 45688 | N26: 45716 | O26: 45747 | P26: 45777 | Q26: 45808 | R26: 45838 | S26: 45869 | T26: 2026 | U26: 45900 | V26: 45930 | W26: 45961 | X26: 45991 | Y26: 46022 | Z26: 46053 | AA26: 46081 | AB26: 46112 | AC26: 46142 | AD26: 46173 | AE26: 46203 | AF26: 46234
A27: Acquisition Cost (JPY) | B27: 120000000
A28: Acquisition Cost (USD) | B28: 800000
A29: Rental Income (JPY) | B29: 652500 | F29: 0 | H29: 0 | I29: 0 | J29: 0 | K29: 0 | L29: 0 | M29: 0 | N29: 0 | O29: 0 | P29: 0 | Q29: 625834.5 | R29: 629923.5 | S29: 649846.5 | U29: 639102 | V29: 647628 | W29: 670335 | X29: 681340.5 | Y29: 681036 | Z29: 668421 | AA29: 677773.5 | AB29: 695478 | AC29: 697696.5 | AD29: 0 | AE29: 0 | AF29: 0
A30: Exchange Rate (USD/JPY) TTM | B30: 150 | C30: 156.9 | D30: 156.74 | E30: 161.07 | F30: 152.44 | H30: 144.8 | I30: 142.73 | J30: 153.64 | K30: 150.74 | L30: 158.18 | M30: 154.43 | N30: 149.67 | O30: 149.52 | P30: 142.57 | Q30: 143.87 | R30: 144.81 | S30: 149.39 | U30: 146.92 | V30: 148.88 | W30: 154.1 | X30: 156.63 | Y30: 156.56 | Z30: 153.66 | AA30: 155.81 | AB30: 159.88 | AC30: 160.39 | AD30: 0 | AE30: 0 | AF30: 0
A31: Rental Income (USD) | B31: 4350 | Q31: 4350 | R31: 4350 | S31: 4350 | U31: 4350 | V31: 4350 | W31: 4350 | X31: 4350 | Y31: 4350 | Z31: 4350 | AA31: 4350 | AB31: 4350 | AC31: 4350 | AD31: 4350
A32: Depreciation (JPY) | B32: 108892921 | K32: 1016333 | L32: 1016333 | M32: 1016337 | N32: 1016333 | O32: 1016333 | P32: 1016333 | Q32: 1016333 | R32: 1016333 | S32: 1016337 | U32: 1016333 | V32: 1016333 | W32: 1016333 | X32: 1016333 | Y32: 1016333 | Z32: 1016338 | AA32: 1016333 | AB32: 1016333 | AC32: 1016333 | AD32: 1016333 | AE32: 1016333 | AF32: 1016339
A33: Depreciation (USD)
A34: Remaining Book Value (JPY) | B34: 108892921 | K34: 107876588 | L34: 106860255 | M34: 105843918 | N34: 104827585 | O34: 103811252 | P34: 102794919 | Q34: 101778586 | R34: 100762253 | S34: 99745916 | U34: 98729583 | V34: 97713250 | W34: 96696917 | X34: 95680584 | Y34: 94664251 | Z34: 93647913 | AA34: 92631580 | AB34: 91615247 | AC34: 90598914 | AD34: 89582581 | AE34: 88566248 | AF34: 87549909
A35: Remaining Book Value (USD)
A36: Management Fee (USD) | L36: 150 | M36: 150 | N36: 150 | O36: 150 | P36: 150 | Q36: 150 | R36: 261 | S36: 261 | U36: 261 | V36: 261 | W36: 261 | X36: 261 | Y36: 261 | Z36: 261 | AA36: 261 | AB36: 261 | AC36: 261 | AD36: 261
A37: Other Expenses (Tax, Recruitment Costs, etc.) (USD) | B37: 13172.52 | K37: 164.51 | L37: 6574.17 | M37: 2989.57 | N37: 1977.6 | O37: 1972.81 | P37: 1975.89 | Q37: 1971.07 | R37: 8120.09 | S37: 2258.05 | U37: 2112.95 | V37: 2112.95 | W37: 2112.95 | X37: 2742.94 | Y37: 2132.94 | Z37: 2204.95 | AA37: 2199.09 | AB37: 2199.09 | AC37: 1096.25 | AD37: 1096.25
A38: Net Rental Yield (JPY)
A39: Net Rental Yield (USD)
A40: Acquisition Book Value Yield (JPY) | B40: 0
A41: Acquisition Book Value Yield (USD)
A42: Remaining Book Value Yield (JPY) | B42: 0
A43: Remaining Book Value Yield (USD)
A44: Cash Flow (JPY) | C44: 0 | D44: 0 | E44: 0 | F44: 0 | H44: 0 | I44: 0 | J44: 0 | K44: -24798.237 | L44: -1063629.2 | M44: -484843.8 | N44: -318437.89 | O44: -317402.55 | P44: -303088.14 | Q44: 320676.16 | R44: -583742.14 | S44: 273525.62 | U44: 290321.27 | V44: 294194.32 | W44: 304509.3 | X44: 210833.38 | Y44: 306240.75 | Z44: 289503.12 | AA44: 294466.88 | AB44: 302158.81 | AC44: 480007.17 | AD44: 0 | AE44: 0 | AF44: 0
A45: Cash Flow (USD) | C45: 0 | D45: 0 | E45: 0 | F45: 0 | H45: 0 | I45: 0 | J45: 0 | K45: -164.51 | L45: -6724.17 | M45: -3139.57 | N45: -2127.6 | O45: -2122.81 | P45: -2125.89 | Q45: 2228.93 | R45: -4031.09 | S45: 1830.95 | U45: 1976.05 | V45: 1976.05 | W45: 1976.05 | X45: 1346.06 | Y45: 1956.06 | Z45: 1884.05 | AA45: 1889.91 | AB45: 1889.91 | AC45: 2992.75 | AD45: 2992.75 | AE45: 0 | AF45: 0
A46: P&L (JPY)
A47: P&L (USD)
P53: 1 | Q53: 1096.26 | R53: 13155.05
P54: 2 | Q54: 1096.26 | R54: 1096.2542
P55: 3 | Q55: 1096.26 | R55: 91.354514
P56: 4 | Q56: 1096.26 | R56: 7.6128762
P57: 5 | Q57: 1096.26
P58: 6 | Q58: 1096.25
P59: 7 | Q59: 1096.25
P60: 8 | Q60: 1096.25
P61: 9 | Q61: 1096.25
P62: 10 | Q62: 1096.25
P63: 11 | Q63: 1096.25
P64: 12 | Q64: 1096.25
Q65: 13155.05

Sheet 301W53rd#6H
A1: 301 West 53rd Street #6H | B1: 2024 | C1: 45412 | D1: 45443 | E1: 45473 | F1: 45504 | G1: 2025 | H1: 45535 | I1: 45565 | J1: 45596 | K1: 45626 | L1: 45657 | M1: 45688 | N1: 45716 | O1: 45747 | P1: 45777 | Q1: 45808 | R1: 45838 | S1: 45869 | T1: 2026 | U1: 45900 | V1: 45930 | W1: 45961 | X1: 45991 | Y1: 46022 | Z1: 46053 | AA1: 46081 | AB1: 46112 | AC1: 46142 | AD1: 46173 | AE1: 46203 | AF1: 46234
A2: 取得簿価(円) | B2: =B3*B5 -> 147750000
A3: 取得簿価(ドル) | B3: 985000
A4: 賃料収入(円) | B4: =B5*B6 -> 630000 | C4: =C5*C6 -> 0 | D4: =D5*D6 -> 0 | E4: =E5*E6 -> 0 | F4: =F5*F6 -> 0 | H4: =H5*H6 -> 0 | I4: =I5*I6 -> 0 | J4: =J5*J6 -> 0 | K4: =K5*K6 -> 0 | L4: =L5*L6 -> 0 | M4: =M5*M6 -> 0 | N4: =N5*N6 -> 0 | O4: =O5*O6 -> 627984 | ... S4: =S5*S6 -> 627438 | U4: =U5*U6 -> 617064 | V4: =V5*V6 -> 625296 | W4: =W5*W6 -> 647220 | X4: =X5*X6 -> 657846 | Y4: =Y5*Y6 -> 657552 | Z4: =Z5*Z6 -> 645372 | AA4: =AA5*AA6 -> 654402 | AB4: =AB5*AB6 -> 671496 | ... AF4: =AF5*AF6 -> 0
A5: 為替レート(ドル円)TTM | B5: ='NY不動産(総計)'!B5 -> 150 | C5: ='NY不動産(総計)'!C5 -> 156.9 | D5: ='NY不動産(総計)'!D5 -> 156.74 | E5: ='NY不動産(総計)'!E5 -> 161.07 | F5: ='NY不動産(総計)'!F5 -> 152.44 | H5: ='NY不動産(総計)'!H5 -> 144.8 | I5: ='NY不動産(総計)'!I5 -> 142.73 | J5: ='NY不動産(総計)'!J5 -> 153.64 | K5: ='NY不動産(総計)'!K5 -> 150.74 | L5: ='NY不動産(総計)'!L5 -> 158.18 | M5: ='NY不動産(総計)'!M5 -> 154.43 | N5: ='NY不動産(総計)'!N5 -> 149.67 | O5: ='NY不動産(総計)'!O5 -> 149.52 | ... S5: ='NY不動産(総計)'!S5 -> 149.39 | U5: ='NY不動産(総計)'!U5 -> 146.92 | V5: ='NY不動産(総計)'!V5 -> 148.88 | W5: ='NY不動産(総計)'!W5 -> 154.1 | X5: ='NY不動産(総計)'!X5 -> 156.63 | Y5: ='NY不動産(総計)'!Y5 -> 156.56 | Z5: ='NY不動産(総計)'!Z5 -> 153.66 | AA5: ='NY不動産(総計)'!AA5 -> 155.81 | AB5: ='NY不動産(総計)'!AB5 -> 159.88 | ... AF5: ='NY不動産(総計)'!AF5 -> 0
A6: 賃料収入(ドル) | B6: 4200 | C6: 0 | D6: 0 | E6: 0 | F6: 0 | H6: 0 | I6: 0 | J6: 0 | K6: 0 | L6: 0 | M6: 0 | N6: 0 | O6: 4200 | P6: 4200 | Q6: 4200 | R6: 4200 | S6: 4200 | U6: 4200 | V6: 4200 | W6: 4200 | X6: 4200 | Y6: 4200 | Z6: 4200 | AA6: 4200 | AB6: 4200 | AC6: 4200
A7: 減価償却費(円) | B7: 136145429 | L7: 1270690 | M7: 1270692 | N7: 1270690 | O7: 1270690 | P7: 1270690 | Q7: 1270690 | R7: 1270690 | S7: 1270693 | U7: 1270690 | V7: 1270690 | W7: 1270690 | X7: 1270690 | Y7: 1270690 | Z7: 1270694 | AA7: 1270690 | AB7: 1270690 | AC7: 1270690 | AD7: 1270690 | AE7: 1270690 | AF7: 1270694
A8: 減価償却費(ドル)
A9: 残存簿価(円) | B9: 136145429 | L9: =B9-L7 -> 134874739 | M9: =L9-M7 -> 133604047 | N9: =M9-N7 -> 132333357 | O9: =N9-O7 -> 131062667 | P9: =O9-P7 -> 129791977 | Q9: =P9-Q7 -> 128521287 | R9: =Q9-R7 -> 127250597 | S9: =R9-S7 -> 125979904 | U9: =S9-U7 -> 124709214 | V9: =U9-V7 -> 123438524 | W9: =V9-W7 -> 122167834 | X9: =W9-X7 -> 120897144 | Y9: =X9-Y7 -> 119626454 | Z9: =Y9-Z7 -> 118355760 | AA9: =Z9-AA7 -> 117085070 | AB9: =AA9-AB7 -> 115814380 | AC9: =AB9-AC7 -> 114543690 | ... AF9: =AE9-AF7 -> 110731616
A10: 残存簿価(ドル)
A11: 管理費(ドル) | L11: 45.16 | M11: 100 | N11: 100 | O11: 252 | P11: 252 | Q11: 252 | R11: 252 | S11: 252 | U11: 252 | V11: 252 | W11: 252 | X11: 252 | Y11: 252 | Z11: 252 | AA11: 252 | AB11: 252 | AC11: 252 | AG11: =SUM(C36:AF36) -> 3773.16 | AH11: 管理費
A12: 諸経費(税金、募集経費等)(ドル) | B12: 41357.25 | L12: 1133.94 | M12: 732.8 | N12: 2756.18 | O12: 8682.91 | P12: 1981.8 | Q12: 1981.8 | R12: 14320.68 | S12: 1981.8 | U12: 732.8 | V12: 732.8 | W12: 732.8 | X12: 732.8 | Y12: 1542.8 | Z12: 1620.74 | AA12: 798.75 | AB12: 798.75 | AC12: 798.75 | AG12: 5460.54 | AH12: コモンチャージ
A13: ネット賃貸収入利回り(円) | AG13: 15436.6 | AH13: 固定資産税
A14: ネット賃貸収入利回り(ドル) | AG14: 12674.77 | AH14: 修繕・雑費・その他支出
A15: 取得時簿価利回り(円) | B15: =B13/B2 -> 0 | AG15: =SUM(AG11:AG14) -> 37345.07 | AH15: 合計
A16: 取得時簿価利回り(ドル)
A17: 残存簿価利回り(円) | B17: =B13/B9 -> 0
A18: 残存簿価利回り(ドル)
A19: CF(円) | C19: =SUM(C5*C20) -> 0 | D19: =SUM(D5*D20) -> 0 | E19: =SUM(E5*E20) -> 0 | F19: =SUM(F5*F20) -> 0 | H19: =SUM(H5*H20) -> 0 | I19: =SUM(I5*I20) -> 0 | J19: =SUM(J5*J20) -> 0 | K19: =SUM(K5*K20) -> 0 | L19: =SUM(L5*L20) -> -186510.04 | M19: =SUM(M5*M20) -> -128609.3 | N19: =SUM(N5*N20) -> -427484.46 | O19: =SUM(O5*O20) -> -707963.74 | ... S19: =SUM(S5*S20) -> 293730.62 | U19: =SUM(U5*U20) -> 472377.18 | V19: =SUM(V5*V20) -> 478678.98 | W19: =SUM(W5*W20) -> 495462.32 | X19: =SUM(X5*X20) -> 503596.78 | Y19: =SUM(Y5*Y20) -> 376558.11 | Z19: =SUM(Z5*Z20) -> 357606.77 | AA19: =SUM(AA5*AA20) -> 490684.64 | AB19: =SUM(AB5*AB20) -> 503502.09 | ... AF19: =SUM(AF5*AF20) -> 0
A20: CF(ドル) | C20: =SUM(C6-C11-C12) -> 0 | D20: =SUM(D6-D11-D12) -> 0 | E20: =SUM(E6-E11-E12) -> 0 | F20: =SUM(F6-F11-F12) -> 0 | H20: =SUM(H6-H11-H12) -> 0 | I20: =SUM(I6-I11-I12) -> 0 | J20: =SUM(J6-J11-J12) -> 0 | K20: =SUM(K6-K11-K12) -> 0 | L20: =SUM(L6-L11-L12) -> -1179.1 | M20: =SUM(M6-M11-M12) -> -832.8 | N20: =SUM(N6-N11-N12) -> -2856.18 | O20: =SUM(O6-O11-O12) -> -4734.91 | ... S20: =SUM(S6-S11-S12) -> 1966.2 | U20: =SUM(U6-U11-U12) -> 3215.2 | V20: =SUM(V6-V11-V12) -> 3215.2 | W20: =SUM(W6-W11-W12) -> 3215.2 | X20: =SUM(X6-X11-X12) -> 3215.2 | Y20: =SUM(Y6-Y11-Y12) -> 2405.2 | Z20: =SUM(Z6-Z11-Z12) -> 2327.26 | AA20: =SUM(AA6-AA11-AA12) -> 3149.25 | AB20: =SUM(AB6-AB11-AB12) -> 3149.25 | ... AF20: =SUM(AF6-AF11-AF12) -> 0
A21: PL(円)
A22: PL(ドル)
A24: 購入日 | B24: 45644
A25: 下記表は固都税を各月の諸経費に分散して計上した表です
A26: 301 West 53rd Street #6H | B26: 2024 | C26: 45412 | D26: 45443 | E26: 45473 | F26: 45504 | G26: 2025 | H26: 45535 | I26: 45565 | J26: 45596 | K26: 45626 | L26: 45657 | M26: 45688 | N26: 45716 | O26: 45747 | P26: 45777 | Q26: 45808 | R26: 45838 | S26: 45869 | T26: 2026 | U26: 45900 | V26: 45930 | W26: 45961 | X26: 45991 | Y26: 46022 | Z26: 46053 | AA26: 46081 | AB26: 46112 | AC26: 46142 | AD26: 46173 | AE26: 46203 | AF26: 46234
A27: 取得簿価(円) | B27: =B28*B30 -> 147750000
A28: 取得簿価(ドル) | B28: 985000
A29: 賃料収入(円) | B29: =B30*B31 -> 630000 | C29: =C30*C31 -> 0 | D29: =D30*D31 -> 0 | E29: =E30*E31 -> 0 | F29: =F30*F31 -> 0 | H29: =H30*H31 -> 0 | I29: =I30*I31 -> 0 | J29: =J30*J31 -> 0 | K29: =K30*K31 -> 0 | L29: =L30*L31 -> 0 | M29: =M30*M31 -> 0 | N29: =N30*N31 -> 0 | O29: =O30*O31 -> 627984 | ... S29: =S30*S31 -> 627438 | U29: =U30*U31 -> 617064 | V29: =V30*V31 -> 625296 | W29: =W30*W31 -> 647220 | X29: =X30*X31 -> 657846 | Y29: =Y30*Y31 -> 657552 | Z29: =Z30*Z31 -> 645372 | AA29: =AA30*AA31 -> 654402 | AB29: =AB30*AB31 -> 671496 | ... AF29: =AF30*AF31 -> 0
A30: 為替レート(ドル円)TTM | B30: ='NY不動産(総計)'!B30 -> 150 | C30: ='NY不動産(総計)'!C30 -> 156.9 | D30: ='NY不動産(総計)'!D30 -> 156.74 | E30: ='NY不動産(総計)'!E30 -> 161.07 | F30: ='NY不動産(総計)'!F30 -> 152.44 | H30: ='NY不動産(総計)'!H30 -> 144.8 | I30: ='NY不動産(総計)'!I30 -> 142.73 | J30: ='NY不動産(総計)'!J30 -> 153.64 | K30: ='NY不動産(総計)'!K30 -> 150.74 | L30: ='NY不動産(総計)'!L30 -> 158.18 | M30: ='NY不動産(総計)'!M30 -> 154.43 | N30: ='NY不動産(総計)'!N30 -> 149.67 | O30: ='NY不動産(総計)'!O30 -> 149.52 | ... S30: ='NY不動産(総計)'!S30 -> 149.39 | U30: ='NY不動産(総計)'!U30 -> 146.92 | V30: ='NY不動産(総計)'!V30 -> 148.88 | W30: ='NY不動産(総計)'!W30 -> 154.1 | X30: ='NY不動産(総計)'!X30 -> 156.63 | Y30: ='NY不動産(総計)'!Y30 -> 156.56 | Z30: ='NY不動産(総計)'!Z30 -> 153.66 | AA30: ='NY不動産(総計)'!AA30 -> 155.81 | AB30: ='NY不動産(総計)'!AB30 -> 159.88 | ... AF30: ='NY不動産(総計)'!AF30 -> 0
A31: 賃料収入(ドル) | B31: 4200 | C31: 0 | D31: 0 | E31: 0 | F31: 0 | H31: 0 | I31: 0 | J31: 0 | K31: 0 | L31: 0 | M31: 0 | N31: 0 | O31: 4200 | P31: 4200 | Q31: 4200 | R31: 4200 | S31: 4200 | U31: 4200 | V31: 4200 | W31: 4200 | X31: 4200 | Y31: 4200 | Z31: 4200 | AA31: 4200 | AB31: 4200 | AC31: 4200
A32: 減価償却費(円) | B32: 136145429 | L32: 1270690 | M32: 1270692 | N32: 1270690 | O32: 1270690 | P32: 1270690 | Q32: 1270690 | R32: 1270690 | S32: 1270693 | U32: 1270690 | V32: 1270690 | W32: 1270690 | X32: 1270690 | Y32: 1270690 | Z32: 1270694 | AA32: 1270690 | AB32: 1270690 | AC32: 1270690 | AD32: 1270690 | AE32: 1270690 | AF32: 1270694
A33: 減価償却費(ドル)
A34: 残存簿価(円) | B34: 136145429 | L34: =B34-L32 -> 134874739 | M34: =L34-M32 -> 133604047 | N34: =M34-N32 -> 132333357 | O34: =N34-O32 -> 131062667 | P34: =O34-P32 -> 129791977 | Q34: =P34-Q32 -> 128521287 | R34: =Q34-R32 -> 127250597 | S34: =R34-S32 -> 125979904 | U34: =S34-U32 -> 124709214 | V34: =U34-V32 -> 123438524 | W34: =V34-W32 -> 122167834 | X34: =W34-X32 -> 120897144 | Y34: =X34-Y32 -> 119626454 | Z34: =Y34-Z32 -> 118355760 | AA34: =Z34-AA32 -> 117085070 | AB34: =AA34-AB32 -> 115814380 | AC34: =AB34-AC32 -> 114543690 | ... AF34: =AE34-AF32 -> 110731616
A35: 残存簿価(ドル)
A36: 管理費(ドル) | L36: 45.16 | M36: 100 | N36: 100 | O36: 252 | P36: 252 | Q36: 252 | R36: 252 | S36: 252 | U36: 252 | V36: 252 | W36: 252 | X36: 252 | Y36: 252 | Z36: 252 | AA36: 252 | AB36: 252 | AC36: 252
A37: 諸経費(税金、募集経費等)(ドル) | B37: 41357.25 | L37: 1133.94 | M37: 732.8 | N37: 2756.18 | O37: 6617.77 | P37: 3014.37 | Q37: 3014.37 | R37: 3010.04 | S37: 3010.04 | U37: 1761.04 | V37: 1761.04 | W37: 1761.04 | X37: 1761.04 | Y37: 2571.04 | Z37: 2648.98 | AA37: 1826.99 | AB37: 1028.24 | AC37: 1028.24 | AD37: 1028.24
A38: ネット賃貸収入利回り(円)
A39: ネット賃貸収入利回り(ドル)
A40: 取得時簿価利回り(円) | B40: =B38/B27 -> 0
A41: 取得時簿価利回り(ドル)
A42: 残存簿価利回り(円) | B42: =B38/B34 -> 0
A43: 残存簿価利回り(ドル)
A44: CF(円) | C44: =SUM(C30*C45) -> 0 | D44: =SUM(D30*D45) -> 0 | E44: =SUM(E30*E45) -> 0 | F44: =SUM(F30*F45) -> 0 | H44: =SUM(H30*H45) -> 0 | I44: =SUM(I30*I45) -> 0 | J44: =SUM(J30*J45) -> 0 | K44: =SUM(K30*K45) -> 0 | L44: =SUM(L30*L45) -> -186510.04 | M44: =SUM(M30*M45) -> -128609.3 | N44: =SUM(N30*N45) -> -427484.46 | O44: =SUM(O30*O45) -> -399184.01 | ... S44: =SUM(S30*S45) -> 140121.84 | U44: =SUM(U30*U45) -> 321308.16 | V44: =SUM(V30*V45) -> 325594.6 | W44: =SUM(W30*W45) -> 337010.54 | X44: =SUM(X30*X45) -> 342543.54 | Y44: =SUM(Y30*Y45) -> 215576.86 | Z44: =SUM(Z30*Z45) -> 199607.41 | AA44: =SUM(AA30*AA45) -> 330474.57 | AB44: =SUM(AB30*AB45) -> 466811.23 | ... AF44: =SUM(AF30*AF45) -> 0
A45: CF(ドル) | C45: =SUM(C31-C36-C37) -> 0 | D45: =SUM(D31-D36-D37) -> 0 | E45: =SUM(E31-E36-E37) -> 0 | F45: =SUM(F31-F36-F37) -> 0 | H45: =SUM(H31-H36-H37) -> 0 | I45: =SUM(I31-I36-I37) -> 0 | J45: =SUM(J31-J36-J37) -> 0 | K45: =SUM(K31-K36-K37) -> 0 | L45: =SUM(L31-L36-L37) -> -1179.1 | M45: =SUM(M31-M36-M37) -> -832.8 | N45: =SUM(N31-N36-N37) -> -2856.18 | O45: =SUM(O31-O36-O37) -> -2669.77 | ... S45: =SUM(S31-S36-S37) -> 937.96 | U45: =SUM(U31-U36-U37) -> 2186.96 | V45: =SUM(V31-V36-V37) -> 2186.96 | W45: =SUM(W31-W36-W37) -> 2186.96 | X45: =SUM(X31-X36-X37) -> 2186.96 | Y45: =SUM(Y31-Y36-Y37) -> 1376.96 | Z45: =SUM(Z31-Z36-Z37) -> 1299.02 | AA45: =SUM(AA31-AA36-AA37) -> 2121.01 | AB45: =SUM(AB31-AB36-AB37) -> 2919.76 | ... AF45: =SUM(AF31-AF36-AF37) -> 0
A46: PL(円)
A47: PL(ドル)
R53: 12338.88
R54: 1028.24
R55: 1028.24
R56: 1028.24
R57: 1028.24
R58: 1028.24
R59: 1028.24
R60: 1028.24
R61: 1028.24
R62: 1028.24
R63: 1028.24
R64: 1028.24
R65: 1028.24

Sheet 20W64th#34C
A1: 20 W 64th St #34C(One Lincoln Plaza) | B1: 2024 | C1: 45412 | D1: 45443 | E1: 45473 | F1: 45504 | G1: 2025 | H1: 45535 | I1: 45565 | J1: 45596 | K1: 45626 | L1: 45657 | M1: 45688 | N1: 45716 | O1: 45747 | P1: 45777 | Q1: 45808 | R1: 45838 | S1: 45869 | T1: 2026 | U1: 45900 | V1: 45901 | W1: 45932 | X1: 45963 | Y1: 45994 | Z1: 46023 | AA1: 46054 | AB1: 46082 | AC1: 46113 | AD1: 46143 | AE1: 46174 | AF1: 46204
A2: 取得簿価(円) | B2: =B3*160 -> 155200000
A3: 取得簿価(ドル) | B3: 970000
A4: 賃料収入(円) | B4: =B6*B5 -> 742500 | C4: =C5*C6 -> 0 | D4: =D5*D6 -> 0 | E4: =E5*E6 -> 0 | F4: =F5*F6 -> 0 | H4: =H5*H6 -> 0 | I4: =I5*I6 -> 0 | J4: =J5*J6 -> 0 | K4: =K5*K6 -> 0 | L4: =L5*L6 -> 0 | M4: =M5*M6 -> 0 | N4: =N5*N6 -> 0 | O4: =O5*O6 -> 0 | ... S4: =S5*S6 -> 0 | U4: =U5*U6 -> 0 | V4: =V5*V6 -> 156536.9 | W4: =W5*W6 -> 762795 | X4: =X5*X6 -> 775318.5 | Y4: =Y5*Y6 -> 774972 | Z4: =Z5*Z6 -> 760617 | AA4: =AA5*AA6 -> 771259.5 | AB4: =AB5*AB6 -> 791406 | ... AF4: =AF5*AF6 -> 0
A5: 為替レート(ドル円)TTM | B5: ='NY不動産(総計)'!B5 -> 150 | C5: ='NY不動産(総計)'!C5 -> 156.9 | D5: ='NY不動産(総計)'!D5 -> 156.74 | E5: ='NY不動産(総計)'!E5 -> 161.07 | F5: ='NY不動産(総計)'!F5 -> 152.44 | H5: ='NY不動産(総計)'!H5 -> 144.8 | I5: ='NY不動産(総計)'!I5 -> 142.73 | J5: ='NY不動産(総計)'!J5 -> 153.64 | K5: ='NY不動産(総計)'!K5 -> 150.74 | L5: ='NY不動産(総計)'!L5 -> 158.18 | M5: ='NY不動産(総計)'!M5 -> 154.43 | N5: ='NY不動産(総計)'!N5 -> 149.67 | O5: ='NY不動産(総計)'!O5 -> 149.52 | ... S5: ='NY不動産(総計)'!S5 -> 149.39 | U5: ='NY不動産(総計)'!U5 -> 146.92 | V5: ='NY不動産(総計)'!V5 -> 148.88 | W5: ='NY不動産(総計)'!W5 -> 154.1 | X5: ='NY不動産(総計)'!X5 -> 156.63 | Y5: ='NY不動産(総計)'!Y5 -> 156.56 | Z5: ='NY不動産(総計)'!Z5 -> 153.66 | AA5: ='NY不動産(総計)'!AA5 -> 155.81 | AB5: ='NY不動産(総計)'!AB5 -> 159.88 | ... AF5: ='NY不動産(総計)'!AF5 -> 0
A6: 賃料収入(ドル) | B6: 4950 | C6: 0 | D6: 0 | E6: 0 | F6: 0 | H6: 0 | I6: 0 | J6: 0 | K6: 0 | L6: 0 | M6: 0 | N6: 0 | O6: 0 | P6: 0 | Q6: 0 | R6: 0 | S6: 0 | U6: 0 | V6: 1051.43 | W6: 4950 | X6: 4950 | Y6: 4950 | Z6: 4950 | AA6: 4950 | AB6: 4950
A7: 減価償却費(円) | U7: 1025794 | V7: 1025794 | W7: 1025794 | X7: 1025794 | Y7: 1025794 | Z7: 1025796 | AA7: 1025794 | AB7: 1025794 | AC7: 1025794 | AD7: 1025794 | AE7: 1025794 | AF7: 1025797
A8: 減価償却費(ドル)
A9: 残存簿価(円) | S9: 108880758 | U9: =S9-U7 -> 107854964 | V9: =U9-V7 -> 106829170 | W9: =V9-W7 -> 105803376 | X9: =W9-X7 -> 104777582 | Y9: =X9-Y7 -> 103751788 | Z9: =Y9-Z7 -> 102725992 | AA9: =Z9-AA7 -> 101700198 | AB9: =AA9-AB7 -> 100674404 | AC9: =AB9-AC7 -> 99648610 | ... AF9: =AE9-AF7 -> 96571225
A10: 残存簿価(ドル)
A11: 管理費(ドル) | S11: 500 | U11: 100 | V11: 100 | W11: 346.5 | X11: 346.5 | Y11: 346.5 | Z11: 346.5 | AA11: 346.5 | AB11: 346.5 | AG11: =SUM(C36:AF36) -> 2779 | AH11: 管理費
A12: 諸経費(税金、募集経費等)(ドル) | B12: 24758.32 | S12: 310.16 | U12: 924.31 | V12: 37591.94 | W12: 1259.4 | X12: 924.31 | Y12: 949.31 | Z12: 952.04 | AA12: 952.04 | AB12: 952.04 | AG12: 1222.47 | AH12: コモンチャージ
A13: ネット賃貸収入利回り(円) | AG13: 0 | AH13: 固定資産税
A14: ネット賃貸収入利回り(ドル) | AG14: 12 | AH14: 修繕・雑費・その他支出
A15: 取得時簿価利回り(円) | B15: =B13/B2 -> 0 | AG15: =SUM(AG11:AG14) -> 4013.47 | AH15: 合計
A16: 取得時簿価利回り(ドル)
A17: 残存簿価利回り(円) | B17: =B13/B9 -> #DIV/0!
A18: 残存簿価利回り(ドル)
A19: CF(円) | C19: =SUM(C5*C20) -> 0 | D19: =SUM(D5*D20) -> 0 | E19: =SUM(E5*E20) -> 0 | F19: =SUM(F5*F20) -> 0 | H19: =SUM(H5*H20) -> 0 | I19: =SUM(I5*I20) -> 0 | J19: =SUM(J5*J20) -> 0 | K19: =SUM(K5*K20) -> 0 | L19: =SUM(L5*L20) -> 0 | M19: =SUM(M5*M20) -> 0 | N19: =SUM(N5*N20) -> 0 | O19: =SUM(O5*O20) -> 0 | ... S19: =SUM(S5*S20) -> -121029.8 | U19: =SUM(U5*U20) -> -150491.63 | V19: =SUM(V5*V20) -> -5455039.1 | W19: =SUM(W5*W20) -> 515325.81 | X19: =SUM(X5*X20) -> 576271.53 | Y19: =SUM(Y5*Y20) -> 572099.99 | Z19: =SUM(Z5*Z20) -> 561083.34 | AA19: =SUM(AA5*AA20) -> 568933.98 | AB19: =SUM(AB5*AB20) -> 583795.42 | ... AF19: =SUM(AF5*AF20) -> 0
A20: CF(ドル) | C20: =SUM(C6-C11-C12) -> 0 | D20: =SUM(D6-D11-D12) -> 0 | E20: =SUM(E6-E11-E12) -> 0 | F20: =SUM(F6-F11-F12) -> 0 | H20: =SUM(H6-H11-H12) -> 0 | I20: =SUM(I6-I11-I12) -> 0 | J20: =SUM(J6-J11-J12) -> 0 | K20: =SUM(K6-K11-K12) -> 0 | L20: =SUM(L6-L11-L12) -> 0 | M20: =SUM(M6-M11-M12) -> 0 | N20: =SUM(N6-N11-N12) -> 0 | O20: =SUM(O6-O11-O12) -> 0 | ... S20: =SUM(S6-S11-S12) -> -810.16 | U20: =SUM(U6-U11-U12) -> -1024.31 | V20: =SUM(V6-V11-V12) -> -36640.51 | W20: =SUM(W6-W11-W12) -> 3344.1 | X20: =SUM(X6-X11-X12) -> 3679.19 | Y20: =SUM(Y6-Y11-Y12) -> 3654.19 | Z20: =SUM(Z6-Z11-Z12) -> 3651.46 | AA20: =SUM(AA6-AA11-AA12) -> 3651.46 | AB20: =SUM(AB6-AB11-AB12) -> 3651.46 | ... AF20: =SUM(AF6-AF11-AF12) -> 0
A21: PL(円)
A22: PL(ドル)
A24: 購入日 | B24: 45860
A25: 下記表は固都税を各月の諸経費に分散して計上した表です
A26: 20 W 64th St #34C(One Lincoln Plaza) | B26: 2024 | C26: 45412 | D26: 45443 | E26: 45473 | F26: 45504 | G26: 2025 | H26: 45535 | I26: 45565 | J26: 45596 | K26: 45626 | L26: 45657 | M26: 45688 | N26: 45716 | O26: 45747 | P26: 45777 | Q26: 45808 | R26: 45838 | S26: 45869 | T26: 2026 | U26: 45900 | V26: 45901 | W26: 45932 | X26: 45963 | Y26: 45994 | Z26: 46023 | AA26: 46054 | AB26: 46082 | AC26: 46113 | AD26: 46143 | AE26: 46174 | AF26: 46204
A27: 取得簿価(円) | B27: =B28*160 -> 155200000
A28: 取得簿価(ドル) | B28: 970000
A29: 賃料収入(円) | B29: =B31*B30 -> 0 | C29: =C30*C31 -> 0 | D29: =D30*D31 -> 0 | E29: =E30*E31 -> 0 | F29: =F30*F31 -> 0 | H29: =H30*H31 -> 0 | I29: =I30*I31 -> 0 | J29: =J30*J31 -> 0 | K29: =K30*K31 -> 0 | L29: =L30*L31 -> 0 | M29: =M30*M31 -> 0 | N29: =N30*N31 -> 0 | O29: =O30*O31 -> 0 | ... S29: =S30*S31 -> 0 | U29: =U30*U31 -> 0 | V29: =V30*V31 -> 156536.9 | W29: =W30*W31 -> 762795 | X29: =X30*X31 -> 775318.5 | Y29: =Y30*Y31 -> 774972 | Z29: =Z30*Z31 -> 760617 | AA29: =AA30*AA31 -> 771259.5 | AB29: =AB30*AB31 -> 791406 | ... AF29: =AF30*AF31 -> 0
A30: 為替レート(ドル円)TTM | B30: ='NY不動産(総計)'!B30 -> 150 | C30: ='NY不動産(総計)'!C30 -> 156.9 | D30: ='NY不動産(総計)'!D30 -> 156.74 | E30: ='NY不動産(総計)'!E30 -> 161.07 | F30: ='NY不動産(総計)'!F30 -> 152.44 | H30: ='NY不動産(総計)'!H30 -> 144.8 | I30: ='NY不動産(総計)'!I30 -> 142.73 | J30: ='NY不動産(総計)'!J30 -> 153.64 | K30: ='NY不動産(総計)'!K30 -> 150.74 | L30: ='NY不動産(総計)'!L30 -> 158.18 | M30: ='NY不動産(総計)'!M30 -> 154.43 | N30: ='NY不動産(総計)'!N30 -> 149.67 | O30: ='NY不動産(総計)'!O30 -> 149.52 | ... S30: ='NY不動産(総計)'!S30 -> 149.39 | U30: ='NY不動産(総計)'!U30 -> 146.92 | V30: ='NY不動産(総計)'!V30 -> 148.88 | W30: ='NY不動産(総計)'!W30 -> 154.1 | X30: ='NY不動産(総計)'!X30 -> 156.63 | Y30: ='NY不動産(総計)'!Y30 -> 156.56 | Z30: ='NY不動産(総計)'!Z30 -> 153.66 | AA30: ='NY不動産(総計)'!AA30 -> 155.81 | AB30: ='NY不動産(総計)'!AB30 -> 159.88 | ... AF30: ='NY不動産(総計)'!AF30 -> 0
A31: 賃料収入(ドル) | U31: 0 | V31: 1051.43 | W31: 4950 | X31: 4950 | Y31: 4950 | Z31: 4950 | AA31: 4950 | AB31: 4950
A32: 減価償却費(円) | U32: 1025794 | V32: 1025794 | W32: 1025794 | X32: 1025794 | Y32: 1025794 | Z32: 1025796 | AA32: 1025794 | AB32: 1025794 | AC32: 1025794 | AD32: 1025794 | AE32: 1025794 | AF32: 1025797
A33: 減価償却費(ドル)
A34: 残存簿価(円) | I34: =B34-I32 -> 0 | J34: =I34-J32 -> 0 | K34: =J34-K32 -> 0 | L34: =K34-L32 -> 0 | M34: =L34-M32 -> 0 | N34: =M34-N32 -> 0 | O34: =N34-O32 -> 0 | P34: =O34-P32 -> 0 | Q34: =P34-Q32 -> 0 | R34: =Q34-R32 -> 0 | S34: 108880758 | U34: =S34-U32 -> 107854964 | V34: =U34-V32 -> 106829170 | W34: =V34-W32 -> 105803376 | X34: =W34-X32 -> 104777582 | Y34: =X34-Y32 -> 103751788 | Z34: =Y34-Z32 -> 102725992 | AA34: =Z34-AA32 -> 101700198 | AB34: =AA34-AB32 -> 100674404 | AC34: =AB34-AC32 -> 99648610 | ... AF34: =AE34-AF32 -> 96571225
A35: 残存簿価(ドル)
A36: 管理費(ドル) | S36: 500 | U36: 100 | V36: 100 | W36: 346.5 | X36: 346.5 | Y36: 346.5 | Z36: 346.5 | AA36: 346.5 | AB36: 346.5
A37: 諸経費(税金、募集経費等)(ドル) | B37: 24758.32 | S37: 310.16 | U37: 924.31 | V37: 30587.62 | W37: 2134.94 | X37: 1799.85 | Y37: 1824.85 | Z37: 1827.58 | AA37: 1827.58 | AB37: 875.54 | AC37: 875.54 | AD37: 875.54
A38: ネット賃貸収入利回り(円)
A39: ネット賃貸収入利回り(ドル)
A40: 取得時簿価利回り(円) | B40: =B38/B27 -> 0
A41: 取得時簿価利回り(ドル)
A42: 残存簿価利回り(円) | B42: =B38/B34 -> #DIV/0!
A43: 残存簿価利回り(ドル)
A44: CF(円) | C44: =SUM(C30*C45) -> 0 | D44: =SUM(D30*D45) -> 0 | E44: =SUM(E30*E45) -> 0 | F44: =SUM(F30*F45) -> 0 | H44: =SUM(H30*H45) -> 0 | I44: =SUM(I30*I45) -> 0 | J44: =SUM(J30*J45) -> 0 | K44: =SUM(K30*K45) -> 0 | L44: =SUM(L30*L45) -> 0 | M44: =SUM(M30*M45) -> 0 | N44: =SUM(N30*N45) -> 0 | O44: =SUM(O30*O45) -> 0 | ... S44: =SUM(S30*S45) -> -121029.8 | U44: =SUM(U30*U45) -> -150491.63 | V44: =SUM(V30*V45) -> -4412236 | W44: =SUM(W30*W45) -> 380405.1 | X44: =SUM(X30*X45) -> 439135.7 | Y44: =SUM(Y30*Y45) -> 435025.44 | Z44: =SUM(Z30*Z45) -> 426547.87 | AA44: =SUM(AA30*AA45) -> 432516.1 | AB44: =SUM(AB30*AB45) -> 596026.24 | ... AF44: =SUM(AF30*AF45) -> 0
A45: CF(ドル) | C45: =SUM(C31-C36-C37) -> 0 | D45: =SUM(D31-D36-D37) -> 0 | E45: =SUM(E31-E36-E37) -> 0 | F45: =SUM(F31-F36-F37) -> 0 | H45: =SUM(H31-H36-H37) -> 0 | I45: =SUM(I31-I36-I37) -> 0 | J45: =SUM(J31-J36-J37) -> 0 | K45: =SUM(K31-K36-K37) -> 0 | L45: =SUM(L31-L36-L37) -> 0 | M45: =SUM(M31-M36-M37) -> 0 | N45: =SUM(N31-N36-N37) -> 0 | O45: =SUM(O31-O36-O37) -> 0 | ... S45: =SUM(S31-S36-S37) -> -810.16 | U45: =SUM(U31-U36-U37) -> -1024.31 | V45: =SUM(V31-V36-V37) -> -29636.19 | W45: =SUM(W31-W36-W37) -> 2468.56 | X45: =SUM(X31-X36-X37) -> 2803.65 | Y45: =SUM(Y31-Y36-Y37) -> 2778.65 | Z45: =SUM(Z31-Z36-Z37) -> 2775.92 | AA45: =SUM(AA31-AA36-AA37) -> 2775.92 | AB45: =SUM(AB31-AB36-AB37) -> 3727.96 | ... AF45: =SUM(AF31-AF36-AF37) -> 0
A46: PL(円)
A47: PL(ドル)
R50: 20198.14 | V50: 7879.87
Q51: 1 | R51: 1683.16 | U51: 1 | V51: 875.55
Q52: 2 | R52: 1683.18 | U52: 2 | V52: 875.54
Q53: 3 | R53: 1683.18 | U53: 3 | V53: 875.54
Q54: 4 | R54: 1683.18 | U54: 4 | V54: 875.54
Q55: 5 | R55: 1683.18 | U55: 5 | V55: 875.54
Q56: 6 | R56: 1683.18 | U56: 6 | V56: 875.54
Q57: 7 | R57: 1683.18 | U57: 7 | V57: 875.54
Q58: 8 | R58: 1683.18 | U58: 8 | V58: 875.54
Q59: 9 | R59: 1683.18 | U59: 9 | V59: 875.54
Q60: 10 | R60: 1683.18 | V60: =SUM(V51:V59) -> 7879.87
Q61: 11 | R61: 1683.18
Q62: 12 | R62: 1683.18
R63: =SUM(R51:R62) -> 20198.14

Sheet 235W75th#225
A1: 235 W 75th St #225(The Astor) | B1: 2024 | C1: 45412 | D1: 45443 | E1: 45473 | F1: 45504 | G1: 2025 | H1: 45535 | I1: 45565 | J1: 45596 | K1: 45626 | L1: 45657 | M1: 45688 | N1: 45716 | O1: 45747 | P1: 45777 | Q1: 45808 | R1: 45838 | S1: 45869 | T1: 2026 | U1: 45900 | V1: 45901 | W1: 45932 | X1: 45963 | Y1: 45994 | Z1: 46023 | AA1: 46054 | AB1: 46082 | AC1: 46113 | AD1: 46143 | AE1: 46174 | AF1: 46204
A2: 取得簿価(円) | B2: =B3*160 -> 178400000
A3: 取得簿価(ドル) | B3: 1115000
A4: 賃料収入(円) | B4: =B6*B5 -> 952500 | C4: =C5*C6 -> 0 | D4: =D5*D6 -> 0 | E4: =E5*E6 -> 0 | F4: =F5*F6 -> 0 | H4: =H5*H6 -> 0 | I4: =I5*I6 -> 0 | J4: =J5*J6 -> 0 | K4: =K5*K6 -> 0 | L4: =L5*L6 -> 0 | M4: =M5*M6 -> 0 | N4: =N5*N6 -> 0 | O4: =O5*O6 -> 0 | ... S4: =S5*S6 -> 0 | U4: =U5*U6 -> 0 | V4: =V5*V6 -> 0 | W4: =W5*W6 -> 0 | X4: =X5*X6 -> 2349.45 | Y4: =Y5*Y6 -> 2348.4 | Z4: =Z5*Z6 -> 545345.49 | AA4: =AA5*AA6 -> 989393.5 | AB4: =AB5*AB6 -> 1046189.2 | ... AF4: =AF5*AF6 -> 0
A5: 為替レート(ドル円)TTM | B5: ='NY不動産(総計)'!B5 -> 150 | C5: ='NY不動産(総計)'!C5 -> 156.9 | D5: ='NY不動産(総計)'!D5 -> 156.74 | E5: ='NY不動産(総計)'!E5 -> 161.07 | F5: ='NY不動産(総計)'!F5 -> 152.44 | H5: ='NY不動産(総計)'!H5 -> 144.8 | I5: ='NY不動産(総計)'!I5 -> 142.73 | J5: ='NY不動産(総計)'!J5 -> 153.64 | K5: ='NY不動産(総計)'!K5 -> 150.74 | L5: ='NY不動産(総計)'!L5 -> 158.18 | M5: ='NY不動産(総計)'!M5 -> 154.43 | N5: ='NY不動産(総計)'!N5 -> 149.67 | O5: ='NY不動産(総計)'!O5 -> 149.52 | ... S5: ='NY不動産(総計)'!S5 -> 149.39 | U5: ='NY不動産(総計)'!U5 -> 146.92 | V5: ='NY不動産(総計)'!V5 -> 148.88 | W5: ='NY不動産(総計)'!W5 -> 154.1 | X5: ='NY不動産(総計)'!X5 -> 156.63 | Y5: ='NY不動産(総計)'!Y5 -> 156.56 | Z5: ='NY不動産(総計)'!Z5 -> 153.66 | AA5: ='NY不動産(総計)'!AA5 -> 155.81 | AB5: ='NY不動産(総計)'!AB5 -> 159.88 | ... AF5: ='NY不動産(総計)'!AF5 -> 0
A6: 賃料収入(ドル) | B6: 6350 | C6: 0 | D6: 0 | E6: 0 | F6: 0 | H6: 0 | I6: 0 | J6: 0 | K6: 0 | L6: 0 | M6: 0 | N6: 0 | O6: 0 | P6: 0 | Q6: 0 | R6: 0 | S6: 0 | U6: 0 | V6: 0 | W6: 0 | X6: 15 | Y6: 15 | Z6: 3549.04 | AA6: 6350 | AB6: 6543.59
A7: 減価償却費(円) | W7: 1767186 | X7: 1767186 | Y7: 1767186 | Z7: 1767186 | AA7: 1767186 | AB7: 1767186 | AC7: 1767186 | AD7: 1767186 | AE7: 1767186 | AF7: 1767186
A8: 減価償却費(ドル)
A9: 残存簿価(円) | S9: =R9-S7 -> 0 | U9: =S9-U7 -> 0 | V9: 126983430 | W9: =V9-W7 -> 125216244 | X9: =W9-X7 -> 123449058 | Y9: =X9-Y7 -> 121681872 | Z9: =Y9-Z7 -> 119914686 | AA9: =Z9-AA7 -> 118147500 | AB9: =AA9-AB7 -> 116380314 | AC9: =AB9-AC7 -> 114613128 | AD9: =AC9-AD7 -> 112845942 | ... AF9: =AE9-AF7 -> 109311570
A10: 残存簿価(ドル)
A11: 管理費(ドル) | W11: 500 | X11: 100 | Y11: 100 | Z11: 444.5 | AA11: 444.5 | AB11: 444.5 | AG11: =SUM(C36:AF36) -> 2033.5 | AH11: 管理費
A12: 諸経費(税金、募集経費等)(ドル) | B12: 57723.96 | W12: 635.84 | X12: 1494.69 | Y12: 10050.59 | Z12: 7858.69 | AA12: 1399.22 | AB12: 1208.69 | AH12: コモンチャージ
A13: ネット賃貸収入利回り(円) | AG13: 0 | AH13: 固定資産税
A14: ネット賃貸収入利回り(ドル) | AH14: 修繕・雑費・その他支出
A15: 取得時簿価利回り(円) | B15: =B13/B2 -> 0 | AG15: =SUM(AG11:AG14) -> 2033.5 | AH15: 合計
A16: 取得時簿価利回り(ドル)
A17: 残存簿価利回り(円) | B17: =B13/B9 -> #DIV/0!
A18: 残存簿価利回り(ドル)
A19: CF(円) | C19: =SUM(C5*C20) -> 0 | D19: =SUM(D5*D20) -> 0 | E19: =SUM(E5*E20) -> 0 | F19: =SUM(F5*F20) -> 0 | H19: =SUM(H5*H20) -> 0 | I19: =SUM(I5*I20) -> 0 | J19: =SUM(J5*J20) -> 0 | K19: =SUM(K5*K20) -> 0 | L19: =SUM(L5*L20) -> 0 | M19: =SUM(M5*M20) -> 0 | N19: =SUM(N5*N20) -> 0 | O19: =SUM(O5*O20) -> 0 | ... S19: =SUM(S5*S20) -> 0 | U19: =SUM(U5*U20) -> 0 | V19: =SUM(V5*V20) -> 0 | W19: =SUM(W5*W20) -> -175032.94 | X19: =SUM(X5*X20) -> -247426.84 | Y19: =SUM(Y5*Y20) -> -1586828 | Z19: =SUM(Z5*Z20) -> -730522.69 | AA19: =SUM(AA5*AA20) -> 702123.49 | AB19: =SUM(AB5*AB20) -> 781877.15 | ... AF19: =SUM(AF5*AF20) -> 0
A20: CF(ドル) | C20: =SUM(C6-C11-C12) -> 0 | D20: =SUM(D6-D11-D12) -> 0 | E20: =SUM(E6-E11-E12) -> 0 | F20: =SUM(F6-F11-F12) -> 0 | H20: =SUM(H6-H11-H12) -> 0 | I20: =SUM(I6-I11-I12) -> 0 | J20: =SUM(J6-J11-J12) -> 0 | K20: =SUM(K6-K11-K12) -> 0 | L20: =SUM(L6-L11-L12) -> 0 | M20: =SUM(M6-M11-M12) -> 0 | N20: =SUM(N6-N11-N12) -> 0 | O20: =SUM(O6-O11-O12) -> 0 | ... S20: =SUM(S6-S11-S12) -> 0 | U20: =SUM(U6-U11-U12) -> 0 | V20: =SUM(V6-V11-V12) -> 0 | W20: =SUM(W6-W11-W12) -> -1135.84 | X20: =SUM(X6-X11-X12) -> -1579.69 | Y20: =SUM(Y6-Y11-Y12) -> -10135.59 | Z20: =SUM(Z6-Z11-Z12) -> -4754.15 | AA20: =SUM(AA6-AA11-AA12) -> 4506.28 | AB20: =SUM(AB6-AB11-AB12) -> 4890.4 | ... AF20: =SUM(AF6-AF11-AF12) -> 0
A21: PL(円)
A22: PL(ドル)
A24: 購入日 | B24: 46311
A25: 下記表は固都税を各月の諸経費に分散して計上した表です
A26: 20 W 64th St #34C(One Lincoln Plaza) | B26: 2024 | C26: 45412 | D26: 45443 | E26: 45473 | F26: 45504 | G26: 2025 | H26: 45535 | I26: 45565 | J26: 45596 | K26: 45626 | L26: 45657 | M26: 45688 | N26: 45716 | O26: 45747 | P26: 45777 | Q26: 45808 | R26: 45838 | S26: 45869 | T26: 2026 | U26: 45900 | V26: 45901 | W26: 45932 | X26: 45963 | Y26: 45994 | Z26: 46023 | AA26: 46054 | AB26: 46082 | AC26: 46113 | AD26: 46143 | AE26: 46174 | AF26: 46204
A27: 取得簿価(円) | B27: =B28*160 -> 178400000
A28: 取得簿価(ドル) | B28: =B3 -> 1115000
A29: 賃料収入(円) | B29: =B31*B30 -> 0 | C29: =C30*C31 -> 0 | D29: =D30*D31 -> 0 | E29: =E30*E31 -> 0 | F29: =F30*F31 -> 0 | H29: =H30*H31 -> 0 | I29: =I30*I31 -> 0 | J29: =J30*J31 -> 0 | K29: =K30*K31 -> 0 | L29: =L30*L31 -> 0 | M29: =M30*M31 -> 0 | N29: =N30*N31 -> 0 | O29: =O30*O31 -> 0 | ... S29: =S30*S31 -> 0 | U29: =U30*U31 -> 0 | V29: =V30*V31 -> 0 | W29: =W30*W31 -> 0 | X29: =X30*X31 -> 2349.45 | Y29: =Y30*Y31 -> 2348.4 | Z29: =Z30*Z31 -> 545345.49 | AA29: =AA30*AA31 -> 989393.5 | AB29: =AB30*AB31 -> 1046189.2 | ... AF29: =AF30*AF31 -> 0
A30: 為替レート(ドル円)TTM | B30: ='NY不動産(総計)'!B30 -> 150 | C30: ='NY不動産(総計)'!C30 -> 156.9 | D30: ='NY不動産(総計)'!D30 -> 156.74 | E30: ='NY不動産(総計)'!E30 -> 161.07 | F30: ='NY不動産(総計)'!F30 -> 152.44 | H30: ='NY不動産(総計)'!H30 -> 144.8 | I30: ='NY不動産(総計)'!I30 -> 142.73 | J30: ='NY不動産(総計)'!J30 -> 153.64 | K30: ='NY不動産(総計)'!K30 -> 150.74 | L30: ='NY不動産(総計)'!L30 -> 158.18 | M30: ='NY不動産(総計)'!M30 -> 154.43 | N30: ='NY不動産(総計)'!N30 -> 149.67 | O30: ='NY不動産(総計)'!O30 -> 149.52 | ... S30: ='NY不動産(総計)'!S30 -> 149.39 | U30: ='NY不動産(総計)'!U30 -> 146.92 | V30: ='NY不動産(総計)'!V30 -> 148.88 | W30: ='NY不動産(総計)'!W30 -> 154.1 | X30: ='NY不動産(総計)'!X30 -> 156.63 | Y30: ='NY不動産(総計)'!Y30 -> 156.56 | Z30: ='NY不動産(総計)'!Z30 -> 153.66 | AA30: ='NY不動産(総計)'!AA30 -> 155.81 | AB30: ='NY不動産(総計)'!AB30 -> 159.88 | ... AF30: ='NY不動産(総計)'!AF30 -> 0
A31: 賃料収入(ドル) | X31: 15 | Y31: 15 | Z31: 3549.04 | AA31: 6350 | AB31: 6543.59
A32: 減価償却費(円)
A33: 減価償却費(ドル)
A34: 残存簿価(円) | I34: =B34-I32 -> 0 | J34: =I34-J32 -> 0 | K34: =J34-K32 -> 0 | L34: =K34-L32 -> 0 | M34: =L34-M32 -> 0 | N34: =M34-N32 -> 0 | O34: =N34-O32 -> 0 | P34: =O34-P32 -> 0 | Q34: =P34-Q32 -> 0 | ... S34: =R34-S32 -> 0 | U34: =S34-U32 -> 0 | V34: =U34-V32 -> 0 | W34: =V34-W32 -> 0 | X34: =W34-X32 -> 0 | Y34: =X34-Y32 -> 0 | Z34: =Y34-Z32 -> 0 | AA34: =Z34-AA32 -> 0 | AB34: =AA34-AB32 -> 0 | AC34: =AB34-AC32 -> 0 | ... AF34: =AE34-AF32 -> 0
A35: 残存簿価(ドル)
A36: 管理費(ドル) | W36: 500 | X36: 100 | Y36: 100 | Z36: 444.5 | AA36: 444.5 | AB36: 444.5
A37: 諸経費(税金、募集経費等)(ドル) | B37: 57723.96 | W37: 635.84 | X37: 1494.69 | Y37: 2754.39 | Z37: 9317.93 | AA37: 2858.46 | AB37: 1459.24 | AC37: 1459.24 | AD37: 1459.24
A38: ネット賃貸収入利回り(円)
A39: ネット賃貸収入利回り(ドル)
A40: 取得時簿価利回り(円) | B40: =B38/B27 -> 0
A41: 取得時簿価利回り(ドル)
A42: 残存簿価利回り(円) | B42: =B38/B34 -> #DIV/0!
A43: 残存簿価利回り(ドル)
A44: CF(円) | C44: =SUM(C30*C45) -> 0 | D44: =SUM(D30*D45) -> 0 | E44: =SUM(E30*E45) -> 0 | F44: =SUM(F30*F45) -> 0 | H44: =SUM(H30*H45) -> 0 | I44: =SUM(I30*I45) -> 0 | J44: =SUM(J30*J45) -> 0 | K44: =SUM(K30*K45) -> 0 | L44: =SUM(L30*L45) -> 0 | M44: =SUM(M30*M45) -> 0 | N44: =SUM(N30*N45) -> 0 | O44: =SUM(O30*O45) -> 0 | ... S44: =SUM(S30*S45) -> 0 | U44: =SUM(U30*U45) -> 0 | V44: =SUM(V30*V45) -> 0 | W44: =SUM(W30*W45) -> -175032.94 | X44: =SUM(X30*X45) -> -247426.84 | Y44: =SUM(Y30*Y45) -> -444534.9 | Z44: =SUM(Z30*Z45) -> -954749.51 | AA44: =SUM(AA30*AA45) -> 474759.3 | AB44: =SUM(AB30*AB45) -> 741819.22 | ... AF44: =SUM(AF30*AF45) -> 0
A45: CF(ドル) | C45: =SUM(C31-C36-C37) -> 0 | D45: =SUM(D31-D36-D37) -> 0 | E45: =SUM(E31-E36-E37) -> 0 | F45: =SUM(F31-F36-F37) -> 0 | H45: =SUM(H31-H36-H37) -> 0 | I45: =SUM(I31-I36-I37) -> 0 | J45: =SUM(J31-J36-J37) -> 0 | K45: =SUM(K31-K36-K37) -> 0 | L45: =SUM(L31-L36-L37) -> 0 | M45: =SUM(M31-M36-M37) -> 0 | N45: =SUM(N31-N36-N37) -> 0 | O45: =SUM(O31-O36-O37) -> 0 | ... S45: =SUM(S31-S36-S37) -> 0 | U45: =SUM(U31-U36-U37) -> 0 | V45: =SUM(V31-V36-V37) -> 0 | W45: =SUM(W31-W36-W37) -> -1135.84 | X45: =SUM(X31-X36-X37) -> -1579.69 | Y45: =SUM(Y31-Y36-Y37) -> -2839.39 | Z45: =SUM(Z31-Z36-Z37) -> -6213.39 | AA45: =SUM(AA31-AA36-AA37) -> 3047.04 | AB45: =SUM(AB31-AB36-AB37) -> 4639.85 | ... AF45: =SUM(AF31-AF36-AF37) -> 0
A46: PL(円)
A47: PL(ドル)
R50: 20198.14 | V50: 7879.87 | X50: 8755.47
Q51: 1 | R51: 1683.16 | U51: 1 | V51: 875.55 | X51: 1459.27
Q52: 2 | R52: 1683.18 | U52: 2 | V52: 875.54 | X52: 1459.24
Q53: 3 | R53: 1683.18 | U53: 3 | V53: 875.54 | X53: 1459.24
Q54: 4 | R54: 1683.18 | U54: 4 | V54: 875.54 | X54: 1459.24
Q55: 5 | R55: 1683.18 | U55: 5 | V55: 875.54 | X55: 1459.24
Q56: 6 | R56: 1683.18 | U56: 6 | V56: 875.54 | X56: 1459.24
Q57: 7 | R57: 1683.18 | U57: 7 | V57: 875.54 | X57: =SUM(X51:X56) -> 8755.47
Q58: 8 | R58: 1683.18 | U58: 8 | V58: 875.54
Q59: 9 | R59: 1683.18 | U59: 9 | V59: 875.54
Q60: 10 | R60: 1683.18 | V60: =SUM(V51:V59) -> 7879.87
Q61: 11 | R61: 1683.18
Q62: 12 | R62: 1683.18
R63: =SUM(R51:R62) -> 20198.14

Sheet 1Wall#731(GRE)
A1: 1 Wall St #731 | B1: 2024 | C1: 45412 | D1: 45443 | E1: 45473 | F1: 45504 | G1: 2025 | H1: 45535 | I1: 45565 | J1: 45596 | K1: 45626 | L1: 45657 | M1: 45688 | N1: 45716 | O1: 45747 | P1: 45777 | Q1: 45808 | R1: 45838 | S1: 45869 | T1: 2026 | U1: 45900 | V1: 45930 | W1: 45961 | X1: 45991 | Y1: 46022 | Z1: 46053 | AA1: 46081 | AB1: 46112 | AC1: 46142 | AD1: 46173 | AE1: 46203 | AF1: 46234
A2: 取得簿価(円) | B2: =B3*160 -> 0
A3: 取得簿価(ドル) | B3: 0
A4: 賃料収入(円) | B4: =B6*B5 -> 975000 | C4: =C5*C6 -> 0 | D4: =D5*D6 -> 0 | E4: =E5*E6 -> 0 | F4: =F5*F6 -> 0 | H4: =H5*H6 -> 0 | I4: =I5*I6 -> 0 | J4: =J5*J6 -> 0 | K4: =K5*K6 -> 0 | L4: =L5*L6 -> 0 | M4: =M5*M6 -> 0 | N4: =N5*N6 -> 0 | O4: =O5*O6 -> 0 | ... S4: =S5*S6 -> 0 | U4: =U5*U6 -> 954980 | V4: =V5*V6 -> 967720 | W4: =W5*W6 -> 1002425.1 | X4: =X5*X6 -> 1024330.4 | Y4: =Y5*Y6 -> 1023464 | Z4: =Z5*Z6 -> 1005457.3 | AA4: =AA5*AA6 -> 1012765 | AB4: =AB5*AB6 -> 1067625.9 | ... AF4: =AF5*AF6 -> 0
A5: 為替レート(ドル円)TTM | B5: ='NY不動産(総計)'!B5 -> 150 | C5: ='NY不動産(総計)'!C5 -> 156.9 | D5: ='NY不動産(総計)'!D5 -> 156.74 | E5: ='NY不動産(総計)'!E5 -> 161.07 | F5: ='NY不動産(総計)'!F5 -> 152.44 | H5: ='NY不動産(総計)'!H5 -> 144.8 | I5: ='NY不動産(総計)'!I5 -> 142.73 | J5: ='NY不動産(総計)'!J5 -> 153.64 | K5: ='NY不動産(総計)'!K5 -> 150.74 | L5: ='NY不動産(総計)'!L5 -> 158.18 | M5: ='NY不動産(総計)'!M5 -> 154.43 | N5: ='NY不動産(総計)'!N5 -> 149.67 | O5: ='NY不動産(総計)'!O5 -> 149.52 | ... S5: ='NY不動産(総計)'!S5 -> 149.39 | U5: ='NY不動産(総計)'!U5 -> 146.92 | V5: ='NY不動産(総計)'!V5 -> 148.88 | W5: ='NY不動産(総計)'!W5 -> 154.1 | X5: ='NY不動産(総計)'!X5 -> 156.63 | Y5: ='NY不動産(総計)'!Y5 -> 156.56 | Z5: ='NY不動産(総計)'!Z5 -> 153.66 | AA5: ='NY不動産(総計)'!AA5 -> 155.81 | AB5: ='NY不動産(総計)'!AB5 -> 159.88 | ... AF5: ='NY不動産(総計)'!AF5 -> 0
A6: 賃料収入(ドル) | B6: 6500 | C6: 0 | D6: 0 | E6: 0 | F6: 0 | H6: 0 | I6: 0 | J6: 0 | K6: 0 | L6: 0 | M6: 0 | N6: 0 | O6: 0 | P6: 0 | Q6: 0 | R6: 0 | S6: 0 | U6: 6500 | V6: 6500 | W6: 6505.03 | X6: 6539.81 | Y6: 6537.2 | Z6: 6543.39 | AA6: 6500 | AB6: 6677.67
A7: 減価償却費(円) | U7: 1964723 | V7: 1964723 | W7: 1964723 | X7: 1964723 | Y7: 1964723 | Z7: 1964725 | AA7: 1964723 | AB7: 1964723 | AC7: 1964723 | AD7: 1964723 | AE7: 1964723 | AF7: 1964726
A8: 減価償却費(ドル)
A9: 残存簿価(円) | S9: 84118399 | U9: =S9-U7 -> 82153676 | V9: =U9-V7 -> 80188953 | W9: =V9-W7 -> 78224230 | X9: =W9-X7 -> 76259507 | Y9: =X9-Y7 -> 74294784 | Z9: =Y9-Z7 -> 72330059 | AA9: =Z9-AA7 -> 70365336 | AB9: =AA9-AB7 -> 68400613 | AC9: =AB9-AC7 -> 66435890 | ... AF9: =AE9-AF7 -> 60541718
A10: 残存簿価(ドル)
A11: 管理費(ドル) | U11: 455 | V11: 455 | W11: 455 | X11: 455 | Y11: 455 | Z11: 455 | AA11: 455 | AB11: 455
A12: 諸経費(税金、募集経費等)(ドル) | U12: 3864.43 | V12: 1402.27 | W12: 4394.58 | X12: 2084.21 | Y12: 1393.6 | Z12: 1434.61 | AA12: 740 | AB12: 1491.85
A13: ネット賃貸収入利回り(円)
A14: ネット賃貸収入利回り(ドル)
A15: 取得時簿価利回り(円) | B15: =B13/B2 -> #DIV/0!
A16: 取得時簿価利回り(ドル)
A17: 残存簿価利回り(円) | B17: =B13/B9 -> #DIV/0!
A18: 残存簿価利回り(ドル)
A19: CF(円) | C19: =SUM(C5*C20) -> 0 | D19: =SUM(D5*D20) -> 0 | E19: =SUM(E5*E20) -> 0 | F19: =SUM(F5*F20) -> 0 | H19: =SUM(H5*H20) -> 0 | I19: =SUM(I5*I20) -> 0 | J19: =SUM(J5*J20) -> 0 | K19: =SUM(K5*K20) -> 0 | L19: =SUM(L5*L20) -> 0 | M19: =SUM(M5*M20) -> 0 | N19: =SUM(N5*N20) -> 0 | O19: =SUM(O5*O20) -> 0 | ... S19: =SUM(S5*S20) -> 0 | U19: =SUM(U5*U20) -> 320369.34 | V19: =SUM(V5*V20) -> 691209.64 | W19: =SUM(W5*W20) -> 255104.84 | X19: =SUM(X5*X20) -> 626613.98 | Y19: =SUM(Y5*Y20) -> 734047.22 | Z19: =SUM(Z5*Z20) -> 715099.83 | AA19: =SUM(AA5*AA20) -> 826572.05 | AB19: =SUM(AB5*AB20) -> 756363.5 | ... AF19: =SUM(AF5*AF20) -> 0
A20: CF(ドル) | C20: =SUM(C6-C11-C12) -> 0 | D20: =SUM(D6-D11-D12) -> 0 | E20: =SUM(E6-E11-E12) -> 0 | F20: =SUM(F6-F11-F12) -> 0 | H20: =SUM(H6-H11-H12) -> 0 | I20: =SUM(I6-I11-I12) -> 0 | J20: =SUM(J6-J11-J12) -> 0 | K20: =SUM(K6-K11-K12) -> 0 | L20: =SUM(L6-L11-L12) -> 0 | M20: =SUM(M6-M11-M12) -> 0 | N20: =SUM(N6-N11-N12) -> 0 | O20: =SUM(O6-O11-O12) -> 0 | ... S20: =SUM(S6-S11-S12) -> 0 | U20: =SUM(U6-U11-U12) -> 2180.57 | V20: =SUM(V6-V11-V12) -> 4642.73 | W20: =SUM(W6-W11-W12) -> 1655.45 | X20: =SUM(X6-X11-X12) -> 4000.6 | Y20: =SUM(Y6-Y11-Y12) -> 4688.6 | Z20: =SUM(Z6-Z11-Z12) -> 4653.78 | AA20: =SUM(AA6-AA11-AA12) -> 5305 | AB20: =SUM(AB6-AB11-AB12) -> 4730.82 | ... AF20: =SUM(AF6-AF11-AF12) -> 0
A21: PL(円)
A22: PL(ドル)
A25: 下記表は固都税を各月の諸経費に分散して計上した表です
A26: 20 W 64th St #34C(One Lincoln Plaza) | B26: 2024 | C26: 45412 | D26: 45443 | E26: 45473 | F26: 45504 | G26: 2025 | H26: 45535 | I26: 45565 | J26: 45596 | K26: 45626 | L26: 45657 | M26: 45688 | N26: 45716 | O26: 45747 | P26: 45777 | Q26: 45808 | R26: 45838 | S26: 45869 | T26: 2026 | U26: 45900 | V26: 45930 | W26: 45961 | X26: 45991 | Y26: 46022 | Z26: 46053 | AA26: 46081 | AB26: 46112 | AC26: 46142 | AD26: 46173 | AE26: 46203 | AF26: 46234
A27: 取得簿価(円) | B27: =B28*160 -> 0
A28: 取得簿価(ドル) | B28: 0
A29: 賃料収入(円) | B29: =B31*B30 -> 0 | C29: =C30*C31 -> 0 | D29: =D30*D31 -> 0 | E29: =E30*E31 -> 0 | F29: =F30*F31 -> 0 | H29: =H30*H31 -> 0 | I29: =I30*I31 -> 0 | J29: =J30*J31 -> 0 | K29: =K30*K31 -> 0 | L29: =L30*L31 -> 0 | M29: =M30*M31 -> 0 | N29: =N30*N31 -> 0 | O29: =O30*O31 -> 0 | ... S29: =S30*S31 -> 0 | U29: =U30*U31 -> 954980 | V29: =V30*V31 -> 967720 | W29: =W30*W31 -> 1002425.1 | X29: =X30*X31 -> 1024330.4 | Y29: =Y30*Y31 -> 1023464 | Z29: =Z30*Z31 -> 1005457.3 | AA29: =AA30*AA31 -> 1012765 | AB29: =AB30*AB31 -> 1067625.9 | ... AF29: =AF30*AF31 -> 0
A30: 為替レート(ドル円)TTM | B30: ='NY不動産(総計)'!B30 -> 150 | C30: ='NY不動産(総計)'!C30 -> 156.9 | D30: ='NY不動産(総計)'!D30 -> 156.74 | E30: ='NY不動産(総計)'!E30 -> 161.07 | F30: ='NY不動産(総計)'!F30 -> 152.44 | H30: ='NY不動産(総計)'!H30 -> 144.8 | I30: ='NY不動産(総計)'!I30 -> 142.73 | J30: ='NY不動産(総計)'!J30 -> 153.64 | K30: ='NY不動産(総計)'!K30 -> 150.74 | L30: ='NY不動産(総計)'!L30 -> 158.18 | M30: ='NY不動産(総計)'!M30 -> 154.43 | N30: ='NY不動産(総計)'!N30 -> 149.67 | O30: ='NY不動産(総計)'!O30 -> 149.52 | ... S30: ='NY不動産(総計)'!S30 -> 149.39 | U30: ='NY不動産(総計)'!U30 -> 146.92 | V30: ='NY不動産(総計)'!V30 -> 148.88 | W30: ='NY不動産(総計)'!W30 -> 154.1 | X30: ='NY不動産(総計)'!X30 -> 156.63 | Y30: ='NY不動産(総計)'!Y30 -> 156.56 | Z30: ='NY不動産(総計)'!Z30 -> 153.66 | AA30: ='NY不動産(総計)'!AA30 -> 155.81 | AB30: ='NY不動産(総計)'!AB30 -> 159.88 | ... AF30: ='NY不動産(総計)'!AF30 -> 0
A31: 賃料収入(ドル) | U31: 6500 | V31: 6500 | W31: 6505.03 | X31: 6539.81 | Y31: 6537.2 | Z31: 6543.39 | AA31: 6500 | AB31: 6677.67
A32: 減価償却費(円) | U32: 1964723 | V32: 1964723 | W32: 1964723 | X32: 1964723 | Y32: 1964723 | Z32: 1964725 | AA32: 1964723 | AB32: 1964723 | AC32: 1964723 | AD32: 1964723 | AE32: 1964723 | AF32: 1964726
A33: 減価償却費(ドル)
A34: 残存簿価(円) | I34: =B34-I32 -> 0 | J34: =I34-J32 -> 0 | K34: =J34-K32 -> 0 | L34: =K34-L32 -> 0 | M34: =L34-M32 -> 0 | N34: =M34-N32 -> 0 | O34: =N34-O32 -> 0 | P34: =O34-P32 -> 0 | Q34: =P34-Q32 -> 0 | R34: =Q34-R32 -> 0 | S34: 84118399 | U34: =S34-U32 -> 82153676 | V34: =U34-V32 -> 80188953 | W34: =V34-W32 -> 78224230 | X34: =W34-X32 -> 76259507 | Y34: =X34-Y32 -> 74294784 | Z34: =Y34-Z32 -> 72330059 | AA34: =Z34-AA32 -> 70365336 | AB34: =AA34-AB32 -> 68400613 | AC34: =AB34-AC32 -> 66435890 | ... AF34: =AE34-AF32 -> 60541718
A35: 残存簿価(ドル)
A36: 管理費(ドル) | U36: 455 | V36: 455 | W36: 455 | X36: 455 | Y36: 455 | Z36: 455 | AA36: 455 | AB36: 455
A37: 諸経費(税金、募集経費等)(ドル) | U37: 3864.43 | V37: 1402.27 | W37: 4394.58 | X37: 2084.21 | Y37: 1393.6 | Z37: 1434.61 | AA37: 740 | AB37: 740
A38: ネット賃貸収入利回り(円)
A39: ネット賃貸収入利回り(ドル)
A40: 取得時簿価利回り(円) | B40: =B38/B27 -> #DIV/0!
A41: 取得時簿価利回り(ドル)
A42: 残存簿価利回り(円) | B42: =B38/B34 -> #DIV/0!
A43: 残存簿価利回り(ドル)
A44: CF(円) | C44: =SUM(C30*C45) -> 0 | D44: =SUM(D30*D45) -> 0 | E44: =SUM(E30*E45) -> 0 | F44: =SUM(F30*F45) -> 0 | H44: =SUM(H30*H45) -> 0 | I44: =SUM(I30*I45) -> 0 | J44: =SUM(J30*J45) -> 0 | K44: =SUM(K30*K45) -> 0 | L44: =SUM(L30*L45) -> 0 | M44: =SUM(M30*M45) -> 0 | N44: =SUM(N30*N45) -> 0 | O44: =SUM(O30*O45) -> 0 | ... S44: =SUM(S30*S45) -> 0 | U44: =SUM(U30*U45) -> 320369.34 | V44: =SUM(V30*V45) -> 691209.64 | W44: =SUM(W30*W45) -> 255104.84 | X44: =SUM(X30*X45) -> 626613.98 | Y44: =SUM(Y30*Y45) -> 734047.22 | Z44: =SUM(Z30*Z45) -> 715099.83 | AA44: =SUM(AA30*AA45) -> 826572.05 | AB44: =SUM(AB30*AB45) -> 876569.28 | ... AF44: =SUM(AF30*AF45) -> 0
A45: CF(ドル) | C45: =SUM(C31-C36-C37) -> 0 | D45: =SUM(D31-D36-D37) -> 0 | E45: =SUM(E31-E36-E37) -> 0 | F45: =SUM(F31-F36-F37) -> 0 | H45: =SUM(H31-H36-H37) -> 0 | I45: =SUM(I31-I36-I37) -> 0 | J45: =SUM(J31-J36-J37) -> 0 | K45: =SUM(K31-K36-K37) -> 0 | L45: =SUM(L31-L36-L37) -> 0 | M45: =SUM(M31-M36-M37) -> 0 | N45: =SUM(N31-N36-N37) -> 0 | O45: =SUM(O31-O36-O37) -> 0 | ... S45: =SUM(S31-S36-S37) -> 0 | U45: =SUM(U31-U36-U37) -> 2180.57 | V45: =SUM(V31-V36-V37) -> 4642.73 | W45: =SUM(W31-W36-W37) -> 1655.45 | X45: =SUM(X31-X36-X37) -> 4000.6 | Y45: =SUM(Y31-Y36-Y37) -> 4688.6 | Z45: =SUM(Z31-Z36-Z37) -> 4653.78 | AA45: =SUM(AA31-AA36-AA37) -> 5305 | AB45: =SUM(AB31-AB36-AB37) -> 5482.67 | ... AF45: =SUM(AF31-AF36-AF37) -> 0
A46: PL(円)
A47: PL(ドル)

Sheet Nine52#400(GRE)
A1: 416 W 52nd St #400(Nine 52) | B1: 2024 | C1: 45412 | D1: 45443 | E1: 45473 | F1: 45504 | G1: 2025 | H1: 45535 | I1: 45565 | J1: 45596 | K1: 45626 | L1: 45657 | M1: 45688 | N1: 45716 | O1: 45747 | P1: 45777 | Q1: 45808 | R1: 45838 | S1: 45869 | T1: 2026 | U1: 45900 | V1: 45930 | W1: 45961 | X1: 45991 | Y1: 46022 | Z1: 46053 | AA1: 46081 | AB1: 46112 | AC1: 46142 | AD1: 46173 | AE1: 46203 | AF1: 46234
A2: 取得簿価(円) | B2: =B3*160 -> 0
A3: 取得簿価(ドル) | B3: 0
A4: 賃料収入(円) | B4: =B6*B5 -> 705000 | C4: =C5*C6 -> 0 | D4: =D5*D6 -> 0 | E4: =E5*E6 -> 0 | F4: =F5*F6 -> 0 | H4: =H5*H6 -> 0 | I4: =I5*I6 -> 0 | J4: =J5*J6 -> 0 | K4: =K5*K6 -> 0 | L4: =L5*L6 -> 0 | M4: =M5*M6 -> 0 | N4: =N5*N6 -> 0 | O4: =O5*O6 -> 0 | ... S4: =S5*S6 -> 0 | U4: =U5*U6 -> 675832 | V4: =V5*V6 -> 684848 | W4: =W5*W6 -> 708860 | X4: =X5*X6 -> 720498 | Y4: =Y5*Y6 -> 735832 | Z4: =Z5*Z6 -> 25095.751 | AA4: =AA5*AA6 -> 2337.15 | AB4: =AB5*AB6 -> 628656.15 | ... AF4: =AF5*AF6 -> 0
A5: 為替レート(ドル円)TTM | B5: ='NY不動産(総計)'!B5 -> 150 | C5: ='NY不動産(総計)'!C5 -> 156.9 | D5: ='NY不動産(総計)'!D5 -> 156.74 | E5: ='NY不動産(総計)'!E5 -> 161.07 | F5: ='NY不動産(総計)'!F5 -> 152.44 | H5: ='NY不動産(総計)'!H5 -> 144.8 | I5: ='NY不動産(総計)'!I5 -> 142.73 | J5: ='NY不動産(総計)'!J5 -> 153.64 | K5: ='NY不動産(総計)'!K5 -> 150.74 | L5: ='NY不動産(総計)'!L5 -> 158.18 | M5: ='NY不動産(総計)'!M5 -> 154.43 | N5: ='NY不動産(総計)'!N5 -> 149.67 | O5: ='NY不動産(総計)'!O5 -> 149.52 | ... S5: ='NY不動産(総計)'!S5 -> 149.39 | U5: ='NY不動産(総計)'!U5 -> 146.92 | V5: ='NY不動産(総計)'!V5 -> 148.88 | W5: ='NY不動産(総計)'!W5 -> 154.1 | X5: ='NY不動産(総計)'!X5 -> 156.63 | Y5: ='NY不動産(総計)'!Y5 -> 156.56 | Z5: ='NY不動産(総計)'!Z5 -> 153.66 | AA5: ='NY不動産(総計)'!AA5 -> 155.81 | AB5: ='NY不動産(総計)'!AB5 -> 159.88 | ... AF5: ='NY不動産(総計)'!AF5 -> 0
A6: 賃料収入(ドル) | B6: 4700 | C6: 0 | D6: 0 | E6: 0 | F6: 0 | H6: 0 | I6: 0 | J6: 0 | K6: 0 | L6: 0 | M6: 0 | N6: 0 | O6: 0 | P6: 0 | Q6: 0 | R6: 0 | S6: 0 | U6: 4600 | V6: 4600 | W6: 4600 | X6: 4600 | Y6: 4700 | Z6: 163.32 | AA6: 15 | AB6: 3932.05
A7: 減価償却費(円) | U7: 1927576 | V7: 1927576 | W7: 1927576 | X7: 1927576 | Y7: 1927576 | Z7: 1927578 | AA7: 1927576 | AB7: 1927576 | AC7: 1927576 | AD7: 1927576 | AE7: 1927576 | AF7: 1927579
A8: 減価償却費(ドル)
A9: 残存簿価(円) | S9: 111522419 | U9: =S9-U7 -> 109594843 | V9: =U9-V7 -> 107667267 | W9: =V9-W7 -> 105739691 | X9: =W9-X7 -> 103812115 | Y9: =X9-Y7 -> 101884539 | Z9: =Y9-Z7 -> 99956961 | AA9: =Z9-AA7 -> 98029385 | AB9: =AA9-AB7 -> 96101809 | AC9: =AB9-AC7 -> 94174233 | ... AF9: =AE9-AF7 -> 88391502
A10: 残存簿価(ドル)
A11: 管理費(ドル) | U11: 368 | V11: 322 | W11: 322 | X11: 322 | Y11: 329 | Z11: 164.5 | AA11: 164.5 | AB11: 364
A12: 諸経費(税金、募集経費等)(ドル) | U12: 897.96 | V12: 866.35 | W12: 866.35 | X12: 866.35 | Y12: 866.35 | Z12: 866.35 | AA12: 7551.85 | AB12: 6586.76
A13: ネット賃貸収入利回り(円)
A14: ネット賃貸収入利回り(ドル)
A15: 取得時簿価利回り(円) | B15: =B13/B2 -> #DIV/0!
A16: 取得時簿価利回り(ドル)
A17: 残存簿価利回り(円) | B17: =B13/B9 -> #DIV/0!
A18: 残存簿価利回り(ドル)
A19: CF(円) | C19: =SUM(C5*C20) -> 0 | D19: =SUM(D5*D20) -> 0 | E19: =SUM(E5*E20) -> 0 | F19: =SUM(F5*F20) -> 0 | H19: =SUM(H5*H20) -> 0 | I19: =SUM(I5*I20) -> 0 | J19: =SUM(J5*J20) -> 0 | K19: =SUM(K5*K20) -> 0 | L19: =SUM(L5*L20) -> 0 | M19: =SUM(M5*M20) -> 0 | N19: =SUM(N5*N20) -> 0 | O19: =SUM(O5*O20) -> 0 | ... S19: =SUM(S5*S20) -> 0 | U19: =SUM(U5*U20) -> 489837.16 | V19: =SUM(V5*V20) -> 507926.45 | W19: =SUM(W5*W20) -> 525735.27 | X19: =SUM(X5*X20) -> 534366.74 | Y19: =SUM(Y5*Y20) -> 548688 | Z19: =SUM(Z5*Z20) -> -133304.66 | AA19: =SUM(AA5*AA20) -> -1199947.3 | AB19: =SUM(AB5*AB20) -> -482631.35 | ... AF19: =SUM(AF5*AF20) -> 0
A20: CF(ドル) | C20: =SUM(C6-C11-C12) -> 0 | D20: =SUM(D6-D11-D12) -> 0 | E20: =SUM(E6-E11-E12) -> 0 | F20: =SUM(F6-F11-F12) -> 0 | H20: =SUM(H6-H11-H12) -> 0 | I20: =SUM(I6-I11-I12) -> 0 | J20: =SUM(J6-J11-J12) -> 0 | K20: =SUM(K6-K11-K12) -> 0 | L20: =SUM(L6-L11-L12) -> 0 | M20: =SUM(M6-M11-M12) -> 0 | N20: =SUM(N6-N11-N12) -> 0 | O20: =SUM(O6-O11-O12) -> 0 | ... S20: =SUM(S6-S11-S12) -> 0 | U20: =SUM(U6-U11-U12) -> 3334.04 | V20: =SUM(V6-V11-V12) -> 3411.65 | W20: =SUM(W6-W11-W12) -> 3411.65 | X20: =SUM(X6-X11-X12) -> 3411.65 | Y20: =SUM(Y6-Y11-Y12) -> 3504.65 | Z20: =SUM(Z6-Z11-Z12) -> -867.53 | AA20: =SUM(AA6-AA11-AA12) -> -7701.35 | AB20: =SUM(AB6-AB11-AB12) -> -3018.71 | ... AF20: =SUM(AF6-AF11-AF12) -> 0
A21: PL(円)
A22: PL(ドル)
A24: 購入日
A25: 下記表は固都税を各月の諸経費に分散して計上した表です
A26: 20 W 64th St #34C(One Lincoln Plaza) | B26: 2024 | C26: 45412 | D26: 45443 | E26: 45473 | F26: 45504 | G26: 2025 | H26: 45535 | I26: 45565 | J26: 45596 | K26: 496 | L26: 45657 | M26: 45688 | N26: 45716 | O26: 45747 | P26: 45777 | Q26: 45808 | R26: 45838 | S26: 45869 | T26: 2026 | U26: 45900 | V26: 45930 | W26: 45961 | X26: 45991 | Y26: 46022 | Z26: 46053 | AA26: 46081 | AB26: 46112 | AC26: 46142 | AD26: 46173 | AE26: 46203 | AF26: 46234
A27: 取得簿価(円) | B27: =B28*160 -> 0
A28: 取得簿価(ドル) | B28: 0
A29: 賃料収入(円) | B29: =B31*B30 -> 0 | C29: =C30*C31 -> 0 | D29: =D30*D31 -> 0 | E29: =E30*E31 -> 0 | F29: =F30*F31 -> 0 | H29: =H30*H31 -> 0 | I29: =I30*I31 -> 0 | J29: =J30*J31 -> 0 | K29: =K30*K31 -> 0 | L29: =L30*L31 -> 0 | M29: =M30*M31 -> 0 | N29: =N30*N31 -> 0 | O29: =O30*O31 -> 0 | ... S29: =S30*S31 -> 0 | U29: =U30*U31 -> 675832 | V29: =V30*V31 -> 684848 | W29: =W30*W31 -> 708860 | X29: =X30*X31 -> 720498 | Y29: =Y30*Y31 -> 735832 | Z29: =Z30*Z31 -> 25095.751 | AA29: =AA30*AA31 -> 2337.15 | AB29: =AB30*AB31 -> 0 | ... AF29: =AF30*AF31 -> 0
A30: 為替レート(ドル円)TTM | B30: ='NY不動産(総計)'!B30 -> 150 | C30: ='NY不動産(総計)'!C30 -> 156.9 | D30: ='NY不動産(総計)'!D30 -> 156.74 | E30: ='NY不動産(総計)'!E30 -> 161.07 | F30: ='NY不動産(総計)'!F30 -> 152.44 | H30: ='NY不動産(総計)'!H30 -> 144.8 | I30: ='NY不動産(総計)'!I30 -> 142.73 | J30: ='NY不動産(総計)'!J30 -> 153.64 | K30: ='NY不動産(総計)'!K30 -> 150.74 | L30: ='NY不動産(総計)'!L30 -> 158.18 | M30: ='NY不動産(総計)'!M30 -> 154.43 | N30: ='NY不動産(総計)'!N30 -> 149.67 | O30: ='NY不動産(総計)'!O30 -> 149.52 | ... S30: ='NY不動産(総計)'!S30 -> 149.39 | U30: ='NY不動産(総計)'!U30 -> 146.92 | V30: ='NY不動産(総計)'!V30 -> 148.88 | W30: ='NY不動産(総計)'!W30 -> 154.1 | X30: ='NY不動産(総計)'!X30 -> 156.63 | Y30: ='NY不動産(総計)'!Y30 -> 156.56 | Z30: ='NY不動産(総計)'!Z30 -> 153.66 | AA30: ='NY不動産(総計)'!AA30 -> 155.81 | AB30: ='NY不動産(総計)'!AB30 -> 159.88 | ... AF30: ='NY不動産(総計)'!AF30 -> 0
A31: 賃料収入(ドル) | U31: 4600 | V31: 4600 | W31: 4600 | X31: 4600 | Y31: 4700 | Z31: 163.32 | AA31: 15
A32: 減価償却費(円) | U32: 1927576 | V32: 1927576 | W32: 1927576 | X32: 1927576 | Y32: 1927576 | Z32: 1927578 | AA32: 1927576 | AB32: 1927576 | AC32: 1927576 | AD32: 1927576 | AE32: 1927576 | AF32: 1927579
A33: 減価償却費(ドル)
A34: 残存簿価(円) | I34: =B34-I32 -> 0 | J34: =I34-J32 -> 0 | K34: =J34-K32 -> 0 | L34: =K34-L32 -> 0 | M34: =L34-M32 -> 0 | N34: =M34-N32 -> 0 | O34: =N34-O32 -> 0 | P34: =O34-P32 -> 0 | Q34: =P34-Q32 -> 0 | R34: =Q34-R32 -> 0 | S34: 111522419 | U34: =S34-U32 -> 109594843 | V34: =U34-V32 -> 107667267 | W34: =V34-W32 -> 105739691 | X34: =W34-X32 -> 103812115 | Y34: =X34-Y32 -> 101884539 | Z34: =Y34-Z32 -> 99956961 | AA34: =Z34-AA32 -> 98029385 | AB34: =AA34-AB32 -> 96101809 | AC34: =AB34-AC32 -> 94174233 | ... AF34: =AE34-AF32 -> 88391502
A35: 残存簿価(ドル)
A36: 管理費(ドル) | U36: 368 | V36: 322 | W36: 322 | X36: 322 | Y36: 329 | Z36: 164.5 | AA36: 164.5
A37: 諸経費(税金、募集経費等)(ドル) | U37: 897.96 | V37: 866.35 | W37: 866.35 | X37: 866.35 | Y37: 866.35 | Z37: 866.35 | AA37: 7551.85
A38: ネット賃貸収入利回り(円)
A39: ネット賃貸収入利回り(ドル)
A40: 取得時簿価利回り(円) | B40: =B38/B27 -> #DIV/0!
A41: 取得時簿価利回り(ドル)
A42: 残存簿価利回り(円) | B42: =B38/B34 -> #DIV/0!
A43: 残存簿価利回り(ドル)
A44: CF(円) | C44: =SUM(C30*C45) -> 0 | D44: =SUM(D30*D45) -> 0 | E44: =SUM(E30*E45) -> 0 | F44: =SUM(F30*F45) -> 0 | H44: =SUM(H30*H45) -> 0 | I44: =SUM(I30*I45) -> 0 | J44: =SUM(J30*J45) -> 0 | K44: =SUM(K30*K45) -> 0 | L44: =SUM(L30*L45) -> 0 | M44: =SUM(M30*M45) -> 0 | N44: =SUM(N30*N45) -> 0 | O44: =SUM(O30*O45) -> 0 | ... S44: =SUM(S30*S45) -> 0 | U44: =SUM(U30*U45) -> 489837.16 | V44: =SUM(V30*V45) -> 507926.45 | W44: =SUM(W30*W45) -> 525735.27 | X44: =SUM(X30*X45) -> 534366.74 | Y44: =SUM(Y30*Y45) -> 548688 | Z44: =SUM(Z30*Z45) -> -133304.66 | AA44: =SUM(AA30*AA45) -> -1199947.3 | AB44: =SUM(AB30*AB45) -> 0 | ... AF44: =SUM(AF30*AF45) -> 0
A45: CF(ドル) | C45: =SUM(C31-C36-C37) -> 0 | D45: =SUM(D31-D36-D37) -> 0 | E45: =SUM(E31-E36-E37) -> 0 | F45: =SUM(F31-F36-F37) -> 0 | H45: =SUM(H31-H36-H37) -> 0 | I45: =SUM(I31-I36-I37) -> 0 | J45: =SUM(J31-J36-J37) -> 0 | K45: =SUM(K31-K36-K37) -> 0 | L45: =SUM(L31-L36-L37) -> 0 | M45: =SUM(M31-M36-M37) -> 0 | N45: =SUM(N31-N36-N37) -> 0 | O45: =SUM(O31-O36-O37) -> 0 | ... S45: =SUM(S31-S36-S37) -> 0 | U45: =SUM(U31-U36-U37) -> 3334.04 | V45: =SUM(V31-V36-V37) -> 3411.65 | W45: =SUM(W31-W36-W37) -> 3411.65 | X45: =SUM(X31-X36-X37) -> 3411.65 | Y45: =SUM(Y31-Y36-Y37) -> 3504.65 | Z45: =SUM(Z31-Z36-Z37) -> -867.53 | AA45: =SUM(AA31-AA36-AA37) -> -7701.35 | AB45: =SUM(AB31-AB36-AB37) -> 0 | ... AF45: =SUM(AF31-AF36-AF37) -> 0
A46: PL(円)
A47: PL(ドル)

Sheet 20W64th#30C(GRE)
A1: 20 W 64th St #30C(One Lincoln Plaza) | B1: 2024 | C1: 45412 | D1: 45443 | E1: 45473 | F1: 45504 | G1: 2025 | H1: 45535 | I1: 45565 | J1: 45596 | K1: 45626 | L1: 45657 | M1: 45688 | N1: 45716 | O1: 45747 | P1: 45777 | Q1: 45808 | R1: 45838 | S1: 45869 | T1: 2026 | U1: 45900 | V1: 45930 | W1: 45961 | X1: 45991 | Y1: 46022 | Z1: 46053 | AA1: 46081 | AB1: 46112 | AC1: 46142 | AD1: 46173 | AE1: 46203 | AF1: 46234
A2: 取得簿価(円) | B2: =B3*160 -> 0
A3: 取得簿価(ドル) | B3: 0
A4: 賃料収入(円) | B4: =B6*B5 -> 675000 | C4: =C5*C6 -> 0 | D4: =D5*D6 -> 0 | E4: =E5*E6 -> 0 | F4: =F5*F6 -> 0 | H4: =H5*H6 -> 0 | I4: =I5*I6 -> 0 | J4: =J5*J6 -> 0 | K4: =K5*K6 -> 0 | L4: =L5*L6 -> 0 | M4: =M5*M6 -> 0 | N4: =N5*N6 -> 0 | O4: =O5*O6 -> 0 | ... S4: =S5*S6 -> 0 | U4: =U5*U6 -> 661140 | V4: =V5*V6 -> 669960 | W4: =W5*W6 -> 702696 | X4: =X5*X6 -> 704835 | Y4: =Y5*Y6 -> 704520 | Z4: =Z5*Z6 -> 691470 | AA4: =AA5*AA6 -> 701145 | AB4: =AB5*AB6 -> 719460 | ... AF4: =AF5*AF6 -> 0
A5: 為替レート(ドル円)TTM | B5: ='NY不動産(総計)'!B5 -> 150 | C5: ='NY不動産(総計)'!C5 -> 156.9 | D5: ='NY不動産(総計)'!D5 -> 156.74 | E5: ='NY不動産(総計)'!E5 -> 161.07 | F5: ='NY不動産(総計)'!F5 -> 152.44 | H5: ='NY不動産(総計)'!H5 -> 144.8 | I5: ='NY不動産(総計)'!I5 -> 142.73 | J5: ='NY不動産(総計)'!J5 -> 153.64 | K5: ='NY不動産(総計)'!K5 -> 150.74 | L5: ='NY不動産(総計)'!L5 -> 158.18 | M5: ='NY不動産(総計)'!M5 -> 154.43 | N5: ='NY不動産(総計)'!N5 -> 149.67 | O5: ='NY不動産(総計)'!O5 -> 149.52 | ... S5: ='NY不動産(総計)'!S5 -> 149.39 | U5: ='NY不動産(総計)'!U5 -> 146.92 | V5: ='NY不動産(総計)'!V5 -> 148.88 | W5: ='NY不動産(総計)'!W5 -> 154.1 | X5: ='NY不動産(総計)'!X5 -> 156.63 | Y5: ='NY不動産(総計)'!Y5 -> 156.56 | Z5: ='NY不動産(総計)'!Z5 -> 153.66 | AA5: ='NY不動産(総計)'!AA5 -> 155.81 | AB5: ='NY不動産(総計)'!AB5 -> 159.88 | ... AF5: ='NY不動産(総計)'!AF5 -> 0
A6: 賃料収入(ドル) | B6: 4500 | C6: 0 | D6: 0 | E6: 0 | F6: 0 | H6: 0 | I6: 0 | J6: 0 | K6: 0 | L6: 0 | M6: 0 | N6: 0 | O6: 0 | P6: 0 | Q6: 0 | R6: 0 | U6: 4500 | V6: 4500 | W6: 4560 | X6: 4500 | Y6: 4500 | Z6: 4500 | AA6: 4500 | AB6: 4500
A7: 減価償却費(円) | U7: 1084904 | V7: 1084904 | W7: 1084904 | X7: 1084904 | Y7: 1084904 | Z7: 1084906 | AA7: 1084904 | AB7: 1084904 | AC7: 1084904 | AD7: 1084904 | AE7: 1084904 | AF7: 1084907
A8: 減価償却費(ドル)
A9: 残存簿価(円) | S9: 89093903 | U9: =S9-U7 -> 88008999 | V9: =U9-V7 -> 86924095 | W9: =V9-W7 -> 85839191 | X9: =W9-X7 -> 84754287 | Y9: =X9-Y7 -> 83669383 | Z9: =Y9-Z7 -> 82584477 | AA9: =Z9-AA7 -> 81499573 | AB9: =AA9-AB7 -> 80414669 | AC9: =AB9-AC7 -> 79329765 | ... AF9: =AE9-AF7 -> 76075050
A10: 残存簿価(ドル)
A11: 管理費(ドル) | U11: 360 | V11: 315 | W11: 315 | X11: 315 | Y11: 315 | Z11: 315 | AA11: 315 | AB11: 315
A12: 諸経費(税金、募集経費等)(ドル) | U12: 2287.9 | V12: 3399.29 | W12: 905.24 | X12: 905.24 | Y12: 905.24 | Z12: 932.39 | AA12: 932.39 | AB12: 932.39
A13: ネット賃貸収入利回り(円)
A14: ネット賃貸収入利回り(ドル)
A15: 取得時簿価利回り(円) | B15: =B13/B2 -> #DIV/0!
A16: 取得時簿価利回り(ドル)
A17: 残存簿価利回り(円) | B17: =B13/B9 -> #DIV/0!
A18: 残存簿価利回り(ドル)
A19: CF(円) | C19: =SUM(C5*C20) -> 0 | D19: =SUM(D5*D20) -> 0 | E19: =SUM(E5*E20) -> 0 | F19: =SUM(F5*F20) -> 0 | H19: =SUM(H5*H20) -> 0 | I19: =SUM(I5*I20) -> 0 | J19: =SUM(J5*J20) -> 0 | K19: =SUM(K5*K20) -> 0 | L19: =SUM(L5*L20) -> 0 | M19: =SUM(M5*M20) -> 0 | N19: =SUM(N5*N20) -> 0 | O19: =SUM(O5*O20) -> 0 | ... S19: =SUM(S5*S20) -> 0 | U19: =SUM(U5*U20) -> 272110.53 | V19: =SUM(V5*V20) -> 116976.5 | W19: =SUM(W5*W20) -> 514657.02 | X19: =SUM(X5*X20) -> 513708.81 | Y19: =SUM(Y5*Y20) -> 513479.23 | Z19: =SUM(Z5*Z20) -> 499796.05 | AA19: =SUM(AA5*AA20) -> 506789.16 | AB19: =SUM(AB5*AB20) -> 520027.29 | ... AF19: =SUM(AF5*AF20) -> 0
A20: CF(ドル) | C20: =SUM(C6-C11-C12) -> 0 | D20: =SUM(D6-D11-D12) -> 0 | E20: =SUM(E6-E11-E12) -> 0 | F20: =SUM(F6-F11-F12) -> 0 | H20: =SUM(H6-H11-H12) -> 0 | I20: =SUM(I6-I11-I12) -> 0 | J20: =SUM(J6-J11-J12) -> 0 | K20: =SUM(K6-K11-K12) -> 0 | L20: =SUM(L6-L11-L12) -> 0 | M20: =SUM(M6-M11-M12) -> 0 | N20: =SUM(N6-N11-N12) -> 0 | O20: =SUM(O6-O11-O12) -> 0 | ... S20: =SUM(S6-S11-S12) -> 0 | U20: =SUM(U6-U11-U12) -> 1852.1 | V20: =SUM(V6-V11-V12) -> 785.71 | W20: =SUM(W6-W11-W12) -> 3339.76 | X20: =SUM(X6-X11-X12) -> 3279.76 | Y20: =SUM(Y6-Y11-Y12) -> 3279.76 | Z20: =SUM(Z6-Z11-Z12) -> 3252.61 | AA20: =SUM(AA6-AA11-AA12) -> 3252.61 | AB20: =SUM(AB6-AB11-AB12) -> 3252.61 | ... AF20: =SUM(AF6-AF11-AF12) -> 0
A21: PL(円)
A22: PL(ドル)
A25: 下記表は固都税を各月の諸経費に分散して計上した表です
A26: 20 W 64th St #34C(One Lincoln Plaza) | B26: 2024 | C26: 45412 | D26: 45443 | E26: 45473 | F26: 45504 | G26: 2025 | H26: 45535 | I26: 45565 | J26: 45596 | K26: 45626 | L26: 45657 | M26: 45688 | N26: 45716 | O26: 45747 | P26: 45777 | Q26: 45808 | R26: 45838 | S26: 45869 | T26: 2026 | U26: 45900 | V26: 45930 | W26: 45961 | X26: 45991 | Y26: 46022 | Z26: 46053 | AA26: 46081 | AB26: 46112 | AC26: 46142 | AD26: 46173 | AE26: 46203 | AF26: 46234
A27: 取得簿価(円) | B27: =B28*160 -> 0
A28: 取得簿価(ドル) | B28: 0
A29: 賃料収入(円) | B29: =B31*B30 -> 0 | C29: =C30*C31 -> 0 | D29: =D30*D31 -> 0 | E29: =E30*E31 -> 0 | F29: =F30*F31 -> 0 | H29: =H30*H31 -> 0 | I29: =I30*I31 -> 0 | J29: =J30*J31 -> 0 | K29: =K30*K31 -> 0 | L29: =L30*L31 -> 0 | M29: =M30*M31 -> 0 | N29: =N30*N31 -> 0 | O29: =O30*O31 -> 0 | ... S29: =S30*S31 -> 0 | U29: =U30*U31 -> 661140 | V29: =V30*V31 -> 669960 | W29: =W30*W31 -> 702696 | X29: =X30*X31 -> 704835 | Y29: =Y30*Y31 -> 704520 | Z29: =Z30*Z31 -> 691470 | AA29: =AA30*AA31 -> 701145 | AB29: =AB30*AB31 -> 719460 | ... AF29: =AF30*AF31 -> 0
A30: 為替レート(ドル円)TTM | B30: ='NY不動産(総計)'!B30 -> 150 | C30: ='NY不動産(総計)'!C30 -> 156.9 | D30: ='NY不動産(総計)'!D30 -> 156.74 | E30: ='NY不動産(総計)'!E30 -> 161.07 | F30: ='NY不動産(総計)'!F30 -> 152.44 | H30: ='NY不動産(総計)'!H30 -> 144.8 | I30: ='NY不動産(総計)'!I30 -> 142.73 | J30: ='NY不動産(総計)'!J30 -> 153.64 | K30: ='NY不動産(総計)'!K30 -> 150.74 | L30: ='NY不動産(総計)'!L30 -> 158.18 | M30: ='NY不動産(総計)'!M30 -> 154.43 | N30: ='NY不動産(総計)'!N30 -> 149.67 | O30: ='NY不動産(総計)'!O30 -> 149.52 | ... S30: ='NY不動産(総計)'!S30 -> 149.39 | U30: ='NY不動産(総計)'!U30 -> 146.92 | V30: ='NY不動産(総計)'!V30 -> 148.88 | W30: ='NY不動産(総計)'!W30 -> 154.1 | X30: ='NY不動産(総計)'!X30 -> 156.63 | Y30: ='NY不動産(総計)'!Y30 -> 156.56 | Z30: ='NY不動産(総計)'!Z30 -> 153.66 | AA30: ='NY不動産(総計)'!AA30 -> 155.81 | AB30: ='NY不動産(総計)'!AB30 -> 159.88 | ... AF30: ='NY不動産(総計)'!AF30 -> 0
A31: 賃料収入(ドル) | U31: 4500 | V31: 4500 | W31: 4560 | X31: 4500 | Y31: 4500 | Z31: 4500 | AA31: 4500 | AB31: 4500
A32: 減価償却費(円) | U32: 1084904 | V32: 1084904 | W32: 1084904 | X32: 1084904 | Y32: 1084904 | Z32: 1084906 | AA32: 1084904 | AB32: 1084904 | AC32: 1084904 | AD32: 1084904 | AE32: 1084904 | AF32: 1084907
A33: 減価償却費(ドル)
A34: 残存簿価(円) | I34: =B34-I32 -> 0 | J34: =I34-J32 -> 0 | K34: =J34-K32 -> 0 | L34: =K34-L32 -> 0 | M34: =L34-M32 -> 0 | N34: =M34-N32 -> 0 | O34: =N34-O32 -> 0 | P34: =O34-P32 -> 0 | Q34: =P34-Q32 -> 0 | R34: =Q34-R32 -> 0 | S34: 89093903 | U34: =S34-U32 -> 88008999 | V34: =U34-V32 -> 86924095 | W34: =V34-W32 -> 85839191 | X34: =W34-X32 -> 84754287 | Y34: =X34-Y32 -> 83669383 | Z34: =Y34-Z32 -> 82584477 | AA34: =Z34-AA32 -> 81499573 | AB34: =AA34-AB32 -> 80414669 | AC34: =AB34-AC32 -> 79329765 | ... AF34: =AE34-AF32 -> 76075050
A35: 残存簿価(ドル)
A36: 管理費(ドル) | U36: 360 | V36: 315 | W36: 315 | X36: 315 | Y36: 315 | Z36: 315 | AA36: 315 | AB36: 315
A37: 諸経費(税金、募集経費等)(ドル) | U37: 2287.9 | V37: 3399.29 | W37: 905.24 | X37: 905.24 | Y37: 905.24 | Z37: 932.39 | AA37: 932.39 | AB37: 932.39
A38: ネット賃貸収入利回り(円)
A39: ネット賃貸収入利回り(ドル)
A40: 取得時簿価利回り(円) | B40: =B38/B27 -> #DIV/0!
A41: 取得時簿価利回り(ドル)
A42: 残存簿価利回り(円) | B42: =B38/B34 -> #DIV/0!
A43: 残存簿価利回り(ドル)
A44: CF(円) | C44: =SUM(C30*C45) -> 0 | D44: =SUM(D30*D45) -> 0 | E44: =SUM(E30*E45) -> 0 | F44: =SUM(F30*F45) -> 0 | H44: =SUM(H30*H45) -> 0 | I44: =SUM(I30*I45) -> 0 | J44: =SUM(J30*J45) -> 0 | K44: =SUM(K30*K45) -> 0 | L44: =SUM(L30*L45) -> 0 | M44: =SUM(M30*M45) -> 0 | N44: =SUM(N30*N45) -> 0 | O44: =SUM(O30*O45) -> 0 | ... S44: =SUM(S30*S45) -> 0 | U44: =SUM(U30*U45) -> 272110.53 | V44: =SUM(V30*V45) -> 116976.5 | W44: =SUM(W30*W45) -> 514657.02 | X44: =SUM(X30*X45) -> 513708.81 | Y44: =SUM(Y30*Y45) -> 513479.23 | Z44: =SUM(Z30*Z45) -> 499796.05 | AA44: =SUM(AA30*AA45) -> 506789.16 | AB44: =SUM(AB30*AB45) -> 520027.29 | ... AF44: =SUM(AF30*AF45) -> 0
A45: CF(ドル) | C45: =SUM(C31-C36-C37) -> 0 | D45: =SUM(D31-D36-D37) -> 0 | E45: =SUM(E31-E36-E37) -> 0 | F45: =SUM(F31-F36-F37) -> 0 | H45: =SUM(H31-H36-H37) -> 0 | I45: =SUM(I31-I36-I37) -> 0 | J45: =SUM(J31-J36-J37) -> 0 | K45: =SUM(K31-K36-K37) -> 0 | L45: =SUM(L31-L36-L37) -> 0 | M45: =SUM(M31-M36-M37) -> 0 | N45: =SUM(N31-N36-N37) -> 0 | O45: =SUM(O31-O36-O37) -> 0 | ... S45: =SUM(S31-S36-S37) -> 0 | U45: =SUM(U31-U36-U37) -> 1852.1 | V45: =SUM(V31-V36-V37) -> 785.71 | W45: =SUM(W31-W36-W37) -> 3339.76 | X45: =SUM(X31-X36-X37) -> 3279.76 | Y45: =SUM(Y31-Y36-Y37) -> 3279.76 | Z45: =SUM(Z31-Z36-Z37) -> 3252.61 | AA45: =SUM(AA31-AA36-AA37) -> 3252.61 | AB45: =SUM(AB31-AB36-AB37) -> 3252.61 | ... AF45: =SUM(AF31-AF36-AF37) -> 0
A46: PL(円)
A47: PL(ドル)

Sheet 1001Lorimer
A1: 1001 Lorimer St, Brooklyn | B1: 2024 | C1: 45412 | D1: 45443 | E1: 45473 | F1: 45504 | G1: 2025 | H1: 45535 | I1: 45565 | J1: 45596 | K1: 45626 | L1: 45657 | M1: 45688 | N1: 45716 | O1: 45747 | P1: 45777 | Q1: 45808 | R1: 45838 | S1: 45869 | T1: 2026 | U1: 45900 | V1: 45930 | W1: 45961 | X1: 45991 | Y1: 46022 | Z1: 46053 | AA1: 46081 | AB1: 46112 | AC1: 46142 | AD1: 46173 | AE1: 46203 | AF1: 46234
A2: 取得簿価(円) | B2: =B3*150 -> 885000000
A3: 取得簿価(ドル) | B3: 5900000
A4: 賃料収入(円) | B4: =B5*B6 -> 4500000 | F4: =F5*F6 -> 0 | H4: =H5*H6 -> 0 | I4: =I5*I6 -> 0 | J4: =J5*J6 -> 0 | K4: =K5*K6 -> 0 | L4: =L5*L6 -> 0 | M4: =M5*M6 -> 2465898.1 | N4: =N5*N6 -> 4939110 | O4: =O5*O6 -> 2990400 | ... S4: =S5*S6 -> 4482118.3 | U4: =U5*U6 -> 4407987.9 | V4: =V5*V6 -> 4466791.6 | W4: =W5*W6 -> 4623431.5 | X4: =X5*X6 -> 4699326 | Y4: =Y5*Y6 -> 4697171 | Z4: =Z5*Z6 -> 4610259.4 | AA4: =AA5*AA6 -> 4674695.8 | AB4: =AB5*AB6 -> 5036688.4 | ... AF4: =AF5*AF6 -> 0
A5: 為替レート(ドル円)TTM | B5: ='NY不動産(総計)'!B5 -> 150 | C5: ='NY不動産(総計)'!C5 -> 156.9 | D5: ='NY不動産(総計)'!D5 -> 156.74 | E5: ='NY不動産(総計)'!E5 -> 161.07 | F5: ='NY不動産(総計)'!F5 -> 152.44 | H5: ='NY不動産(総計)'!H5 -> 144.8 | I5: ='NY不動産(総計)'!I5 -> 142.73 | J5: ='NY不動産(総計)'!J5 -> 153.64 | K5: ='NY不動産(総計)'!K5 -> 150.74 | L5: ='NY不動産(総計)'!L5 -> 158.18 | M5: ='NY不動産(総計)'!M5 -> 154.43 | N5: ='NY不動産(総計)'!N5 -> 149.67 | O5: ='NY不動産(総計)'!O5 -> 149.52 | ... S5: ='NY不動産(総計)'!S5 -> 149.39 | U5: ='NY不動産(総計)'!U5 -> 146.92 | V5: ='NY不動産(総計)'!V5 -> 148.88 | W5: ='NY不動産(総計)'!W5 -> 154.1 | X5: ='NY不動産(総計)'!X5 -> 156.63 | Y5: ='NY不動産(総計)'!Y5 -> 156.56 | Z5: ='NY不動産(総計)'!Z5 -> 153.66 | AA5: ='NY不動産(総計)'!AA5 -> 155.81 | AB5: ='NY不動産(総計)'!AB5 -> 159.88 | ... AF5: ='NY不動産(総計)'!AF5 -> 0
A6: 賃料収入(ドル) | B6: 30000 | M6: 15967.74 | N6: 33000 | O6: 20000 | P6: 26002.19 | Q6: 30002.81 | R6: 30002.63 | S6: 30002.8 | U6: 30002.64 | V6: 30002.63 | W6: 30002.8 | X6: 30002.72 | Y6: 30002.37 | Z6: 30002.99 | AA6: 30002.54 | AB6: 31502.93
A7: 減価償却費(円) | B7: 818326168 | M7: 17048463 | N7: 17048461 | O7: 17048461 | P7: 17048461 | Q7: 17048461 | R7: 17048461 | S7: 17048464 | U7: 17048461 | V7: 17048461 | W7: 17048461 | X7: 17048461 | Y7: 17048461 | Z7: 17048466 | AA7: 17048461 | AB7: 17048461 | AC7: 17048461 | AD7: 17048461 | AE7: 17048461 | AF7: 17048466
A8: 減価償却費(ドル)
A9: 残存簿価(円) | B9: 818326168 | M9: =B9-M7 -> 801277705 | N9: =M9-N7 -> 784229244 | O9: =N9-O7 -> 767180783 | P9: =O9-P7 -> 750132322 | Q9: =P9-Q7 -> 733083861 | R9: =Q9-R7 -> 716035400 | S9: =R9-S7 -> 698986936 | U9: =S9-U7 -> 681938475 | V9: =U9-V7 -> 664890014 | W9: =V9-W7 -> 647841553 | X9: =W9-X7 -> 630793092 | Y9: =X9-Y7 -> 613744631 | Z9: =Y9-Z7 -> 596696165 | AA9: =Z9-AA7 -> 579647704 | AB9: =AA9-AB7 -> 562599243 | AC9: =AB9-AC7 -> 545550782 | ... AF9: =AE9-AF7 -> 494405394
A10: 残存簿価(ドル)
A11: 管理費(ドル) | M11: 813.7 | N11: 1550 | O11: 1200 | P11: 1500 | Q11: 1500 | R11: 1500 | S11: 1500 | U11: 1500 | V11: 1500 | W11: 1500 | X11: 1500 | Y11: 1500 | Z11: 1500 | AA11: 1500 | AB11: 1575 | AG11: =SUM(C36:AF36) -> 21638.7 | AH11: 管理費
A12: 諸経費(税金、募集経費等)(ドル) | B12: 354417.72 | M12: 124.52 | N12: 10561.65 | O12: 10335.85 | P12: 17211.03 | Q12: 1185.8 | R12: 14627.06 | S12: 4142.89 | U12: 3631.81 | V12: 1546.45 | W12: 18337.44 | X12: 1130.16 | Y12: 1478.69 | Z12: 14313.43 | AA12: 9843.61 | AB12: 23872.07 | AG12: 0 | AH12: コモンチャージ
A13: ネット賃貸収入利回り(円) | AG13: 12443.46 | AH13: 固定資産税
A14: ネット賃貸収入利回り(ドル) | AG14: 45745.34 | AH14: 修繕・雑費・その他支出
A15: 取得時簿価利回り(円) | B15: =B13/B2 -> 0 | AG15: =SUM(AG11:AG14) -> 79827.5 | AH15: 合計
A16: 取得時簿価利回り(ドル)
A17: 残存簿価利回り(円) | B17: =B13/B9 -> 0
A18: 残存簿価利回り(ドル)
A19: CF(円) | C19: =SUM(C5*C20) -> 0 | D19: =SUM(D5*D20) -> 0 | E19: =SUM(E5*E20) -> 0 | F19: =SUM(F5*F20) -> 0 | H19: =SUM(H5*H20) -> 0 | I19: =SUM(I5*I20) -> 0 | J19: =SUM(J5*J20) -> 0 | K19: =SUM(K5*K20) -> 0 | L19: =SUM(L5*L20) -> 0 | M19: =SUM(M5*M20) -> 2321008.8 | N19: =SUM(N5*N20) -> 3126359.3 | O19: =SUM(O5*O20) -> 1265559.7 | ... S19: =SUM(S5*S20) -> 3639127 | U19: =SUM(U5*U20) -> 3654022.3 | V19: =SUM(V5*V20) -> 4013236.1 | W19: =SUM(W5*W20) -> 1566482 | X19: =SUM(X5*X20) -> 4287364.1 | Y19: =SUM(Y5*Y20) -> 4230827.3 | Z19: =SUM(Z5*Z20) -> 2180367.8 | AA19: =SUM(AA5*AA20) -> 2907247.9 | AB19: =SUM(AB5*AB20) -> 968210.9 | ... AF19: =SUM(AF5*AF20) -> 0
A20: CF(ドル) | C20: =SUM(C6-C11-C12) -> 0 | D20: =SUM(D6-D11-D12) -> 0 | E20: =SUM(E6-E11-E12) -> 0 | F20: =SUM(F6-F11-F12) -> 0 | H20: =SUM(H6-H11-H12) -> 0 | I20: =SUM(I6-I11-I12) -> 0 | J20: =SUM(J6-J11-J12) -> 0 | K20: =SUM(K6-K11-K12) -> 0 | L20: =SUM(L6-L11-L12) -> 0 | M20: =SUM(M6-M11-M12) -> 15029.52 | N20: =SUM(N6-N11-N12) -> 20888.35 | O20: =SUM(O6-O11-O12) -> 8464.15 | ... S20: =SUM(S6-S11-S12) -> 24359.91 | U20: =SUM(U6-U11-U12) -> 24870.83 | V20: =SUM(V6-V11-V12) -> 26956.18 | W20: =SUM(W6-W11-W12) -> 10165.36 | X20: =SUM(X6-X11-X12) -> 27372.56 | Y20: =SUM(Y6-Y11-Y12) -> 27023.68 | Z20: =SUM(Z6-Z11-Z12) -> 14189.56 | AA20: =SUM(AA6-AA11-AA12) -> 18658.93 | AB20: =SUM(AB6-AB11-AB12) -> 6055.86 | ... AF20: =SUM(AF6-AF11-AF12) -> 0
A21: PL(円)
A22: PL(ドル)
A24: 購入日 | B24: 45674
A25: 下記表は固都税を各月の諸経費に分散して計上した表です
A26: 1001 Lorimer St, Brooklyn | B26: 2024 | C26: 45412 | D26: 45443 | E26: 45473 | F26: 45504 | G26: 2025 | H26: 45535 | I26: 45565 | J26: 45596 | K26: 45626 | L26: 45657 | M26: 45688 | N26: 45716 | O26: 45747 | P26: 45777 | Q26: 45808 | R26: 45838 | S26: 45869 | T26: 2026 | U26: 45900 | V26: 45930 | W26: 45961 | X26: 45991 | Y26: 46022 | Z26: 46053 | AA26: 46081 | AB26: 46112 | AC26: 46142 | AD26: 46173 | AE26: 46203 | AF26: 46234
A27: 取得簿価(円) | B27: =B28*150 -> 885000000
A28: 取得簿価(ドル) | B28: 5900000
A29: 賃料収入(円) | B29: =B30*B31 -> 4500000 | F29: =F30*F31 -> 0 | H29: =H30*H31 -> 0 | I29: =I30*I31 -> 0 | J29: =J30*J31 -> 0 | K29: =K30*K31 -> 0 | L29: =L30*L31 -> 0 | M29: =M30*M31 -> 2465898.1 | N29: =N30*N31 -> 4939110 | O29: =O30*O31 -> 2990400 | ... S29: =S30*S31 -> 4482118.3 | U29: =U30*U31 -> 4407987.9 | V29: =V30*V31 -> 4466791.6 | W29: =W30*W31 -> 4623431.5 | X29: =X30*X31 -> 4699326 | Y29: =Y30*Y31 -> 4697171 | Z29: =Z30*Z31 -> 4610259.4 | AA29: =AA30*AA31 -> 4674695.8 | AB29: =AB30*AB31 -> 5036688.4 | ... AF29: =AF30*AF31 -> 0
A30: 為替レート(ドル円)TTM | B30: ='NY不動産(総計)'!B30 -> 150 | C30: ='NY不動産(総計)'!C30 -> 156.9 | D30: ='NY不動産(総計)'!D30 -> 156.74 | E30: ='NY不動産(総計)'!E30 -> 161.07 | F30: ='NY不動産(総計)'!F30 -> 152.44 | H30: ='NY不動産(総計)'!H30 -> 144.8 | I30: ='NY不動産(総計)'!I30 -> 142.73 | J30: ='NY不動産(総計)'!J30 -> 153.64 | K30: ='NY不動産(総計)'!K30 -> 150.74 | L30: ='NY不動産(総計)'!L30 -> 158.18 | M30: ='NY不動産(総計)'!M30 -> 154.43 | N30: ='NY不動産(総計)'!N30 -> 149.67 | O30: ='NY不動産(総計)'!O30 -> 149.52 | ... S30: ='NY不動産(総計)'!S30 -> 149.39 | U30: ='NY不動産(総計)'!U30 -> 146.92 | V30: ='NY不動産(総計)'!V30 -> 148.88 | W30: ='NY不動産(総計)'!W30 -> 154.1 | X30: ='NY不動産(総計)'!X30 -> 156.63 | Y30: ='NY不動産(総計)'!Y30 -> 156.56 | Z30: ='NY不動産(総計)'!Z30 -> 153.66 | AA30: ='NY不動産(総計)'!AA30 -> 155.81 | AB30: ='NY不動産(総計)'!AB30 -> 159.88 | ... AF30: ='NY不動産(総計)'!AF30 -> 0
A31: 賃料収入(ドル) | B31: 30000 | M31: 15967.74 | N31: 33000 | O31: 20000 | P31: 26002.19 | Q31: 30002.81 | R31: 30002.63 | S31: 30002.8 | U31: 30002.64 | V31: 30002.63 | W31: 30002.8 | X31: 30002.72 | Y31: 30002.37 | Z31: 30002.99 | AA31: 30002.54 | AB31: 31502.93
A32: 減価償却費(円) | B32: 818326168 | M32: 17048463 | N32: 17048461 | O32: 17048461 | P32: 17048461 | Q32: 17048461 | R32: 17048461 | S32: 17048464 | U32: 17048461 | V32: 17048461 | W32: 17048461 | X32: 17048461 | Y32: 17048461 | Z32: 17048466 | AA32: 17048461 | AB32: 17048461 | AC32: 17048461 | AD32: 17048461 | AE32: 17048461 | AF32: 17048466
A33: 減価償却費(ドル)
A34: 残存簿価(円) | B34: 818326168 | M34: =B34-M32 -> 801277705 | N34: =M34-N32 -> 784229244 | O34: =N34-O32 -> 767180783 | P34: =O34-P32 -> 750132322 | Q34: =P34-Q32 -> 733083861 | R34: =Q34-R32 -> 716035400 | S34: =R34-S32 -> 698986936 | U34: =S34-U32 -> 681938475 | V34: =U34-V32 -> 664890014 | W34: =V34-W32 -> 647841553 | X34: =W34-X32 -> 630793092 | Y34: =X34-Y32 -> 613744631 | Z34: =Y34-Z32 -> 596696165 | AA34: =Z34-AA32 -> 579647704 | AB34: =AA34-AB32 -> 562599243 | AC34: =AB34-AC32 -> 545550782 | ... AF34: =AE34-AF32 -> 494405394
A35: 残存簿価(ドル)
A36: 管理費(ドル) | M36: 813.7 | N36: 1550 | O36: 1200 | P36: 1500 | Q36: 1500 | R36: 1500 | S36: 1500 | U36: 1500 | V36: 1500 | W36: 1500 | X36: 1500 | Y36: 1500 | Z36: 1500 | AA36: 1500 | AB36: 1575
A37: 諸経費(税金、募集経費等)(ドル) | B37: 354417.72 | M37: 124.52 | N37: 10887.65 | O37: 10335.85 | P37: 15651.39 | Q37: 1965.62 | R37: 6144.88 | S37: 4984.89 | U37: 4473.81 | V37: 2388.45 | W37: 19179.44 | X37: 1972.16 | Y37: 2320.69 | Z37: 15155.43 | AA37: 10685.61 | AB37: 842 | AC37: 842 | AD37: 842
A38: ネット賃貸収入利回り(円)
A39: ネット賃貸収入利回り(ドル)
A40: 取得時簿価利回り(円) | B40: =B38/B27 -> 0
A41: 取得時簿価利回り(ドル)
A42: 残存簿価利回り(円) | B42: =B38/B34 -> 0
A43: 残存簿価利回り(ドル)
A44: CF(円) | C44: =SUM(C30*C45) -> 0 | D44: =SUM(D30*D45) -> 0 | E44: =SUM(E30*E45) -> 0 | F44: =SUM(F30*F45) -> 0 | H44: =SUM(H30*H45) -> 0 | I44: =SUM(I30*I45) -> 0 | J44: =SUM(J30*J45) -> 0 | K44: =SUM(K30*K45) -> 0 | L44: =SUM(L30*L45) -> 0 | M44: =SUM(M30*M45) -> 2321008.8 | N44: =SUM(N30*N45) -> 3077566.9 | O44: =SUM(O30*O45) -> 1265559.7 | ... S44: =SUM(S30*S45) -> 3513340.6 | U44: =SUM(U30*U45) -> 3530315.7 | V44: =SUM(V30*V45) -> 3887879.1 | W44: =SUM(W30*W45) -> 1436729.8 | X44: =SUM(X30*X45) -> 4155481.6 | Y44: =SUM(Y30*Y45) -> 4099003.8 | Z44: =SUM(Z30*Z45) -> 2050986.1 | AA44: =SUM(AA30*AA45) -> 2776055.9 | AB44: =SUM(AB30*AB45) -> 4650258.5 | ... AF44: =SUM(AF30*AF45) -> 0
A45: CF(ドル) | C45: =SUM(C31-C36-C37) -> 0 | D45: =SUM(D31-D36-D37) -> 0 | E45: =SUM(E31-E36-E37) -> 0 | F45: =SUM(F31-F36-F37) -> 0 | H45: =SUM(H31-H36-H37) -> 0 | I45: =SUM(I31-I36-I37) -> 0 | J45: =SUM(J31-J36-J37) -> 0 | K45: =SUM(K31-K36-K37) -> 0 | L45: =SUM(L31-L36-L37) -> 0 | M45: =SUM(M31-M36-M37) -> 15029.52 | N45: =SUM(N31-N36-N37) -> 20562.35 | O45: =SUM(O31-O36-O37) -> 8464.15 | ... S45: =SUM(S31-S36-S37) -> 23517.91 | U45: =SUM(U31-U36-U37) -> 24028.83 | V45: =SUM(V31-V36-V37) -> 26114.18 | W45: =SUM(W31-W36-W37) -> 9323.36 | X45: =SUM(X31-X36-X37) -> 26530.56 | Y45: =SUM(Y31-Y36-Y37) -> 26181.68 | Z45: =SUM(Z31-Z36-Z37) -> 13347.56 | AA45: =SUM(AA31-AA36-AA37) -> 17816.93 | AB45: =SUM(AB31-AB36-AB37) -> 29085.93 | ... AF45: =SUM(AF31-AF36-AF37) -> 0
A46: PL(円)
A47: PL(ドル)
R50: 10104.01
R51: 842.01
R52: 842
R53: 842
R54: 842
R55: 842
R56: 842
R57: 842
R58: 842
R59: 842
R60: 842
R61: 842
R62: 842
R63: =SUM(R51:R62) -> 10104.01

Sheet 248-250W102nd
A1: 248-250 W 102nd St, NY | B1: 2024 | C1: 45412 | D1: 45443 | E1: 45473 | F1: 45504 | G1: 2025 | H1: 45535 | I1: 45565 | J1: 45596 | K1: 45626 | L1: 45657 | M1: 45688 | N1: 45716 | O1: 45747 | P1: 45777 | Q1: 45808 | R1: 45838 | S1: 45869 | T1: 2026 | U1: 45900 | V1: 45930 | W1: 45961 | X1: 45991 | Y1: 46022 | Z1: 46053 | AA1: 46081 | AB1: 46112 | AC1: 46142 | AD1: 46173 | AE1: 46203 | AF1: 46234
A2: 取得簿価(円) | B2: =B3*150 -> 1350000000
A3: 取得簿価(ドル) | B3: 9000000
A4: 賃料収入(円) | B4: =B5*B6 -> 9596112 | F4: =F5*F6 -> 0 | H4: =H5*H6 -> 0 | I4: =I5*I6 -> 0 | J4: =J5*J6 -> 0 | K4: =K5*K6 -> 0 | L4: =L5*L6 -> 0 | M4: =M5*M6 -> 0 | N4: =N5*N6 -> 0 | O4: =O5*O6 -> 0 | ... S4: =S5*S6 -> 8618917.1 | U4: =U5*U6 -> 7416630.3 | V4: =V5*V6 -> 7266596.1 | W4: =W5*W6 -> 9435954.4 | X4: =X5*X6 -> 9848712.7 | Y4: =Y5*Y6 -> 8779516.9 | Z4: =Z5*Z6 -> 9164053.4 | AA4: =AA5*AA6 -> 10020566 | AB4: =AB5*AB6 -> 8168814.4 | ... AF4: =AF5*AF6 -> 0
A5: 為替レート(ドル円)TTM | B5: ='NY不動産(総計)'!B5 -> 150 | C5: ='NY不動産(総計)'!C5 -> 156.9 | D5: ='NY不動産(総計)'!D5 -> 156.74 | E5: ='NY不動産(総計)'!E5 -> 161.07 | F5: ='NY不動産(総計)'!F5 -> 152.44 | H5: ='NY不動産(総計)'!H5 -> 144.8 | I5: ='NY不動産(総計)'!I5 -> 142.73 | J5: ='NY不動産(総計)'!J5 -> 153.64 | K5: ='NY不動産(総計)'!K5 -> 150.74 | L5: ='NY不動産(総計)'!L5 -> 158.18 | M5: ='NY不動産(総計)'!M5 -> 154.43 | N5: ='NY不動産(総計)'!N5 -> 149.67 | O5: ='NY不動産(総計)'!O5 -> 149.52 | ... S5: ='NY不動産(総計)'!S5 -> 149.39 | U5: ='NY不動産(総計)'!U5 -> 146.92 | V5: ='NY不動産(総計)'!V5 -> 148.88 | W5: ='NY不動産(総計)'!W5 -> 154.1 | X5: ='NY不動産(総計)'!X5 -> 156.63 | Y5: ='NY不動産(総計)'!Y5 -> 156.56 | Z5: ='NY不動産(総計)'!Z5 -> 153.66 | AA5: ='NY不動産(総計)'!AA5 -> 155.81 | AB5: ='NY不動産(総計)'!AB5 -> 159.88 | ... AF5: ='NY不動産(総計)'!AF5 -> 0
A6: 賃料収入(ドル) | B6: 63974.08 | Q6: 26149.74 | R6: 49588.88 | S6: 57694.07 | U6: 50480.74 | V6: 48808.41 | W6: 61232.67 | X6: 62878.84 | Y6: 56077.65 | Z6: 59638.51 | AA6: 64312.73 | AB6: 51093.41
A7: 減価償却費(円) | B7: 975722914 | Q7: 11627364 | R7: 11627364 | S7: 11627365 | U7: 11627364 | V7: 11627364 | W7: 11627364 | X7: 11627364 | Y7: 11627364 | Z7: 11627367 | AA7: 11627364 | AB7: 11627364 | AC7: 11627364 | AD7: 11627364 | AE7: 11627364 | AF7: 11627369
A8: 減価償却費(ドル)
A9: 残存簿価(円) | B9: 975722914 | Q9: =B9-Q7 -> 964095550 | R9: =Q9-R7 -> 952468186 | S9: =R9-S7 -> 940840821 | U9: =S9-U7 -> 929213457 | V9: =U9-V7 -> 917586093 | W9: =V9-W7 -> 905958729 | X9: =W9-X7 -> 894331365 | Y9: =X9-Y7 -> 882704001 | Z9: =Y9-Z7 -> 871076634 | AA9: =Z9-AA7 -> 859449270 | AB9: =AA9-AB7 -> 847821906 | AC9: =AB9-AC7 -> 836194542 | ... AF9: =AE9-AF7 -> 801312445 | AI9: PURCHASER | AJ9: SELLER
A10: 残存簿価(ドル)
A11: 管理費(ドル) | Q11: 1307.49 | R11: 2479.27 | S11: 2884.37 | U11: 2341.3 | V11: 2440.21 | W11: 2951.4 | X11: 3088.46 | Y11: 1463.39 | Z11: 2862.62 | AA11: 2981.66 | AB11: 3256.37 | AG11: =SUM(C36:AF36) -> 28056.54 | AH11: 管理費 | AI11: 12852 | AJ11: 6335.14
A12: 諸経費(税金、募集経費等)(ドル) | B12: 264881.43 | Q12: -70 | R12: 34155.72 | S12: 136327.59 | U12: 21050.66 | V12: 8821.26 | W12: 17258.22 | X12: 16179.27 | Y12: 19748.45 | Z12: 15743.72 | AA12: 12896.03 | AB12: 10572.58 | AG12: 0 | AH12: コモンチャージ | AI12: 13297.74 | AJ12: 9036.13
A13: ネット賃貸収入利回り(円) | AG13: 119513.83 | AH13: 固定資産税 | AI13: 23756.57 | AJ13: 63.29
A14: ネット賃貸収入利回り(ドル) | AG14: 50899.48 | AH14: 修繕・雑費・その他支出 | AI14: 25021.35 | AJ14: 11.99
A15: 取得時簿価利回り(円) | B15: =B13/B2 -> 0 | AG15: =SUM(AG11:AG14) -> 198469.85 | AH15: 合計 | AI15: 103.66 | AJ15: 434.9
A16: 取得時簿価利回り(ドル) | AI16: 185
A17: 残存簿価利回り(円) | B17: =B13/B9 -> 0 | AI17: 7.61
A18: 残存簿価利回り(ドル) | AI18: =SUM(AI10:AI17) -> 75223.93 | AJ18: =SUM(AJ10:AJ17) -> 15881.45 | AK18: =AJ18+AJ27-AI18 -> 238731.69
A19: CF(円) | C19: =SUM(C5*C20) -> 0 | D19: =SUM(D5*D20) -> 0 | E19: =SUM(E5*E20) -> 0 | F19: =SUM(F5*F20) -> 0 | H19: =SUM(H5*H20) -> 0 | I19: =SUM(I5*I20) -> 0 | J19: =SUM(J5*J20) -> 0 | K19: =SUM(K5*K20) -> 0 | L19: =SUM(L5*L20) -> 0 | M19: =SUM(M5*M20) -> 0 | N19: =SUM(N5*N20) -> 0 | O19: =SUM(O5*O20) -> 0 | ... S19: =SUM(S5*S20) -> -12177958 | U19: =SUM(U5*U20) -> 3979883.6 | V19: =SUM(V5*V20) -> 5589988.4 | W19: =SUM(W5*W20) -> 6321652 | X19: =SUM(X5*X20) -> 6830808.2 | Y19: =SUM(Y5*Y20) -> 5458591.2 | Z19: =SUM(Z5*Z20) -> 6305003.2 | AA19: =SUM(AA5*AA20) -> 7546663.6 | AB19: =SUM(AB5*AB20) -> 5957841.9 | ... AF19: =SUM(AF5*AF20) -> 0
A20: CF(ドル) | C20: =SUM(C6-C11-C12) -> 0 | D20: =SUM(D6-D11-D12) -> 0 | E20: =SUM(E6-E11-E12) -> 0 | F20: =SUM(F6-F11-F12) -> 0 | H20: =SUM(H6-H11-H12) -> 0 | I20: =SUM(I6-I11-I12) -> 0 | J20: =SUM(J6-J11-J12) -> 0 | K20: =SUM(K6-K11-K12) -> 0 | L20: =SUM(L6-L11-L12) -> 0 | M20: =SUM(M6-M11-M12) -> 0 | N20: =SUM(N6-N11-N12) -> 0 | O20: =SUM(O6-O11-O12) -> 0 | ... S20: =SUM(S6-S11-S12) -> -81517.89 | U20: =SUM(U6-U11-U12) -> 27088.78 | V20: =SUM(V6-V11-V12) -> 37546.94 | W20: =SUM(W6-W11-W12) -> 41023.05 | X20: =SUM(X6-X11-X12) -> 43611.11 | Y20: =SUM(Y6-Y11-Y12) -> 34865.81 | Z20: =SUM(Z6-Z11-Z12) -> 41032.17 | AA20: =SUM(AA6-AA11-AA12) -> 48435.04 | AB20: =SUM(AB6-AB11-AB12) -> 37264.46 | ... AF20: =SUM(AF6-AF11-AF12) -> 0 | AJ20: 32626.25
A21: PL(円) | AJ21: 23756.57
A22: PL(ドル) | AJ22: 25021.35
A23: 購入日 | B23: 45792 | AJ23: 1170
AJ24: 180000
A25: 下記表は固都税を各月の諸経費に分散して計上した表です | AJ25: 400
A26: 248-250 W 102nd St, NY | B26: 2024 | C26: 45412 | D26: 45443 | E26: 45473 | F26: 45504 | G26: 2025 | H26: 45535 | I26: 45565 | J26: 45596 | K26: 45626 | L26: 45657 | M26: 45688 | N26: 45716 | O26: 45747 | P26: 45777 | Q26: 45808 | R26: 45838 | S26: 45869 | T26: 2026 | U26: 45900 | V26: 45930 | W26: 45961 | X26: 45991 | Y26: 46022 | Z26: 46053 | AA26: 46081 | AB26: 46112 | AC26: 46142 | AD26: 46173 | AE26: 46203 | AF26: 46234 | AJ26: 35100
A27: 取得簿価(円) | B27: =B28*150 -> 1350000000 | AJ27: =SUM(AJ20:AJ26) -> 298074.17
A28: 取得簿価(ドル) | B28: 9000000
A29: 賃料収入(円) | B29: =B30*B31 -> 0 | F29: =F30*F31 -> 0 | H29: =H30*H31 -> 0 | I29: =I30*I31 -> 0 | J29: =J30*J31 -> 0 | K29: =K30*K31 -> 0 | L29: =L30*L31 -> 0 | M29: =M30*M31 -> 0 | N29: =N30*N31 -> 0 | O29: =O30*O31 -> 0 | ... S29: =S30*S31 -> 8618917.1 | U29: =U30*U31 -> 7416630.3 | V29: =V30*V31 -> 7266596.1 | W29: =W30*W31 -> 9435954.4 | X29: =X30*X31 -> 9848712.7 | Y29: =Y30*Y31 -> 8779516.9 | Z29: =Z30*Z31 -> 9164053.4 | AA29: =AA30*AA31 -> 10020566 | AB29: =AB30*AB31 -> 8168814.4 | ... AF29: =AF30*AF31 -> 0
A30: 為替レート(ドル円)TTM | B30: ='NY不動産(総計)'!B30 -> 150 | C30: ='NY不動産(総計)'!C30 -> 156.9 | D30: ='NY不動産(総計)'!D30 -> 156.74 | E30: ='NY不動産(総計)'!E30 -> 161.07 | F30: ='NY不動産(総計)'!F30 -> 152.44 | H30: ='NY不動産(総計)'!H30 -> 144.8 | I30: ='NY不動産(総計)'!I30 -> 142.73 | J30: ='NY不動産(総計)'!J30 -> 153.64 | K30: ='NY不動産(総計)'!K30 -> 150.74 | L30: ='NY不動産(総計)'!L30 -> 158.18 | M30: ='NY不動産(総計)'!M30 -> 154.43 | N30: ='NY不動産(総計)'!N30 -> 149.67 | O30: ='NY不動産(総計)'!O30 -> 149.52 | ... S30: ='NY不動産(総計)'!S30 -> 149.39 | U30: ='NY不動産(総計)'!U30 -> 146.92 | V30: ='NY不動産(総計)'!V30 -> 148.88 | W30: ='NY不動産(総計)'!W30 -> 154.1 | X30: ='NY不動産(総計)'!X30 -> 156.63 | Y30: ='NY不動産(総計)'!Y30 -> 156.56 | Z30: ='NY不動産(総計)'!Z30 -> 153.66 | AA30: ='NY不動産(総計)'!AA30 -> 155.81 | AB30: ='NY不動産(総計)'!AB30 -> 159.88 | ... AF30: ='NY不動産(総計)'!AF30 -> 0
A31: 賃料収入(ドル) | Q31: 26149.74 | R31: 49588.88 | S31: 57694.07 | U31: 50480.74 | V31: 48808.41 | W31: 61232.67 | X31: 62878.84 | Y31: 56077.65 | Z31: 59638.51 | AA31: 64312.73 | AB31: 51093.41
A32: 減価償却費(円) | B32: 975722914 | Q32: 11627364 | R32: 11627364 | S32: 11627365 | U32: 11627364 | V32: 11627364 | W32: 11627364 | X32: 11627364 | Y32: 11627364 | Z32: 11627367 | AA32: 11627364 | AB32: 11627364 | AC32: 11627364 | AD32: 11627364 | AE32: 11627364 | AF32: 11627369
A33: 減価償却費(ドル)
A34: 残存簿価(円) | B34: 975722914 | Q34: =B34-Q32 -> 964095550 | R34: =Q34-R32 -> 952468186 | S34: =R34-S32 -> 940840821 | U34: =S34-U32 -> 929213457 | V34: =U34-V32 -> 917586093 | W34: =V34-W32 -> 905958729 | X34: =W34-X32 -> 894331365 | Y34: =X34-Y32 -> 882704001 | Z34: =Y34-Z32 -> 871076634 | AA34: =Z34-AA32 -> 859449270 | AB34: =AA34-AB32 -> 847821906 | AC34: =AB34-AC32 -> 836194542 | ... AF34: =AE34-AF32 -> 801312445
A35: 残存簿価(ドル)
A36: 管理費(ドル) | Q36: 1307.49 | R36: 2479.27 | S36: 2884.37 | U36: 2341.3 | V36: 2440.21 | W36: 2951.4 | X36: 3088.46 | Y36: 1463.39 | Z36: 2862.62 | AA36: 2981.66 | AB36: 3256.37 | AG36: 248
A37: 諸経費(税金、募集経費等)(ドル) | B37: 264881.43 | Q37: -70 | R37: 34155.72 | S37: 26773.31 | U37: 31010.14 | V37: 18780.74 | W37: 27217.7 | X37: 26138.75 | Y37: 29707.93 | Z37: 25703.2 | AA37: 22855.51 | AB37: 9959.48 | AC37: 9959.48 | AD37: 9959.48 | AE37: 9959.48 | AG37: 維持管理：3,337.69
A38: ネット賃貸収入利回り(円) | AG38: オイル：2,459.26
A39: ネット賃貸収入利回り(ドル) | AG39: ガス電気代：166.01
A40: 取得時簿価利回り(円) | B40: =B38/B27 -> 0 | AG40: 管理人フィー：750.00
A41: 取得時簿価利回り(ドル) | AG41: その他経費：2,010.48
A42: 残存簿価利回り(円) | B42: =B38/B34 -> 0 | AG42: レント更新料：200.00
A43: 残存簿価利回り(ドル) | AG43: 合計：8,923.44
A44: CF(円) | C44: =SUM(C30*C45) -> 0 | D44: =SUM(D30*D45) -> 0 | E44: =SUM(E30*E45) -> 0 | F44: =SUM(F30*F45) -> 0 | H44: =SUM(H30*H45) -> 0 | I44: =SUM(I30*I45) -> 0 | J44: =SUM(J30*J45) -> 0 | K44: =SUM(K30*K45) -> 0 | L44: =SUM(L30*L45) -> 0 | M44: =SUM(M30*M45) -> 0 | N44: =SUM(N30*N45) -> 0 | O44: =SUM(O30*O45) -> 0 | ... S44: =SUM(S30*S45) -> 4188356.3 | U44: =SUM(U30*U45) -> 2516636.8 | V44: =SUM(V30*V45) -> 4107221 | W44: =SUM(W30*W45) -> 4786896.1 | X44: =SUM(X30*X45) -> 5270854.8 | Y44: =SUM(Y30*Y45) -> 3899335 | Z44: =SUM(Z30*Z45) -> 4774629.5 | AA44: =SUM(AA30*AA45) -> 5994877 | AB44: =SUM(AB30*AB45) -> 6055864.3 | ... AF44: =SUM(AF30*AF45) -> 0
